Workbook

Sheet README
B2: KClinics Financial Model
B3: Built 2026-08-28 from the live K-Clinics catalogue + UK 2026 cost research. This workbook is the basis for refactoring pricing and cost structure for the brand — it does not touch the admin.
B5: HOW TO USE
B6: Blue text on a cream background = an input you edit. Everything else is a formula — change an input and the whole model (prices, energy, P&L) recalculates.
B7: The three levers that matter most: the utilisation ramp (Volumes, blue row), the target margins by machine class (Pricing, top), and the machinery purchase prices (Machinery — replace class-typical estimates with your invoices).
B9: TABS
B10: Assumptions — every global input with its source. • Machinery — machines, enhancements, depreciation & amortisation schedule. • Energy — seasonal A/C vs heating curve per room, base load, machine kWh, cost split. • Pricing — per-variant unit economics and recommended prices (the price architecture). • Volumes — capacity × utilisation × mix forecast. • P&L — 36 monthly columns + annual totals: gross profit, EBITDA, net profit. • Data — raw catalogue extract (audit trail).
B12: CONVENTIONS
B13: Gross profit = net revenue − variable direct costs (consumables, machine energy & service, card fees). Salaried staff are overheads. EBITDA excludes depreciation & amortisation, which are charged below it. Monthly corporation tax is a flat 19% accrual; the annual columns apply the real 2026/27 bands (19% / 26.5% marginal / 25%). AIA means cash tax in a capex year will be lower than the accrual — the accounting P&L still depreciates over asset life.
B14: VAT: the company is not VAT-registered. The P&L tracks rolling 12-month taxable turnover and switches VAT on the month after it crosses £90k (override on Assumptions). Prices are held constant at registration, so VAT comes out of margin — that is why the Pricing tab prices for the registered state by default.
B16: CATALOGUE ISSUES FOUND DURING EXTRACTION (fix in admin before publishing new prices)
B17: • Laser Skin Resurfacing: the 5-session course (£450) is cheaper than the 3-session course (£480).
... B41: Catalogue & bookings: live production DB (read-only) via authenticated admin scrape, 2026-08-28. Cost benchmarks: web research Aug 2026 — Ofgem/business tariff comparisons (energy), UK equipment vendors (machinery), UK clinic industry norms (staff, rent, marketing, insurance). Basis noted next to every assumption.

Sheet Assumptions
A1: Assumptions — every editable input in the model
A2: Blue on cream = edit me. Column D says where each number came from. Nothing else in the workbook is hardcoded.
A4: CLINIC & CAPACITY
A5: Model start month | B5: 46266 | C5: date | D5: First forecast month. Clinic re-opened 30 May 2026; model starts Sep 2026.
A6: Usable treatment rooms | B6: 9 | C6: rooms | D6: 11 active rooms in DB (3 Aesthetics, 2 Dental, 6 Treatment); 2 dental rooms excluded until dentistry launches (separate company). ESTIMATE — confirm dental rooms are not used as overflow.
A7: Rooms heated/cooled (HVAC) | B7: 9 | C7: rooms | D7: Rooms actively conditioned. Set to 11 if dental rooms are kept conditioned while mothballed.
A8: Open days per week | B8: 6 | C8: days | D8: Live booking hours imply ~57 open hours/week.
A9: Open hours per day | B9: 9.5 | C9: hours | D9: 57 open hours/week ÷ 6 days.
A10: Assumed room size | B10: 15 | C10: m² | D10: ASSUMPTION — no floor area in codebase or lease data. Drives the HVAC curve on the Energy tab.
A11: STAFFING
A12: Practitioner salary | B12: 41000 | C12: £/yr | D12: Glassdoor London aesthetic practitioner avg £41,155; skin & laser therapist UK avg £38,637, London upper half; hourly £14–£25
A13: Receptionist salary | B13: 27000 | C13: £/yr | D13: Indeed London £29,652 / PayScale £26,494; London private-clinic roles £24k–£30k
A14: Owner salary (market rate) | B14: 48000 | C14: £/yr | D14: GAP — owner remuneration undefined. £48k market-rate placeholder so owner labour is not modelled as free. Set to your actual salary/dividend policy.
A15: Employer on-cost multiplier | B15: 1.16 | C15: × | D15: 2026/27 employer NI 15% above £5,000 secondary threshold + 3% auto-enrolment pension on qualifying earnings (£6,240–£50,270) = ~15–17% on-cost for £25k–£45k staff; Employment Allowance can offset first £10,500 of NI if eligible
A16: Practitioners — headcount Y1 / Y2 / Y3 | B16: 2 | C16: 3 | D16: Y1 in column B, Y2 in column C, Y3 in column E. Defaults 2/3/5 track the default utilisation ramp. | E16: 5
A17: Receptionists — headcount Y1 / Y2 / Y3 | B17: 1 | C17: 1 | D17: Y1 in column B, Y2 in column C, Y3 in column E. | E17: 2
A18: Practitioner productive treatment hours/week | B18: 30 | C18: hrs | D18: Hours actually treating (vs admin/gaps) — drives labour cost per session in Pricing.
A19: Working weeks per year | B19: 46 | C19: wks | D19: 52 minus holiday/sickness/training.
A20: Loaded practitioner cost per treatment hour | B20: =Assumptions!$B$12*Assumptions!$B$15/(Assumptions!$B$19*Assumptions!$B$18) -> 34.463768 | C20: £/hr | D20: Calculated: salary × on-cost ÷ (working weeks × productive hours). Used in Pricing unit economics.
A21: Practitioner capacity per month | B21: =Assumptions!$B$18*Assumptions!$B$19/12 -> 115 | C21: hrs/mo | D21: Per practitioner FTE — used by the P&L capacity check.
A22: ENERGY
A23: Electricity unit rate | B23: 27 | C23: p/kWh | D23: Aug 2026 UK small-business market: AquaSwitch/BusinessEnergyDeals average ~29.6p, competitive fixed deals 20–23p; Ofgem Jul–Sep 2026 domestic cap 26.11p cross-check. 27p chosen as central figure for a micro-business on a 2026 fixed deal; small businesses pay 20% VAT on energy unless <33 kWh/day.
A24: Standing charge | B24: 55 | C24: p/day | D24: BusinessEnergyDeals/AquaSwitch Aug 2026: average 55.3p/day small business, supplier range 34.7–105.9p.
A25: Base load (lighting, fridge, autoclave, PCs) | B25: 12 | C25: kWh/day | D25: Bottom-up: LED lighting 5–8 kWh, autoclave cycles 2–4 kWh, medical/skincare fridge 1.5–3 kWh (24/7), PCs/screens/kiosk 1.5–3 kWh, misc 1–3 kWh. Consistent with Ofgem micro-business band (5,000–15,000 kWh/yr) minus HVAC.
A26: Heating & cooling | B26: see Energy tab | D26: NO GAS MODELLED — 4 Charterhouse Buildings (converted Clerkenwell building) assumed all-electric per CIBSE TM46 'general retail' zero fossil-thermal convention; heating via reverse-cycle splits at COP 3 on the electricity tariff. Confirm no gas meter on the lease (gap). Seasonal per-room kWh curve is editable on the Energy tab.
A27: PROPERTY
A28: Rent | B28: 64000 | C28: £/yr | D28: NO FLOOR AREA IN CODEBASE. Placeholder = 2,000 sqft x £32/sqft. Goswell Rd EC1M comparables Aug 2026: £27–£34/sqft (1,283 sqft at £35k pa; 972 sqft at £2,750/mo); Charterhouse Buildings is secondary frontage — use £30–£35/sqft, NOT prime Clerkenwell £50+. An 11-room clinic implies roughly 1,800–3,000 sqft; get the actual lease figure (gap).
A29: Business rates | B29: 11500 | C29: £/yr | D29: RV unknown — check VOA. 2026/27 RHL small multiplier 38.2p/£ (RV<£51k) if retail/hospitality/leisure status granted; general small multiplier 48p otherwise; RV ≤ £12k = nil via Small Business Rate Relief. Placeholder assumes RV ~£30k x 38.2p.
A30: Service charge / building costs | B30: 0 | C30: £/yr | D30: Unknown — set from the lease.
A31: OTHER OVERHEADS
A32: Insurance (treatment risk + PL + laser cover) | B32: 1500 | C32: £/yr | D32: Hamilton Fraser/PolicyBee: PI+PL from £300–£600; £1m treatment liability incl. laser/IPL from £573; device-based laser cover adds £500–£2,000. Laser-led clinic with employed staff typically £1,000–£3,000. Laser claims are ~half of insurer claims (avg payout £4,307) — do not skimp.
A33: Platform hosting & infra | B33: 50 | C33: £/mo | D33: OVERRIDES the £100/mo benchmark: K-Clinics runs its OWN booking/CRM/admin platform (this repo, Vercel + Postgres/Neon) — no third-party licence. Line = hosting/infra: Vercel Pro ~£16/mo + Neon + email/VoIP (yay.com) + AI API usage, ~£30–£100/mo. Flag: developer/maintenance time is an unmodelled cost (gap).
A34: Card processing fee | B34: 0.017 | C34: % of card takings | D34: UK SMB blended 2026: SumUp 1.69%/Square 1.75% in-person, 2.5% online/payment links. Stripe card-on-file (SetupIntent) flow in use — online-rate share will pull the blend toward 2%+; apply to ~95% of turnover (assume near-cashless).
A35: Card share of turnover | B35: 0.95 | C35: % | D35: Near-cashless assumption (Stripe card-on-file flow in use).
A36: Cleaning & sundries | B36: 400 | C36: £/mo | D36: ESTIMATE — laundry, room consumables not tied to treatments, waste disposal (clinical waste contract).
A37: Other fixed costs | B37: 200 | C37: £/mo | D37: ESTIMATE — accountancy, bank, phone/VoIP, misc subscriptions.
A38: MARKETING
A39: Marketing % of net revenue — Y1 / Y2 / Y3 | B39: 0.12 | C39: 0.1 | D39: UK aesthetic clinic benchmarks (Pulse Digital, Aesthetic Launch Lab): growing clinics 7–12%, new clinics 12–15%; single-site commit £1.5k–£5k/mo. Paid-ads CAC ~£45/booked consultation (£30–£60). Clinic reopened May 2026 — use 12–15% (or the £1,500 floor if higher) for year 1, taper to 8–10%. Y1 in B, Y2 in C, Y3 in E. | E39: 0.08
A40: Marketing monthly floor | B40: 1500 | C40: £/mo | D40: Spend floor while revenue is small — you cannot ramp without visibility. CAC benchmark ~£45/booked consultation.
A41: VAT & TAX
A42: VAT standard rate | B42: 0.2 | C42: % | D42: STANDARD-RATED 20%. All 36 null-vatClass services derive as STANDARD in the app. The 'Laser Hair Removal — Women' EXEMPT flag is treated as a DATA-ENTRY ERROR, not a tax fact: UK medical exemption requires a genuine medical purpose by a regulated professional (Illuminate Skin Clinics v HMRC UT 2025; Advanced Hair Technology; HMRC actively scrutinising clinics 2026), and the men's counterpart is standard-rated. Model 20% on the whole aesthetics catalogue; log the flag for correction.
A43: VAT registration threshold | B43: 90000 | C43: £ rolling 12-mo | D43: KCLINICS SKIN & LASER LIMITED (co. 17101088) is NOT VAT registered. Mandatory registration at £90,000 rolling 12-month taxable turnover — a hard modelling constraint: the model must track cumulative taxable turnover and switch on 20% output VAT (a ~16.7% net-revenue cut unless prices rise) at the crossing date, likely within year 1 at any plausible ramp.
A44: Taxable turnover in the 12 months before model start | B44: 25000 | C44: £ | D44: ESTIMATE from 225 bookings in the 90 days post-reopening — feeds the rolling-12-month VAT threshold tracker in P&L. Replace with the real figure from your accounts.
A45: VAT registration month override | B45: 0 | C45: month # (0 = auto) | D45: 0 = the model registers you automatically the month after rolling 12-mo turnover crosses the threshold. Set 1–36 to force a date; prices are held (VAT absorbed out of margin) — see README.
A46: Corporation tax — small profits rate / limit | B46: 0.19 | C46: 50000 | D46: 2026/27: 19% to £50,000; 26.5% effective £50k–£250k (marginal relief); 25% main rate. Annual columns in P&L apply the bands properly.
A47: Corporation tax — marginal band rate / upper limit | B47: 0.265 | C47: 250000 | D47: Effective rate between the limits via marginal relief.
A48: Corporation tax — main rate | B48: 0.25 | C48: % | D48: Annual Investment Allowance: 100% first-year TAX deduction on qualifying plant & machinery (all lasers/devices/fit-out; full expensing also available on new main-rate plant). TIMING benefit only — the accounting P&L still depreciates machinery straight-line over the life-years in the machinery table (4–9 yrs). MODEL TAX AND BOOK DEPRECIATION SEPARATELY: expect tax losses / minimal CT in the capex year, deferred-tax style divergence after.

Sheet Machinery
A1: Machinery, enhancements, depreciation & amortisation
A2: Purchase prices are class-typical UK market figures (see basis column) — replace with your invoice amounts. In-service month: 0 = owned before the model starts; 1–36 = bought in that forecast month; blank = not owned (excluded). Planned hours/month is only the allocation base for service & depreciation per treatment hour in Pricing.
A4: Machine | B4: Class key | C4: Ownership | D4: Purchase £ | E4: In-service month | F4: Life (yrs) | G4: Monthly depreciation | H4: kWh per treatment hr | I4: Annual service £ | J4: Planned hours/mo | K4: Service £/hr | L4: Depreciation £/hr | M4: Consumables model | N4: Basis
A5: Diode laser hair-removal platform | B5: diode-laser | C5: OWNED (serves 63% of recent non-consultation bookings) | D5: 18000 | E5: 0 | F5: 7 | G5: =IF(E5="",0,D5/(F5*12)) -> 214.28571 | H5: 1 | I5: 1800 | J5: 250 | K5: =IF(J5=0,0,I5/12/J5) -> 0.6 | L5: =IF(J5=0,0,G5/J5) -> 0.85714286 | M5: £1–£3.50/session gel + razors (scaled by area in treatments table); handpiece stack rated 1M+ shots, replacement is a maintenance event not a per-session cost | N5: UK trade listings (thelasermachineco, britishlasers): clinic-grade £8k–£15k, premium £30k–£60k; typical premium-clinic buy £18k–£35k. Service ~10% of typical price per britishlasers contract range £1k–£3.5k. kWh: plate 2–3.5 kW at 25–40% duty (engineering estimate).
A6: Multi-application laser/IPL skin platform (shared 'laser' resource pool; may be same combi chassis as diode — Lynton Lumina class covers both for £30k–£50k) | B6: laser-ipl-platform | C6: OWNED (pigmentation/vascular/IPL/rejuvenation/resurfacing/rosacea/wrinkle/spider-vein/carbon-peel/fungal-nail all book against it) | D6: 45000 | E6: 0 | F6: 8 | G6: =IF(E6="",0,D6/(F6*12)) -> 468.75 | H6: 0.8 | I6: 3000 | J6: 30 | K6: =IF(J6=0,0,I6/12/J6) -> 8.3333333 | L6: =IF(J6=0,0,G6/J6) -> 15.625 | M6: £2/session gel; £5–£7 carbon lotion for Hollywood Peel; IPL flashlamp refurb £500–£1,500 per handpiece every ~50k–100k pulses (treat as maintenance) | N6: Lumenis Stellar M22 £45k–£70k; Lynton Lumina £28k–£50k. Service £2k–£5k/yr (Lynton/Lumenis UK contracts, 6–8% of price). Duty 25–35% of plate 1.5–3 kW.
A7: Q-switched/picosecond tattoo & pigment laser | B7: pico-laser-PLANNED | C7: NOT YET PURCHASED — phase-2 capex; tattoo/PMU pages live with prices, bookings closed | D7: 110000 | F7: 8 | G7: =IF(E7="",0,D7/(F7*12)) -> 0 | H7: 1 | I7: 7500 | J7: 25 | K7: =IF(J7=0,0,I7/12/J7) -> 25 | L7: =IF(J7=0,0,G7/J7) -> 0 | M7: ~£1–£2.50/session (gel, wipes, aftercare dressings) — negligible; service contract is the real running cost (8–10% of purchase) | N7: PicoSure Pro/PicoWay £90k–£175k; mid-tier Quanta/Lutronic £50k–£80k; Far-East pico £12.5k; Q-switched Nd:YAG alternative £15k–£40k. Model as a capex decision with three price scenarios — £110k premium figure only holds if buying PicoSure-class.
A8: Fractional CO2 laser with intimate/gynae handpiece | B8: co2-laser | C8: VERIFY — intimate line is COMING_SOON; codebase confirms the treatment tech but not that the unit is on site | D8: 55000 | E8: 0 | F8: 9 | G8: =IF(E8="",0,D8/(F8*12)) -> 509.25926 | H8: 0.4 | I8: 4000 | J8: 8 | K8: =IF(J8=0,0,I8/12/J8) -> 41.666667 | L8: =IF(J8=0,0,G8/J8) -> 63.657407 | M8: £20–£80/session single-use gynae probe covers/hygiene sleeves + numbing cream (£50 midpoint used in treatments table) | N8: Deka SmartXide/Alma FemiLift £40k–£90k with intimate handpiece; generic £5k–£15k; premium-clinic buy £45k–£65k. RF-excited tubes last 8–12 yrs. Service 6–8% of purchase.
A9: HIFU (SMAS ultrasound) with face + body cartridges | B9: hifu | C9: OWNED (live bookings) | D9: 30000 | E9: 0 | F9: 6 | G9: =IF(E9="",0,D9/(F9*12)) -> 416.66667 | H9: 0.3 | I9: 2250 | J9: 25 | K9: =IF(J9=0,0,I9/12/J9) -> 7.5 | L9: =IF(J9=0,0,G9/J9) -> 16.666667 | M9: SHOT-LIMITED CARTRIDGES — the largest device consumable line: £30–£100/session Ultraformer-class (£40 small area / £65 full face / £80 body used in treatments table); would be £300–£900/session if Ultherapy transducers. Plus gel. | N9: Classys Ultraformer III/MPT £25k–£40k UK; Ultherapy £30k–£60k; generic 7D £3k–£8k. Cartridges ~10k–20k shots at £300–£600 each. Service £1.5k–£3k/yr. Duty 30–40% of 0.5–1 kW plate.
A10: Radiofrequency skin-tightening device | B10: rf-tightening | C10: OWNED (live bookings under rf-lifting/rf-skin-tightening) | D10: 40000 | E10: 0 | F10: 7 | G10: =IF(E10="",0,D10/(F10*12)) -> 476.19048 | H10: 0.5 | I10: 3000 | J10: 12 | K10: =IF(J10=0,0,I10/12/J10) -> 20.833333 | L10: =IF(J10=0,0,G10/J10) -> 39.68254 | M10: £2–£5/session conductive gel (plain RF — catalogue has no RF-microneedling, so no Morpheus8-style £100–£180 tips) | N10: BTL Exilis Ultra £30k–£45k; mid-tier £5k–£15k; premium tier £30k–£50k. Service 5–8% of purchase. Near-continuous RF delivery, duty 40–60%.
A11: HydraFacial-style vortex facial platform | B11: hydrafacial-platform | C11: OWNED (live bookings) | D11: 25000 | E11: 0 | F11: 6 | G11: =IF(E11="",0,D11/(F11*12)) -> 347.22222 | H11: 0.2 | I11: 1500 | J11: 60 | K11: =IF(J11=0,0,I11/12/J11) -> 2.0833333 | L11: =IF(J11=0,0,G11/J11) -> 5.787037 | M11: £15–£25/session tips + branded serums, scaling with tier (Signature £15 / Deluxe £20 / Platinum £25); genuine HydraFacial ties serum purchase to warranty. Deep Cleansing menu on same platform at £8–£15/session products. | N11: Genuine HydraFacial Syndeo/Elite £20k–£32k UK; clones £3k–£8k. Consumables $20–$30/treatment (konmison/workee).
A12: Endosphere compressive micro-vibration + anti-cellulite vacuum body platform | B12: endosphere-vacuum | C12: OWNED (body-contouring + vacuum-massage bookings) | D12: 27000 | E12: 0 | F12: 7 | G12: =IF(E12="",0,D12/(F12*12)) -> 321.42857 | H12: 0.35 | I12: 1750 | J12: 45 | K12: =IF(J12=0,0,I12/12/J12) -> 3.2407407 | L12: =IF(J12=0,0,G12/J12) -> 7.1428571 | M12: £1–£3/session oil/cream/disposable bodysuits | N12: Endospheres AK Body dealer pricing ~€25k–€35k (~£21k–£30k, baltic-lasers.eu) — DEALER-QUOTE ESTIMATE, not published list price. Service/roller refurb ~5% of price. Motor runs near-continuously at 0.3–0.5 kW.
A13: Microneedling pen (+ BB Glow micro-channelling) | B13: microneedling-pen | C13: OWNED (live bookings) | D13: 3000 | E13: 0 | F13: 4 | G13: =IF(E13="",0,D13/(F13*12)) -> 62.5 | H13: 0.02 | I13: 100 | J13: 18 | K13: =IF(J13=0,0,I13/12/J13) -> 0.46296296 | L13: =IF(J13=0,0,G13/J13) -> 3.4722222 | M13: £5–£35/session sterile needle cartridge + serum (SkinPen cartridges £25–£35, generic £5–£20); BB Glow tinted ampoule £5–£15 extra | N13: SkinPen Precision £2k–£3.5k, Dermapen 4 £3k–£5.5k. Negligible power. Battery/handpiece wear limits life to 3–5 yrs.
A14: Microdermabrasion device (diamond-tip/crystal) | B14: microdermabrasion | C14: OWNED (1 booking in 90d) | D14: 3000 | E14: 0 | F14: 6 | G14: =IF(E14="",0,D14/(F14*12)) -> 41.666667 | H14: 0.25 | I14: 300 | J14: 8 | K14: =IF(J14=0,0,I14/12/J14) -> 3.125 | L14: =IF(J14=0,0,G14/J14) -> 5.2083333 | M14: £1–£3/session filters + disposable tips (crystals £3–£5 if crystal type) | N14: UK professional diamond-tip units £1.2k–£6k, typical £2.5k–£3.5k. Vacuum pump 0.2–0.4 kW near-continuous.
A15: Microcurrent facial toning device + LED panel | B15: microcurrent-led | C15: AMBIGUOUS — codebase marks microcurrent/LED 'onRequest, machine not yet in', but the live catalogue lists Microcurrent lifting and LED as NORMAL and there are 6 microcurrent-facial bookings in 90d. Assume a non-CACI-branded unit is on site; confirm with owner. | D15: 15000 | E15: 0 | F15: 8 | G15: =IF(E15="",0,D15/(F15*12)) -> 156.25 | H15: 0.1 | I15: 750 | J15: 25 | K15: =IF(J15=0,0,I15/12/J15) -> 2.5 | L15: =IF(J15=0,0,G15/J15) -> 6.25 | M15: £2–£5/session conductive gel, cotton buds; hydra mask +£5; LED session ~£1 | N15: CACI Synergy £14k–£17k inc training, Ultimate £18k–£22k, Classic £9k–£12k (dealer channel, prices on application). If the on-site unit is a generic microcurrent+LED device the capex could be £2k–£5k — use the low end unless CACI-branded purchase is confirmed.
A16: Injectables room (no machine): electric couch + MHRA-compliant medical fridge + sharps/emergency kit | B16: none-injectables | C16: OWNED | D16: 2500 | E16: 0 | F16: 10 | G16: =IF(E16="",0,D16/(F16*12)) -> 20.833333 | H16: 0 | I16: 150 | J16: 25 | K16: =IF(J16=0,0,I16/12/J16) -> 0.5 | L16: =IF(J16=0,0,G16/J16) -> 0.83333333 | M16: DOMINANT COGS LINE: toxin vials £45–£85/tx by area count, HA filler £35–£85/tx by ml, fat-dissolving vials £35–£75/tx, polynucleotides £70–£100/tx, meso cocktails £25/tx, plus needles/cannulae/numbing (in per-row figures). Fridge runs 24/7: ~1.5–3 kWh/day counted in base load, not per-treatment. | N16: Couch £700–£2,500, pharmacy fridge £400–£1,500, kit £200–£500. Injectable COGS from UK aesthetic wholesale norms (Church Pharmacy tier) — brand-dependent estimates, no recorded costs.
A17: Topical/manual treatment room kit (couch, trolley, steamer, hot cabinet) | B17: none-manual | C17: OWNED | D17: 1500 | E17: 0 | F17: 9 | G17: =IF(E17="",0,D17/(F17*12)) -> 13.888889 | H17: 0.1 | I17: 100 | J17: 25 | K17: =IF(J17=0,0,I17/12/J17) -> 0.33333333 | L17: =IF(J17=0,0,G17/J17) -> 0.55555556 | M17: £1.50–£15/session: peel solutions + neutralisers £10–£15, massage oils £2–£4, masks/towels/products £3–£8 | N17: UK salon equipment norms; steamer ~0.3 kW only while on.
A20: ENHANCEMENTS & FIT-OUT (amortised)
A21: Item | C21: Notes | D21: Cost £ | E21: In-service month | F21: Life (yrs) | G21: Monthly amortisation
A22: Initial fit-out / leasehold improvements | C22: GAP — fit-out spend on 4 Charterhouse Buildings unknown. Enter the capitalised amount; it amortises over the life you set. | D22: 0 | E22: 0 | F22: 10 | G22: =IF(OR(E22="",F22=0),0,D22/(F22*12)) -> 0
A23: EXAMPLE — reception refresh (edit or zero out) | C23: Example row showing the expected format. | D23: 8000 | E23: 6 | F23: 5 | G23: =IF(OR(E23="",F23=0),0,D23/(F23*12)) -> 133.33333
A24: Planned enhancement 2 | D24: 0 | F24: 5 | G24: =IF(OR(E24="",F24=0),0,D24/(F24*12)) -> 0
A25: Planned enhancement 3 | D25: 0 | F25: 5 | G25: =IF(OR(E25="",F25=0),0,D25/(F25*12)) -> 0
A26: Planned enhancement 4 | D26: 0 | F26: 5 | G26: =IF(OR(E26="",F26=0),0,D26/(F26*12)) -> 0
A29: MONTHLY D&A SCHEDULE (feeds P&L)
A30: Month # | B30: 1 | C30: 2 | D30: 3 | E30: 4 | F30: 5 | G30: 6 | H30: 7 | I30: 8 | J30: 9 | K30: 10 | L30: 11 | M30: 12 | N30: 13 | O30: 14 | P30: 15 | Q30: 16 | R30: 17 | S30: 18 | T30: 19 | U30: 20 | V30: 21 | W30: 22 | X30: 23 | Y30: 24 | Z30: 25 | AA30: 26 | AB30: 27 | AC30: 28 | AD30: 29 | AE30: 30 | AF30: 31 | AG30: 32 | AH30: 33 | AI30: 34 | AJ30: 35 | AK30: 36
A31: =A5 -> Diode laser hair-removal platform | B31: =IF($E5="",0,IF(AND(COLUMN()-1>=MAX($E5,1),COLUMN()-1<$E5+$F5*12),$G5,0)) -> 214.28571 | C31: =IF($E5="",0,IF(AND(COLUMN()-1>=MAX($E5,1),COLUMN()-1<$E5+$F5*12),$G5,0)) -> 214.28571 | D31: =IF($E5="",0,IF(AND(COLUMN()-1>=MAX($E5,1),COLUMN()-1<$E5+$F5*12),$G5,0)) -> 214.28571 | E31: =IF($E5="",0,IF(AND(COLUMN()-1>=MAX($E5,1),COLUMN()-1<$E5+$F5*12),$G5,0)) -> 214.28571 | F31: =IF($E5="",0,IF(AND(COLUMN()-1>=MAX($E5,1),COLUMN()-1<$E5+$F5*12),$G5,0)) -> 214.28571 | G31: =IF($E5="",0,IF(AND(COLUMN()-1>=MAX($E5,1),COLUMN()-1<$E5+$F5*12),$G5,0)) -> 214.28571 | H31: =IF($E5="",0,IF(AND(COLUMN()-1>=MAX($E5,1),COLUMN()-1<$E5+$F5*12),$G5,0)) -> 214.28571 | I31: =IF($E5="",0,IF(AND(COLUMN()-1>=MAX($E5,1),COLUMN()-1<$E5+$F5*12),$G5,0)) -> 214.28571 | ... AK31: =IF($E5="",0,IF(AND(COLUMN()-1>=MAX($E5,1),COLUMN()-1<$E5+$F5*12),$G5,0)) -> 214.28571
A32: =A6 -> Multi-application laser/IPL skin platform (shared 'laser' resource pool; may be same combi chassis as diode — Lynton Lumina class covers both for £30k–£50k) | B32: =IF($E6="",0,IF(AND(COLUMN()-1>=MAX($E6,1),COLUMN()-1<$E6+$F6*12),$G6,0)) -> 468.75 | C32: =IF($E6="",0,IF(AND(COLUMN()-1>=MAX($E6,1),COLUMN()-1<$E6+$F6*12),$G6,0)) -> 468.75 | D32: =IF($E6="",0,IF(AND(COLUMN()-1>=MAX($E6,1),COLUMN()-1<$E6+$F6*12),$G6,0)) -> 468.75 | E32: =IF($E6="",0,IF(AND(COLUMN()-1>=MAX($E6,1),COLUMN()-1<$E6+$F6*12),$G6,0)) -> 468.75 | F32: =IF($E6="",0,IF(AND(COLUMN()-1>=MAX($E6,1),COLUMN()-1<$E6+$F6*12),$G6,0)) -> 468.75 | G32: =IF($E6="",0,IF(AND(COLUMN()-1>=MAX($E6,1),COLUMN()-1<$E6+$F6*12),$G6,0)) -> 468.75 | H32: =IF($E6="",0,IF(AND(COLUMN()-1>=MAX($E6,1),COLUMN()-1<$E6+$F6*12),$G6,0)) -> 468.75 | I32: =IF($E6="",0,IF(AND(COLUMN()-1>=MAX($E6,1),COLUMN()-1<$E6+$F6*12),$G6,0)) -> 468.75 | ... AK32: =IF($E6="",0,IF(AND(COLUMN()-1>=MAX($E6,1),COLUMN()-1<$E6+$F6*12),$G6,0)) -> 468.75
A33: =A7 -> Q-switched/picosecond tattoo & pigment laser | B33: =IF($E7="",0,IF(AND(COLUMN()-1>=MAX($E7,1),COLUMN()-1<$E7+$F7*12),$G7,0)) -> 0 | C33: =IF($E7="",0,IF(AND(COLUMN()-1>=MAX($E7,1),COLUMN()-1<$E7+$F7*12),$G7,0)) -> 0 | D33: =IF($E7="",0,IF(AND(COLUMN()-1>=MAX($E7,1),COLUMN()-1<$E7+$F7*12),$G7,0)) -> 0 | E33: =IF($E7="",0,IF(AND(COLUMN()-1>=MAX($E7,1),COLUMN()-1<$E7+$F7*12),$G7,0)) -> 0 | F33: =IF($E7="",0,IF(AND(COLUMN()-1>=MAX($E7,1),COLUMN()-1<$E7+$F7*12),$G7,0)) -> 0 | G33: =IF($E7="",0,IF(AND(COLUMN()-1>=MAX($E7,1),COLUMN()-1<$E7+$F7*12),$G7,0)) -> 0 | H33: =IF($E7="",0,IF(AND(COLUMN()-1>=MAX($E7,1),COLUMN()-1<$E7+$F7*12),$G7,0)) -> 0 | I33: =IF($E7="",0,IF(AND(COLUMN()-1>=MAX($E7,1),COLUMN()-1<$E7+$F7*12),$G7,0)) -> 0 | ... AK33: =IF($E7="",0,IF(AND(COLUMN()-1>=MAX($E7,1),COLUMN()-1<$E7+$F7*12),$G7,0)) -> 0
A34: =A8 -> Fractional CO2 laser with intimate/gynae handpiece | B34: =IF($E8="",0,IF(AND(COLUMN()-1>=MAX($E8,1),COLUMN()-1<$E8+$F8*12),$G8,0)) -> 509.25926 | C34: =IF($E8="",0,IF(AND(COLUMN()-1>=MAX($E8,1),COLUMN()-1<$E8+$F8*12),$G8,0)) -> 509.25926 | D34: =IF($E8="",0,IF(AND(COLUMN()-1>=MAX($E8,1),COLUMN()-1<$E8+$F8*12),$G8,0)) -> 509.25926 | E34: =IF($E8="",0,IF(AND(COLUMN()-1>=MAX($E8,1),COLUMN()-1<$E8+$F8*12),$G8,0)) -> 509.25926 | F34: =IF($E8="",0,IF(AND(COLUMN()-1>=MAX($E8,1),COLUMN()-1<$E8+$F8*12),$G8,0)) -> 509.25926 | G34: =IF($E8="",0,IF(AND(COLUMN()-1>=MAX($E8,1),COLUMN()-1<$E8+$F8*12),$G8,0)) -> 509.25926 | H34: =IF($E8="",0,IF(AND(COLUMN()-1>=MAX($E8,1),COLUMN()-1<$E8+$F8*12),$G8,0)) -> 509.25926 | I34: =IF($E8="",0,IF(AND(COLUMN()-1>=MAX($E8,1),COLUMN()-1<$E8+$F8*12),$G8,0)) -> 509.25926 | ... AK34: =IF($E8="",0,IF(AND(COLUMN()-1>=MAX($E8,1),COLUMN()-1<$E8+$F8*12),$G8,0)) -> 509.25926
A35: =A9 -> HIFU (SMAS ultrasound) with face + body cartridges | B35: =IF($E9="",0,IF(AND(COLUMN()-1>=MAX($E9,1),COLUMN()-1<$E9+$F9*12),$G9,0)) -> 416.66667 | C35: =IF($E9="",0,IF(AND(COLUMN()-1>=MAX($E9,1),COLUMN()-1<$E9+$F9*12),$G9,0)) -> 416.66667 | D35: =IF($E9="",0,IF(AND(COLUMN()-1>=MAX($E9,1),COLUMN()-1<$E9+$F9*12),$G9,0)) -> 416.66667 | E35: =IF($E9="",0,IF(AND(COLUMN()-1>=MAX($E9,1),COLUMN()-1<$E9+$F9*12),$G9,0)) -> 416.66667 | F35: =IF($E9="",0,IF(AND(COLUMN()-1>=MAX($E9,1),COLUMN()-1<$E9+$F9*12),$G9,0)) -> 416.66667 | G35: =IF($E9="",0,IF(AND(COLUMN()-1>=MAX($E9,1),COLUMN()-1<$E9+$F9*12),$G9,0)) -> 416.66667 | H35: =IF($E9="",0,IF(AND(COLUMN()-1>=MAX($E9,1),COLUMN()-1<$E9+$F9*12),$G9,0)) -> 416.66667 | I35: =IF($E9="",0,IF(AND(COLUMN()-1>=MAX($E9,1),COLUMN()-1<$E9+$F9*12),$G9,0)) -> 416.66667 | ... AK35: =IF($E9="",0,IF(AND(COLUMN()-1>=MAX($E9,1),COLUMN()-1<$E9+$F9*12),$G9,0)) -> 416.66667
A36: =A10 -> Radiofrequency skin-tightening device | B36: =IF($E10="",0,IF(AND(COLUMN()-1>=MAX($E10,1),COLUMN()-1<$E10+$F10*12),$G10,0)) -> 476.19048 | C36: =IF($E10="",0,IF(AND(COLUMN()-1>=MAX($E10,1),COLUMN()-1<$E10+$F10*12),$G10,0)) -> 476.19048 | D36: =IF($E10="",0,IF(AND(COLUMN()-1>=MAX($E10,1),COLUMN()-1<$E10+$F10*12),$G10,0)) -> 476.19048 | E36: =IF($E10="",0,IF(AND(COLUMN()-1>=MAX($E10,1),COLUMN()-1<$E10+$F10*12),$G10,0)) -> 476.19048 | F36: =IF($E10="",0,IF(AND(COLUMN()-1>=MAX($E10,1),COLUMN()-1<$E10+$F10*12),$G10,0)) -> 476.19048 | G36: =IF($E10="",0,IF(AND(COLUMN()-1>=MAX($E10,1),COLUMN()-1<$E10+$F10*12),$G10,0)) -> 476.19048 | H36: =IF($E10="",0,IF(AND(COLUMN()-1>=MAX($E10,1),COLUMN()-1<$E10+$F10*12),$G10,0)) -> 476.19048 | I36: =IF($E10="",0,IF(AND(COLUMN()-1>=MAX($E10,1),COLUMN()-1<$E10+$F10*12),$G10,0)) -> 476.19048 | ... AK36: =IF($E10="",0,IF(AND(COLUMN()-1>=MAX($E10,1),COLUMN()-1<$E10+$F10*12),$G10,0)) -> 476.19048
A37: =A11 -> HydraFacial-style vortex facial platform | B37: =IF($E11="",0,IF(AND(COLUMN()-1>=MAX($E11,1),COLUMN()-1<$E11+$F11*12),$G11,0)) -> 347.22222 | C37: =IF($E11="",0,IF(AND(COLUMN()-1>=MAX($E11,1),COLUMN()-1<$E11+$F11*12),$G11,0)) -> 347.22222 | D37: =IF($E11="",0,IF(AND(COLUMN()-1>=MAX($E11,1),COLUMN()-1<$E11+$F11*12),$G11,0)) -> 347.22222 | E37: =IF($E11="",0,IF(AND(COLUMN()-1>=MAX($E11,1),COLUMN()-1<$E11+$F11*12),$G11,0)) -> 347.22222 | F37: =IF($E11="",0,IF(AND(COLUMN()-1>=MAX($E11,1),COLUMN()-1<$E11+$F11*12),$G11,0)) -> 347.22222 | G37: =IF($E11="",0,IF(AND(COLUMN()-1>=MAX($E11,1),COLUMN()-1<$E11+$F11*12),$G11,0)) -> 347.22222 | H37: =IF($E11="",0,IF(AND(COLUMN()-1>=MAX($E11,1),COLUMN()-1<$E11+$F11*12),$G11,0)) -> 347.22222 | I37: =IF($E11="",0,IF(AND(COLUMN()-1>=MAX($E11,1),COLUMN()-1<$E11+$F11*12),$G11,0)) -> 347.22222 | ... AK37: =IF($E11="",0,IF(AND(COLUMN()-1>=MAX($E11,1),COLUMN()-1<$E11+$F11*12),$G11,0)) -> 347.22222
A38: =A12 -> Endosphere compressive micro-vibration + anti-cellulite vacuum body platform | B38: =IF($E12="",0,IF(AND(COLUMN()-1>=MAX($E12,1),COLUMN()-1<$E12+$F12*12),$G12,0)) -> 321.42857 | C38: =IF($E12="",0,IF(AND(COLUMN()-1>=MAX($E12,1),COLUMN()-1<$E12+$F12*12),$G12,0)) -> 321.42857 | D38: =IF($E12="",0,IF(AND(COLUMN()-1>=MAX($E12,1),COLUMN()-1<$E12+$F12*12),$G12,0)) -> 321.42857 | E38: =IF($E12="",0,IF(AND(COLUMN()-1>=MAX($E12,1),COLUMN()-1<$E12+$F12*12),$G12,0)) -> 321.42857 | F38: =IF($E12="",0,IF(AND(COLUMN()-1>=MAX($E12,1),COLUMN()-1<$E12+$F12*12),$G12,0)) -> 321.42857 | G38: =IF($E12="",0,IF(AND(COLUMN()-1>=MAX($E12,1),COLUMN()-1<$E12+$F12*12),$G12,0)) -> 321.42857 | H38: =IF($E12="",0,IF(AND(COLUMN()-1>=MAX($E12,1),COLUMN()-1<$E12+$F12*12),$G12,0)) -> 321.42857 | I38: =IF($E12="",0,IF(AND(COLUMN()-1>=MAX($E12,1),COLUMN()-1<$E12+$F12*12),$G12,0)) -> 321.42857 | ... AK38: =IF($E12="",0,IF(AND(COLUMN()-1>=MAX($E12,1),COLUMN()-1<$E12+$F12*12),$G12,0)) -> 321.42857
A39: =A13 -> Microneedling pen (+ BB Glow micro-channelling) | B39: =IF($E13="",0,IF(AND(COLUMN()-1>=MAX($E13,1),COLUMN()-1<$E13+$F13*12),$G13,0)) -> 62.5 | C39: =IF($E13="",0,IF(AND(COLUMN()-1>=MAX($E13,1),COLUMN()-1<$E13+$F13*12),$G13,0)) -> 62.5 | D39: =IF($E13="",0,IF(AND(COLUMN()-1>=MAX($E13,1),COLUMN()-1<$E13+$F13*12),$G13,0)) -> 62.5 | E39: =IF($E13="",0,IF(AND(COLUMN()-1>=MAX($E13,1),COLUMN()-1<$E13+$F13*12),$G13,0)) -> 62.5 | F39: =IF($E13="",0,IF(AND(COLUMN()-1>=MAX($E13,1),COLUMN()-1<$E13+$F13*12),$G13,0)) -> 62.5 | G39: =IF($E13="",0,IF(AND(COLUMN()-1>=MAX($E13,1),COLUMN()-1<$E13+$F13*12),$G13,0)) -> 62.5 | H39: =IF($E13="",0,IF(AND(COLUMN()-1>=MAX($E13,1),COLUMN()-1<$E13+$F13*12),$G13,0)) -> 62.5 | I39: =IF($E13="",0,IF(AND(COLUMN()-1>=MAX($E13,1),COLUMN()-1<$E13+$F13*12),$G13,0)) -> 62.5 | ... AK39: =IF($E13="",0,IF(AND(COLUMN()-1>=MAX($E13,1),COLUMN()-1<$E13+$F13*12),$G13,0)) -> 62.5
A40: =A14 -> Microdermabrasion device (diamond-tip/crystal) | B40: =IF($E14="",0,IF(AND(COLUMN()-1>=MAX($E14,1),COLUMN()-1<$E14+$F14*12),$G14,0)) -> 41.666667 | C40: =IF($E14="",0,IF(AND(COLUMN()-1>=MAX($E14,1),COLUMN()-1<$E14+$F14*12),$G14,0)) -> 41.666667 | D40: =IF($E14="",0,IF(AND(COLUMN()-1>=MAX($E14,1),COLUMN()-1<$E14+$F14*12),$G14,0)) -> 41.666667 | E40: =IF($E14="",0,IF(AND(COLUMN()-1>=MAX($E14,1),COLUMN()-1<$E14+$F14*12),$G14,0)) -> 41.666667 | F40: =IF($E14="",0,IF(AND(COLUMN()-1>=MAX($E14,1),COLUMN()-1<$E14+$F14*12),$G14,0)) -> 41.666667 | G40: =IF($E14="",0,IF(AND(COLUMN()-1>=MAX($E14,1),COLUMN()-1<$E14+$F14*12),$G14,0)) -> 41.666667 | H40: =IF($E14="",0,IF(AND(COLUMN()-1>=MAX($E14,1),COLUMN()-1<$E14+$F14*12),$G14,0)) -> 41.666667 | I40: =IF($E14="",0,IF(AND(COLUMN()-1>=MAX($E14,1),COLUMN()-1<$E14+$F14*12),$G14,0)) -> 41.666667 | ... AK40: =IF($E14="",0,IF(AND(COLUMN()-1>=MAX($E14,1),COLUMN()-1<$E14+$F14*12),$G14,0)) -> 41.666667
A41: =A15 -> Microcurrent facial toning device + LED panel | B41: =IF($E15="",0,IF(AND(COLUMN()-1>=MAX($E15,1),COLUMN()-1<$E15+$F15*12),$G15,0)) -> 156.25 | C41: =IF($E15="",0,IF(AND(COLUMN()-1>=MAX($E15,1),COLUMN()-1<$E15+$F15*12),$G15,0)) -> 156.25 | D41: =IF($E15="",0,IF(AND(COLUMN()-1>=MAX($E15,1),COLUMN()-1<$E15+$F15*12),$G15,0)) -> 156.25 | E41: =IF($E15="",0,IF(AND(COLUMN()-1>=MAX($E15,1),COLUMN()-1<$E15+$F15*12),$G15,0)) -> 156.25 | F41: =IF($E15="",0,IF(AND(COLUMN()-1>=MAX($E15,1),COLUMN()-1<$E15+$F15*12),$G15,0)) -> 156.25 | G41: =IF($E15="",0,IF(AND(COLUMN()-1>=MAX($E15,1),COLUMN()-1<$E15+$F15*12),$G15,0)) -> 156.25 | H41: =IF($E15="",0,IF(AND(COLUMN()-1>=MAX($E15,1),COLUMN()-1<$E15+$F15*12),$G15,0)) -> 156.25 | I41: =IF($E15="",0,IF(AND(COLUMN()-1>=MAX($E15,1),COLUMN()-1<$E15+$F15*12),$G15,0)) -> 156.25 | ... AK41: =IF($E15="",0,IF(AND(COLUMN()-1>=MAX($E15,1),COLUMN()-1<$E15+$F15*12),$G15,0)) -> 156.25
A42: =A16 -> Injectables room (no machine): electric couch + MHRA-compliant medical fridge + sharps/emergency kit | B42: =IF($E16="",0,IF(AND(COLUMN()-1>=MAX($E16,1),COLUMN()-1<$E16+$F16*12),$G16,0)) -> 20.833333 | C42: =IF($E16="",0,IF(AND(COLUMN()-1>=MAX($E16,1),COLUMN()-1<$E16+$F16*12),$G16,0)) -> 20.833333 | D42: =IF($E16="",0,IF(AND(COLUMN()-1>=MAX($E16,1),COLUMN()-1<$E16+$F16*12),$G16,0)) -> 20.833333 | E42: =IF($E16="",0,IF(AND(COLUMN()-1>=MAX($E16,1),COLUMN()-1<$E16+$F16*12),$G16,0)) -> 20.833333 | F42: =IF($E16="",0,IF(AND(COLUMN()-1>=MAX($E16,1),COLUMN()-1<$E16+$F16*12),$G16,0)) -> 20.833333 | G42: =IF($E16="",0,IF(AND(COLUMN()-1>=MAX($E16,1),COLUMN()-1<$E16+$F16*12),$G16,0)) -> 20.833333 | H42: =IF($E16="",0,IF(AND(COLUMN()-1>=MAX($E16,1),COLUMN()-1<$E16+$F16*12),$G16,0)) -> 20.833333 | I42: =IF($E16="",0,IF(AND(COLUMN()-1>=MAX($E16,1),COLUMN()-1<$E16+$F16*12),$G16,0)) -> 20.833333 | ... AK42: =IF($E16="",0,IF(AND(COLUMN()-1>=MAX($E16,1),COLUMN()-1<$E16+$F16*12),$G16,0)) -> 20.833333
A43: =A17 -> Topical/manual treatment room kit (couch, trolley, steamer, hot cabinet) | B43: =IF($E17="",0,IF(AND(COLUMN()-1>=MAX($E17,1),COLUMN()-1<$E17+$F17*12),$G17,0)) -> 13.888889 | C43: =IF($E17="",0,IF(AND(COLUMN()-1>=MAX($E17,1),COLUMN()-1<$E17+$F17*12),$G17,0)) -> 13.888889 | D43: =IF($E17="",0,IF(AND(COLUMN()-1>=MAX($E17,1),COLUMN()-1<$E17+$F17*12),$G17,0)) -> 13.888889 | E43: =IF($E17="",0,IF(AND(COLUMN()-1>=MAX($E17,1),COLUMN()-1<$E17+$F17*12),$G17,0)) -> 13.888889 | F43: =IF($E17="",0,IF(AND(COLUMN()-1>=MAX($E17,1),COLUMN()-1<$E17+$F17*12),$G17,0)) -> 13.888889 | G43: =IF($E17="",0,IF(AND(COLUMN()-1>=MAX($E17,1),COLUMN()-1<$E17+$F17*12),$G17,0)) -> 13.888889 | H43: =IF($E17="",0,IF(AND(COLUMN()-1>=MAX($E17,1),COLUMN()-1<$E17+$F17*12),$G17,0)) -> 13.888889 | I43: =IF($E17="",0,IF(AND(COLUMN()-1>=MAX($E17,1),COLUMN()-1<$E17+$F17*12),$G17,0)) -> 13.888889 | ... AK43: =IF($E17="",0,IF(AND(COLUMN()-1>=MAX($E17,1),COLUMN()-1<$E17+$F17*12),$G17,0)) -> 13.888889
A44: =A22 -> Initial fit-out / leasehold improvements | B44: =IF(OR($E22="",$F22=0),0,IF(AND(COLUMN()-1>=MAX($E22,1),COLUMN()-1<$E22+$F22*12),$G22,0)) -> 0 | C44: =IF(OR($E22="",$F22=0),0,IF(AND(COLUMN()-1>=MAX($E22,1),COLUMN()-1<$E22+$F22*12),$G22,0)) -> 0 | D44: =IF(OR($E22="",$F22=0),0,IF(AND(COLUMN()-1>=MAX($E22,1),COLUMN()-1<$E22+$F22*12),$G22,0)) -> 0 | E44: =IF(OR($E22="",$F22=0),0,IF(AND(COLUMN()-1>=MAX($E22,1),COLUMN()-1<$E22+$F22*12),$G22,0)) -> 0 | F44: =IF(OR($E22="",$F22=0),0,IF(AND(COLUMN()-1>=MAX($E22,1),COLUMN()-1<$E22+$F22*12),$G22,0)) -> 0 | G44: =IF(OR($E22="",$F22=0),0,IF(AND(COLUMN()-1>=MAX($E22,1),COLUMN()-1<$E22+$F22*12),$G22,0)) -> 0 | H44: =IF(OR($E22="",$F22=0),0,IF(AND(COLUMN()-1>=MAX($E22,1),COLUMN()-1<$E22+$F22*12),$G22,0)) -> 0 | I44: =IF(OR($E22="",$F22=0),0,IF(AND(COLUMN()-1>=MAX($E22,1),COLUMN()-1<$E22+$F22*12),$G22,0)) -> 0 | ... AK44: =IF(OR($E22="",$F22=0),0,IF(AND(COLUMN()-1>=MAX($E22,1),COLUMN()-1<$E22+$F22*12),$G22,0)) -> 0
A45: =A23 -> EXAMPLE — reception refresh (edit or zero out) | B45: =IF(OR($E23="",$F23=0),0,IF(AND(COLUMN()-1>=MAX($E23,1),COLUMN()-1<$E23+$F23*12),$G23,0)) -> 0 | C45: =IF(OR($E23="",$F23=0),0,IF(AND(COLUMN()-1>=MAX($E23,1),COLUMN()-1<$E23+$F23*12),$G23,0)) -> 0 | D45: =IF(OR($E23="",$F23=0),0,IF(AND(COLUMN()-1>=MAX($E23,1),COLUMN()-1<$E23+$F23*12),$G23,0)) -> 0 | E45: =IF(OR($E23="",$F23=0),0,IF(AND(COLUMN()-1>=MAX($E23,1),COLUMN()-1<$E23+$F23*12),$G23,0)) -> 0 | F45: =IF(OR($E23="",$F23=0),0,IF(AND(COLUMN()-1>=MAX($E23,1),COLUMN()-1<$E23+$F23*12),$G23,0)) -> 0 | G45: =IF(OR($E23="",$F23=0),0,IF(AND(COLUMN()-1>=MAX($E23,1),COLUMN()-1<$E23+$F23*12),$G23,0)) -> 133.33333 | H45: =IF(OR($E23="",$F23=0),0,IF(AND(COLUMN()-1>=MAX($E23,1),COLUMN()-1<$E23+$F23*12),$G23,0)) -> 133.33333 | I45: =IF(OR($E23="",$F23=0),0,IF(AND(COLUMN()-1>=MAX($E23,1),COLUMN()-1<$E23+$F23*12),$G23,0)) -> 133.33333 | ... AK45: =IF(OR($E23="",$F23=0),0,IF(AND(COLUMN()-1>=MAX($E23,1),COLUMN()-1<$E23+$F23*12),$G23,0)) -> 133.33333
A46: =A24 -> Planned enhancement 2 | B46: =IF(OR($E24="",$F24=0),0,IF(AND(COLUMN()-1>=MAX($E24,1),COLUMN()-1<$E24+$F24*12),$G24,0)) -> 0 | C46: =IF(OR($E24="",$F24=0),0,IF(AND(COLUMN()-1>=MAX($E24,1),COLUMN()-1<$E24+$F24*12),$G24,0)) -> 0 | D46: =IF(OR($E24="",$F24=0),0,IF(AND(COLUMN()-1>=MAX($E24,1),COLUMN()-1<$E24+$F24*12),$G24,0)) -> 0 | E46: =IF(OR($E24="",$F24=0),0,IF(AND(COLUMN()-1>=MAX($E24,1),COLUMN()-1<$E24+$F24*12),$G24,0)) -> 0 | F46: =IF(OR($E24="",$F24=0),0,IF(AND(COLUMN()-1>=MAX($E24,1),COLUMN()-1<$E24+$F24*12),$G24,0)) -> 0 | G46: =IF(OR($E24="",$F24=0),0,IF(AND(COLUMN()-1>=MAX($E24,1),COLUMN()-1<$E24+$F24*12),$G24,0)) -> 0 | H46: =IF(OR($E24="",$F24=0),0,IF(AND(COLUMN()-1>=MAX($E24,1),COLUMN()-1<$E24+$F24*12),$G24,0)) -> 0 | I46: =IF(OR($E24="",$F24=0),0,IF(AND(COLUMN()-1>=MAX($E24,1),COLUMN()-1<$E24+$F24*12),$G24,0)) -> 0 | ... AK46: =IF(OR($E24="",$F24=0),0,IF(AND(COLUMN()-1>=MAX($E24,1),COLUMN()-1<$E24+$F24*12),$G24,0)) -> 0
A47: =A25 -> Planned enhancement 3 | B47: =IF(OR($E25="",$F25=0),0,IF(AND(COLUMN()-1>=MAX($E25,1),COLUMN()-1<$E25+$F25*12),$G25,0)) -> 0 | C47: =IF(OR($E25="",$F25=0),0,IF(AND(COLUMN()-1>=MAX($E25,1),COLUMN()-1<$E25+$F25*12),$G25,0)) -> 0 | D47: =IF(OR($E25="",$F25=0),0,IF(AND(COLUMN()-1>=MAX($E25,1),COLUMN()-1<$E25+$F25*12),$G25,0)) -> 0 | E47: =IF(OR($E25="",$F25=0),0,IF(AND(COLUMN()-1>=MAX($E25,1),COLUMN()-1<$E25+$F25*12),$G25,0)) -> 0 | F47: =IF(OR($E25="",$F25=0),0,IF(AND(COLUMN()-1>=MAX($E25,1),COLUMN()-1<$E25+$F25*12),$G25,0)) -> 0 | G47: =IF(OR($E25="",$F25=0),0,IF(AND(COLUMN()-1>=MAX($E25,1),COLUMN()-1<$E25+$F25*12),$G25,0)) -> 0 | H47: =IF(OR($E25="",$F25=0),0,IF(AND(COLUMN()-1>=MAX($E25,1),COLUMN()-1<$E25+$F25*12),$G25,0)) -> 0 | I47: =IF(OR($E25="",$F25=0),0,IF(AND(COLUMN()-1>=MAX($E25,1),COLUMN()-1<$E25+$F25*12),$G25,0)) -> 0 | ... AK47: =IF(OR($E25="",$F25=0),0,IF(AND(COLUMN()-1>=MAX($E25,1),COLUMN()-1<$E25+$F25*12),$G25,0)) -> 0
A48: =A26 -> Planned enhancement 4 | B48: =IF(OR($E26="",$F26=0),0,IF(AND(COLUMN()-1>=MAX($E26,1),COLUMN()-1<$E26+$F26*12),$G26,0)) -> 0 | C48: =IF(OR($E26="",$F26=0),0,IF(AND(COLUMN()-1>=MAX($E26,1),COLUMN()-1<$E26+$F26*12),$G26,0)) -> 0 | D48: =IF(OR($E26="",$F26=0),0,IF(AND(COLUMN()-1>=MAX($E26,1),COLUMN()-1<$E26+$F26*12),$G26,0)) -> 0 | E48: =IF(OR($E26="",$F26=0),0,IF(AND(COLUMN()-1>=MAX($E26,1),COLUMN()-1<$E26+$F26*12),$G26,0)) -> 0 | F48: =IF(OR($E26="",$F26=0),0,IF(AND(COLUMN()-1>=MAX($E26,1),COLUMN()-1<$E26+$F26*12),$G26,0)) -> 0 | G48: =IF(OR($E26="",$F26=0),0,IF(AND(COLUMN()-1>=MAX($E26,1),COLUMN()-1<$E26+$F26*12),$G26,0)) -> 0 | H48: =IF(OR($E26="",$F26=0),0,IF(AND(COLUMN()-1>=MAX($E26,1),COLUMN()-1<$E26+$F26*12),$G26,0)) -> 0 | I48: =IF(OR($E26="",$F26=0),0,IF(AND(COLUMN()-1>=MAX($E26,1),COLUMN()-1<$E26+$F26*12),$G26,0)) -> 0 | ... AK48: =IF(OR($E26="",$F26=0),0,IF(AND(COLUMN()-1>=MAX($E26,1),COLUMN()-1<$E26+$F26*12),$G26,0)) -> 0
A49: Total depreciation (machines) | B49: =SUM(B31:B43) -> 3048.9418 | C49: =SUM(C31:C43) -> 3048.9418 | D49: =SUM(D31:D43) -> 3048.9418 | E49: =SUM(E31:E43) -> 3048.9418 | F49: =SUM(F31:F43) -> 3048.9418 | G49: =SUM(G31:G43) -> 3048.9418 | H49: =SUM(H31:H43) -> 3048.9418 | I49: =SUM(I31:I43) -> 3048.9418 | ... AK49: =SUM(AK31:AK43) -> 3048.9418
A50: Total amortisation (enhancements) | B50: =SUM(B44:B48) -> 0 | C50: =SUM(C44:C48) -> 0 | D50: =SUM(D44:D48) -> 0 | E50: =SUM(E44:E48) -> 0 | F50: =SUM(F44:F48) -> 0 | G50: =SUM(G44:G48) -> 133.33333 | H50: =SUM(H44:H48) -> 133.33333 | I50: =SUM(I44:I48) -> 133.33333 | ... AK50: =SUM(AK44:AK48) -> 133.33333

Sheet Pricing
A1: Treatment pricing architecture — unit economics per variant
A2: Every recommended price is a formula: fully-loaded cost ÷ (1 − target margin − card-fee drag), then VAT, then rounding. Change the levers below or any machine/labour assumption and the whole price list moves. Current prices scraped from the live admin catalogue on 2026-08-28. Recorded COGS is empty on every variant, so consumables are researched estimates (blue).
A4: LEVERS
A5: Price for the VAT-registered state? (1 = yes) | B5: 1 | C5: 1 = recommended prices keep their margin AFTER VAT registration (the safe basis for a durable price list). 0 = price for today's unregistered state.
A6: Round recommended prices to nearest £ | B6: 1 | C6: 1, 5 or 9 — e.g. 5 gives £85/£90-style pricing.
A7: Course discount — 3 sessions | B7: 0.1 | C7: Per-session discount vs single price. Current live courses average ~15% off.
A8: Course discount — 6 sessions | B8: 0.15
A9: Course discount — 10 sessions | B9: 0.2
A11: TARGET CONTRIBUTION MARGIN BY MACHINE CLASS
A12: Class | B12: Target margin | C12: Margin = (net revenue − fully-loaded cost) ÷ net revenue. Fully-loaded cost includes consumables, machine energy, machine service & depreciation per hour, practitioner time and card fees.
A13: diode-laser | B13: 0.7
A14: laser-ipl-platform | B14: 0.7
A15: pico-laser-PLANNED | B15: 0.7
A16: co2-laser | B16: 0.7
A17: hifu | B17: 0.6
A18: rf-tightening | B18: 0.7
A19: hydrafacial-platform | B19: 0.65
A20: endosphere-vacuum | B20: 0.7
A21: microneedling-pen | B21: 0.65
A22: microdermabrasion | B22: 0.7
A23: microcurrent-led | B23: 0.7
A24: none-injectables | B24: 0.55
A25: none-manual | B25: 0.65
A28: Service | B28: Variant | C28: Category | D28: Status | E28: Machine class | F28: Internal min | G28: Machine min | H28: VAT % | I28: Current price £ | J28: Current net £ | K28: Consumables £ | L28: Machine energy £ | M28: Machine service £ | N28: Machine depreciation £ | O28: Practitioner £ | P28: Card fee £ | Q28: Fully-loaded cost £ | R28: Contribution £ | S28: Contribution % | T28: Target % | U28: Recommended net £ | V28: Recommended price £ | W28: Δ vs current | X28: Course 3 rec £ | Y28: Course 6 rec £ | Z28: Course 10 rec £ | AA28: Current course 6 £ | AB28: Current 6-course discount | AC28: Sellable
A29: Laser Hair Removal — Women | B29: Bikini Line | C29: aesthetics | D29: CONSULTATION | E29: diode-laser | F29: 20 | G29: 20 | H29: 0.2 | I29: 35 | J29: =I29/(1+H29*$B$5) -> 29.166667 | K29: 1.5 | L29: =G29/60*Machinery!$H$5*Assumptions!$B$23/100 -> 0.09 | M29: =G29/60*Machinery!$K$5 -> 0.2 | N29: =G29/60*Machinery!$L$5 -> 0.28571429 | O29: =F29/60*Assumptions!$B$20 -> 11.487923 | P29: =I29*Assumptions!$B$34*Assumptions!$B$35 -> 0.56525 | Q29: =SUM(K29:P29) -> 14.128887 | R29: =J29-Q29 -> 15.03778 | S29: =IF(J29=0,0,R29/J29) -> 0.51558102 | T29: =INDEX($B$13:$B$25,MATCH(E29,$A$13:$A$25,0)) -> 0.7 | U29: =SUM(K29:O29)/(1-T29-Assumptions!$B$34*Assumptions!$B$35*(1+H29*$B$5)) -> 48.334534 | V29: =MROUND(U29*(1+H29*$B$5),$B$6) -> 58 | W29: =IF(I29=0,0,V29/I29-1) -> 0.65714286 | X29: =MROUND(V29*3*(1-$B$7),$B$6) -> 157 | Y29: =MROUND(V29*6*(1-$B$8),$B$6) -> 296 | Z29: =MROUND(V29*10*(1-$B$9),$B$6) -> 464 | AC29: =IF(OR(D29="ACTIVE",D29="CONSULTATION"),1,0) -> 1
A30: Laser Hair Removal — Women | B30: Brazilian | C30: aesthetics | D30: CONSULTATION | E30: diode-laser | F30: 20 | G30: 20 | H30: 0.2 | I30: 43 | J30: =I30/(1+H30*$B$5) -> 35.833333 | K30: 1.5 | L30: =G30/60*Machinery!$H$5*Assumptions!$B$23/100 -> 0.09 | M30: =G30/60*Machinery!$K$5 -> 0.2 | N30: =G30/60*Machinery!$L$5 -> 0.28571429 | O30: =F30/60*Assumptions!$B$20 -> 11.487923 | P30: =I30*Assumptions!$B$34*Assumptions!$B$35 -> 0.69445 | Q30: =SUM(K30:P30) -> 14.258087 | R30: =J30-Q30 -> 21.575246 | S30: =IF(J30=0,0,R30/J30) -> 0.6020999 | T30: =INDEX($B$13:$B$25,MATCH(E30,$A$13:$A$25,0)) -> 0.7 | U30: =SUM(K30:O30)/(1-T30-Assumptions!$B$34*Assumptions!$B$35*(1+H30*$B$5)) -> 48.334534 | V30: =MROUND(U30*(1+H30*$B$5),$B$6) -> 58 | W30: =IF(I30=0,0,V30/I30-1) -> 0.34883721 | X30: =MROUND(V30*3*(1-$B$7),$B$6) -> 157 | Y30: =MROUND(V30*6*(1-$B$8),$B$6) -> 296 | Z30: =MROUND(V30*10*(1-$B$9),$B$6) -> 464 | AC30: =IF(OR(D30="ACTIVE",D30="CONSULTATION"),1,0) -> 1
A31: Laser Hair Removal — Women | B31: Hollywood Brazilian (incl. Peri-Anal) | C31: aesthetics | D31: CONSULTATION | E31: diode-laser | F31: 30 | G31: 30 | H31: 0.2 | I31: 54 | J31: =I31/(1+H31*$B$5) -> 45 | K31: 1.5 | L31: =G31/60*Machinery!$H$5*Assumptions!$B$23/100 -> 0.135 | M31: =G31/60*Machinery!$K$5 -> 0.3 | N31: =G31/60*Machinery!$L$5 -> 0.42857143 | O31: =F31/60*Assumptions!$B$20 -> 17.231884 | P31: =I31*Assumptions!$B$34*Assumptions!$B$35 -> 0.8721 | Q31: =SUM(K31:P31) -> 20.467555 | R31: =J31-Q31 -> 24.532445 | S31: =IF(J31=0,0,R31/J31) -> 0.54516543 | T31: =INDEX($B$13:$B$25,MATCH(E31,$A$13:$A$25,0)) -> 0.7 | U31: =SUM(K31:O31)/(1-T31-Assumptions!$B$34*Assumptions!$B$35*(1+H31*$B$5)) -> 69.829148 | V31: =MROUND(U31*(1+H31*$B$5),$B$6) -> 84 | W31: =IF(I31=0,0,V31/I31-1) -> 0.55555556 | X31: =MROUND(V31*3*(1-$B$7),$B$6) -> 227 | Y31: =MROUND(V31*6*(1-$B$8),$B$6) -> 428 | Z31: =MROUND(V31*10*(1-$B$9),$B$6) -> 672 | AC31: =IF(OR(D31="ACTIVE",D31="CONSULTATION"),1,0) -> 1
A32: Laser Hair Removal — Women | B32: Behind (Peri-Anal) | C32: aesthetics | D32: CONSULTATION | E32: diode-laser | F32: 20 | G32: 20 | H32: 0.2 | I32: 26 | J32: =I32/(1+H32*$B$5) -> 21.666667 | K32: 1.5 | L32: =G32/60*Machinery!$H$5*Assumptions!$B$23/100 -> 0.09 | M32: =G32/60*Machinery!$K$5 -> 0.2 | N32: =G32/60*Machinery!$L$5 -> 0.28571429 | O32: =F32/60*Assumptions!$B$20 -> 11.487923 | P32: =I32*Assumptions!$B$34*Assumptions!$B$35 -> 0.4199 | Q32: =SUM(K32:P32) -> 13.983537 | R32: =J32-Q32 -> 7.6831297 | S32: =IF(J32=0,0,R32/J32) -> 0.35460599 | T32: =INDEX($B$13:$B$25,MATCH(E32,$A$13:$A$25,0)) -> 0.7 | U32: =SUM(K32:O32)/(1-T32-Assumptions!$B$34*Assumptions!$B$35*(1+H32*$B$5)) -> 48.334534 | V32: =MROUND(U32*(1+H32*$B$5),$B$6) -> 58 | W32: =IF(I32=0,0,V32/I32-1) -> 1.2307692 | X32: =MROUND(V32*3*(1-$B$7),$B$6) -> 157 | Y32: =MROUND(V32*6*(1-$B$8),$B$6) -> 296 | Z32: =MROUND(V32*10*(1-$B$9),$B$6) -> 464 | AC32: =IF(OR(D32="ACTIVE",D32="CONSULTATION"),1,0) -> 1
A33: Laser Hair Removal — Women | B33: Brazilian/Bikini & Underarms | C33: aesthetics | D33: CONSULTATION | E33: diode-laser | F33: 30 | G33: 30 | H33: 0.2 | I33: 60 | J33: =I33/(1+H33*$B$5) -> 50 | K33: 1.5 | L33: =G33/60*Machinery!$H$5*Assumptions!$B$23/100 -> 0.135 | M33: =G33/60*Machinery!$K$5 -> 0.3 | N33: =G33/60*Machinery!$L$5 -> 0.42857143 | O33: =F33/60*Assumptions!$B$20 -> 17.231884 | P33: =I33*Assumptions!$B$34*Assumptions!$B$35 -> 0.969 | Q33: =SUM(K33:P33) -> 20.564455 | R33: =J33-Q33 -> 29.435545 | S33: =IF(J33=0,0,R33/J33) -> 0.58871089 | T33: =INDEX($B$13:$B$25,MATCH(E33,$A$13:$A$25,0)) -> 0.7 | U33: =SUM(K33:O33)/(1-T33-Assumptions!$B$34*Assumptions!$B$35*(1+H33*$B$5)) -> 69.829148 | V33: =MROUND(U33*(1+H33*$B$5),$B$6) -> 84 | W33: =IF(I33=0,0,V33/I33-1) -> 0.4 | X33: =MROUND(V33*3*(1-$B$7),$B$6) -> 227 | Y33: =MROUND(V33*6*(1-$B$8),$B$6) -> 428 | Z33: =MROUND(V33*10*(1-$B$9),$B$6) -> 672 | AC33: =IF(OR(D33="ACTIVE",D33="CONSULTATION"),1,0) -> 1
A34: Laser Hair Removal — Women | B34: Hollywood Brazilian (incl. Peri-Anal) & Underarms | C34: aesthetics | D34: CONSULTATION | E34: diode-laser | F34: 30 | G34: 30 | H34: 0.2 | I34: 64 | J34: =I34/(1+H34*$B$5) -> 53.333333 | K34: 1.5 | L34: =G34/60*Machinery!$H$5*Assumptions!$B$23/100 -> 0.135 | M34: =G34/60*Machinery!$K$5 -> 0.3 | N34: =G34/60*Machinery!$L$5 -> 0.42857143 | O34: =F34/60*Assumptions!$B$20 -> 17.231884 | P34: =I34*Assumptions!$B$34*Assumptions!$B$35 -> 1.0336 | Q34: =SUM(K34:P34) -> 20.629055 | R34: =J34-Q34 -> 32.704278 | S34: =IF(J34=0,0,R34/J34) -> 0.61320521 | T34: =INDEX($B$13:$B$25,MATCH(E34,$A$13:$A$25,0)) -> 0.7 | U34: =SUM(K34:O34)/(1-T34-Assumptions!$B$34*Assumptions!$B$35*(1+H34*$B$5)) -> 69.829148 | V34: =MROUND(U34*(1+H34*$B$5),$B$6) -> 84 | W34: =IF(I34=0,0,V34/I34-1) -> 0.3125 | X34: =MROUND(V34*3*(1-$B$7),$B$6) -> 227 | Y34: =MROUND(V34*6*(1-$B$8),$B$6) -> 428 | Z34: =MROUND(V34*10*(1-$B$9),$B$6) -> 672 | AC34: =IF(OR(D34="ACTIVE",D34="CONSULTATION"),1,0) -> 1
A35: Laser Hair Removal — Women | B35: Hollywood Brazilian (incl. Peri-Anal) & Full Legs | C35: aesthetics | D35: CONSULTATION | E35: diode-laser | F35: 40 | G35: 40 | H35: 0.2 | I35: 119 | J35: =I35/(1+H35*$B$5) -> 99.166667 | K35: 2 | L35: =G35/60*Machinery!$H$5*Assumptions!$B$23/100 -> 0.18 | M35: =G35/60*Machinery!$K$5 -> 0.4 | N35: =G35/60*Machinery!$L$5 -> 0.57142857 | O35: =F35/60*Assumptions!$B$20 -> 22.975845 | P35: =I35*Assumptions!$B$34*Assumptions!$B$35 -> 1.92185 | Q35: =SUM(K35:P35) -> 28.049124 | R35: =J35-Q35 -> 71.117543 | S35: =IF(J35=0,0,R35/J35) -> 0.71715169 | T35: =INDEX($B$13:$B$25,MATCH(E35,$A$13:$A$25,0)) -> 0.7 | U35: =SUM(K35:O35)/(1-T35-Assumptions!$B$34*Assumptions!$B$35*(1+H35*$B$5)) -> 93.105531 | V35: =MROUND(U35*(1+H35*$B$5),$B$6) -> 112 | W35: =IF(I35=0,0,V35/I35-1) -> -0.058823529 | X35: =MROUND(V35*3*(1-$B$7),$B$6) -> 302 | Y35: =MROUND(V35*6*(1-$B$8),$B$6) -> 571 | Z35: =MROUND(V35*10*(1-$B$9),$B$6) -> 896 | AC35: =IF(OR(D35="ACTIVE",D35="CONSULTATION"),1,0) -> 1
A36: Laser Hair Removal — Women | B36: Full Leg & Underarms | C36: aesthetics | D36: CONSULTATION | E36: diode-laser | F36: 30 | G36: 30 | H36: 0.2 | I36: 115 | J36: =I36/(1+H36*$B$5) -> 95.833333 | K36: 2 | L36: =G36/60*Machinery!$H$5*Assumptions!$B$23/100 -> 0.135 | M36: =G36/60*Machinery!$K$5 -> 0.3 | N36: =G36/60*Machinery!$L$5 -> 0.42857143 | O36: =F36/60*Assumptions!$B$20 -> 17.231884 | P36: =I36*Assumptions!$B$34*Assumptions!$B$35 -> 1.85725 | Q36: =SUM(K36:P36) -> 21.952705 | R36: =J36-Q36 -> 73.880628 | S36: =IF(J36=0,0,R36/J36) -> 0.77092829 | T36: =INDEX($B$13:$B$25,MATCH(E36,$A$13:$A$25,0)) -> 0.7 | U36: =SUM(K36:O36)/(1-T36-Assumptions!$B$34*Assumptions!$B$35*(1+H36*$B$5)) -> 71.610917 | V36: =MROUND(U36*(1+H36*$B$5),$B$6) -> 86 | W36: =IF(I36=0,0,V36/I36-1) -> -0.25217391 | X36: =MROUND(V36*3*(1-$B$7),$B$6) -> 232 | Y36: =MROUND(V36*6*(1-$B$8),$B$6) -> 439 | Z36: =MROUND(V36*10*(1-$B$9),$B$6) -> 688 | AC36: =IF(OR(D36="ACTIVE",D36="CONSULTATION"),1,0) -> 1
A37: Laser Hair Removal — Women | B37: Lower Leg, Brazilian/Bikini & Underarms | C37: aesthetics | D37: CONSULTATION | E37: diode-laser | F37: 40 | G37: 40 | H37: 0.2 | I37: 95 | J37: =I37/(1+H37*$B$5) -> 79.166667 | K37: 2 | L37: =G37/60*Machinery!$H$5*Assumptions!$B$23/100 -> 0.18 | M37: =G37/60*Machinery!$K$5 -> 0.4 | N37: =G37/60*Machinery!$L$5 -> 0.57142857 | O37: =F37/60*Assumptions!$B$20 -> 22.975845 | P37: =I37*Assumptions!$B$34*Assumptions!$B$35 -> 1.53425 | Q37: =SUM(K37:P37) -> 27.661524 | R37: =J37-Q37 -> 51.505143 | S37: =IF(J37=0,0,R37/J37) -> 0.65059128 | T37: =INDEX($B$13:$B$25,MATCH(E37,$A$13:$A$25,0)) -> 0.7 | U37: =SUM(K37:O37)/(1-T37-Assumptions!$B$34*Assumptions!$B$35*(1+H37*$B$5)) -> 93.105531 | V37: =MROUND(U37*(1+H37*$B$5),$B$6) -> 112 | W37: =IF(I37=0,0,V37/I37-1) -> 0.17894737 | X37: =MROUND(V37*3*(1-$B$7),$B$6) -> 302 | Y37: =MROUND(V37*6*(1-$B$8),$B$6) -> 571 | Z37: =MROUND(V37*10*(1-$B$9),$B$6) -> 896 | AC37: =IF(OR(D37="ACTIVE",D37="CONSULTATION"),1,0) -> 1
A38: Laser Hair Removal — Women | B38: Full Legs, Brazilian/Bikini & Underarms | C38: aesthetics | D38: CONSULTATION | E38: diode-laser | F38: 50 | G38: 50 | H38: 0.2 | I38: 121 | J38: =I38/(1+H38*$B$5) -> 100.83333 | K38: 2 | L38: =G38/60*Machinery!$H$5*Assumptions!$B$23/100 -> 0.225 | M38: =G38/60*Machinery!$K$5 -> 0.5 | N38: =G38/60*Machinery!$L$5 -> 0.71428571 | O38: =F38/60*Assumptions!$B$20 -> 28.719807 | P38: =I38*Assumptions!$B$34*Assumptions!$B$35 -> 1.95415 | Q38: =SUM(K38:P38) -> 34.113242 | R38: =J38-Q38 -> 66.720091 | S38: =IF(J38=0,0,R38/J38) -> 0.66168685 | T38: =INDEX($B$13:$B$25,MATCH(E38,$A$13:$A$25,0)) -> 0.7 | U38: =SUM(K38:O38)/(1-T38-Assumptions!$B$34*Assumptions!$B$35*(1+H38*$B$5)) -> 114.60014 | V38: =MROUND(U38*(1+H38*$B$5),$B$6) -> 138 | W38: =IF(I38=0,0,V38/I38-1) -> 0.14049587 | X38: =MROUND(V38*3*(1-$B$7),$B$6) -> 373 | Y38: =MROUND(V38*6*(1-$B$8),$B$6) -> 704 | Z38: =MROUND(V38*10*(1-$B$9),$B$6) -> 1104 | AC38: =IF(OR(D38="ACTIVE",D38="CONSULTATION"),1,0) -> 1
A39: Laser Hair Removal — Women | B39: Full Legs, Hollywood Brazilian (incl. Peri-Anal) & Underarms | C39: aesthetics | D39: CONSULTATION | E39: diode-laser | F39: 50 | G39: 50 | H39: 0.2 | I39: 149 | J39: =I39/(1+H39*$B$5) -> 124.16667 | K39: 2 | L39: =G39/60*Machinery!$H$5*Assumptions!$B$23/100 -> 0.225 | M39: =G39/60*Machinery!$K$5 -> 0.5 | N39: =G39/60*Machinery!$L$5 -> 0.71428571 | O39: =F39/60*Assumptions!$B$20 -> 28.719807 | P39: =I39*Assumptions!$B$34*Assumptions!$B$35 -> 2.40635 | Q39: =SUM(K39:P39) -> 34.565442 | R39: =J39-Q39 -> 89.601224 | S39: =IF(J39=0,0,R39/J39) -> 0.7216206 | T39: =INDEX($B$13:$B$25,MATCH(E39,$A$13:$A$25,0)) -> 0.7 | U39: =SUM(K39:O39)/(1-T39-Assumptions!$B$34*Assumptions!$B$35*(1+H39*$B$5)) -> 114.60014 | V39: =MROUND(U39*(1+H39*$B$5),$B$6) -> 138 | W39: =IF(I39=0,0,V39/I39-1) -> -0.073825503 | X39: =MROUND(V39*3*(1-$B$7),$B$6) -> 373 | Y39: =MROUND(V39*6*(1-$B$8),$B$6) -> 704 | Z39: =MROUND(V39*10*(1-$B$9),$B$6) -> 1104 | AC39: =IF(OR(D39="ACTIVE",D39="CONSULTATION"),1,0) -> 1
A40: Laser Hair Removal — Women | B40: Eyebrows (middle, above bridge of nose) | C40: aesthetics | D40: CONSULTATION | E40: diode-laser | F40: 15 | G40: 15 | H40: 0.2 | I40: 11 | J40: =I40/(1+H40*$B$5) -> 9.1666667 | K40: 1 | L40: =G40/60*Machinery!$H$5*Assumptions!$B$23/100 -> 0.0675 | M40: =G40/60*Machinery!$K$5 -> 0.15 | N40: =G40/60*Machinery!$L$5 -> 0.21428571 | O40: =F40/60*Assumptions!$B$20 -> 8.615942 | P40: =I40*Assumptions!$B$34*Assumptions!$B$35 -> 0.17765 | Q40: =SUM(K40:P40) -> 10.225378 | R40: =J40-Q40 -> -1.0587111 | S40: =IF(J40=0,0,R40/J40) -> -0.11549575 | T40: =INDEX($B$13:$B$25,MATCH(E40,$A$13:$A$25,0)) -> 0.7 | U40: =SUM(K40:O40)/(1-T40-Assumptions!$B$34*Assumptions!$B$35*(1+H40*$B$5)) -> 35.805458 | V40: =MROUND(U40*(1+H40*$B$5),$B$6) -> 43 | W40: =IF(I40=0,0,V40/I40-1) -> 2.9090909 | X40: =MROUND(V40*3*(1-$B$7),$B$6) -> 116 | Y40: =MROUND(V40*6*(1-$B$8),$B$6) -> 219 | Z40: =MROUND(V40*10*(1-$B$9),$B$6) -> 344 | AC40: =IF(OR(D40="ACTIVE",D40="CONSULTATION"),1,0) -> 1
... A88: Laser Hair Removal — Men | B88: Full Legs | C88: aesthetics | D88: ACTIVE | E88: diode-laser | F88: 60 | G88: 60 | H88: 0.2 | I88: 147 | J88: =I88/(1+H88*$B$5) -> 122.5 | K88: 2.5 | L88: =G88/60*Machinery!$H$5*Assumptions!$B$23/100 -> 0.27 | M88: =G88/60*Machinery!$K$5 -> 0.6 | N88: =G88/60*Machinery!$L$5 -> 0.85714286 | O88: =F88/60*Assumptions!$B$20 -> 34.463768 | P88: =I88*Assumptions!$B$34*Assumptions!$B$35 -> 2.37405 | Q88: =SUM(K88:P88) -> 41.064961 | R88: =J88-Q88 -> 81.435039 | S88: =IF(J88=0,0,R88/J88) -> 0.66477583 | T88: =INDEX($B$13:$B$25,MATCH(E88,$A$13:$A$25,0)) -> 0.7 | U88: =SUM(K88:O88)/(1-T88-Assumptions!$B$34*Assumptions!$B$35*(1+H88*$B$5)) -> 137.87653 | V88: =MROUND(U88*(1+H88*$B$5),$B$6) -> 165 | W88: =IF(I88=0,0,V88/I88-1) -> 0.12244898 | X88: =MROUND(V88*3*(1-$B$7),$B$6) -> 446 | Y88: =MROUND(V88*6*(1-$B$8),$B$6) -> 842 | Z88: =MROUND(V88*10*(1-$B$9),$B$6) -> 1320 | AC88: =IF(OR(D88="ACTIVE",D88="CONSULTATION"),1,0) -> 1
A89: Intimate Rejuvenation | B89: CO2 Laser Rejuvenation | C89: aesthetics | D89: COMING_SOON | E89: co2-laser | F89: 40 | G89: 40 | H89: 0.2 | I89: 690 | J89: =I89/(1+H89*$B$5) -> 575 | K89: 50 | L89: =G89/60*Machinery!$H$8*Assumptions!$B$23/100 -> 0.072 | M89: =G89/60*Machinery!$K$8 -> 27.777778 | N89: =G89/60*Machinery!$L$8 -> 42.438272 | O89: =F89/60*Assumptions!$B$20 -> 22.975845 | P89: =I89*Assumptions!$B$34*Assumptions!$B$35 -> 11.1435 | Q89: =SUM(K89:P89) -> 154.40739 | R89: =J89-Q89 -> 420.59261 | S89: =IF(J89=0,0,R89/J89) -> 0.7314654 | T89: =INDEX($B$13:$B$25,MATCH(E89,$A$13:$A$25,0)) -> 0.7 | U89: =SUM(K89:O89)/(1-T89-Assumptions!$B$34*Assumptions!$B$35*(1+H89*$B$5)) -> 510.52632 | V89: =MROUND(U89*(1+H89*$B$5),$B$6) -> 613 | W89: =IF(I89=0,0,V89/I89-1) -> -0.1115942 | X89: =MROUND(V89*3*(1-$B$7),$B$6) -> 1655 | Y89: =MROUND(V89*6*(1-$B$8),$B$6) -> 3126 | Z89: =MROUND(V89*10*(1-$B$9),$B$6) -> 4904 | AC89: =IF(OR(D89="ACTIVE",D89="CONSULTATION"),1,0) -> 0
A90: Intimate Rejuvenation | B90: Intimate Area Whitening | C90: aesthetics | D90: COMING_SOON | E90: co2-laser | F90: 40 | G90: 40 | H90: 0.2 | I90: 690 | J90: =I90/(1+H90*$B$5) -> 575 | K90: 50 | L90: =G90/60*Machinery!$H$8*Assumptions!$B$23/100 -> 0.072 | M90: =G90/60*Machinery!$K$8 -> 27.777778 | N90: =G90/60*Machinery!$L$8 -> 42.438272 | O90: =F90/60*Assumptions!$B$20 -> 22.975845 | P90: =I90*Assumptions!$B$34*Assumptions!$B$35 -> 11.1435 | Q90: =SUM(K90:P90) -> 154.40739 | R90: =J90-Q90 -> 420.59261 | S90: =IF(J90=0,0,R90/J90) -> 0.7314654 | T90: =INDEX($B$13:$B$25,MATCH(E90,$A$13:$A$25,0)) -> 0.7 | U90: =SUM(K90:O90)/(1-T90-Assumptions!$B$34*Assumptions!$B$35*(1+H90*$B$5)) -> 510.52632 | V90: =MROUND(U90*(1+H90*$B$5),$B$6) -> 613 | W90: =IF(I90=0,0,V90/I90-1) -> -0.1115942 | X90: =MROUND(V90*3*(1-$B$7),$B$6) -> 1655 | Y90: =MROUND(V90*6*(1-$B$8),$B$6) -> 3126 | Z90: =MROUND(V90*10*(1-$B$9),$B$6) -> 4904 | AC90: =IF(OR(D90="ACTIVE",D90="CONSULTATION"),1,0) -> 0
A91: Laser Pigmentation Removal | B91: Face | C91: aesthetics | D91: ACTIVE | E91: laser-ipl-platform | F91: 30 | G91: 30 | H91: 0.2 | I91: 150 | J91: =I91/(1+H91*$B$5) -> 125 | K91: 2 | L91: =G91/60*Machinery!$H$6*Assumptions!$B$23/100 -> 0.108 | M91: =G91/60*Machinery!$K$6 -> 4.1666667 | N91: =G91/60*Machinery!$L$6 -> 7.8125 | O91: =F91/60*Assumptions!$B$20 -> 17.231884 | P91: =I91*Assumptions!$B$34*Assumptions!$B$35 -> 2.4225 | Q91: =SUM(K91:P91) -> 33.741551 | R91: =J91-Q91 -> 91.258449 | S91: =IF(J91=0,0,R91/J91) -> 0.73006759 | T91: =INDEX($B$13:$B$25,MATCH(E91,$A$13:$A$25,0)) -> 0.7 | U91: =SUM(K91:O91)/(1-T91-Assumptions!$B$34*Assumptions!$B$35*(1+H91*$B$5)) -> 111.60662 | V91: =MROUND(U91*(1+H91*$B$5),$B$6) -> 134 | W91: =IF(I91=0,0,V91/I91-1) -> -0.10666667 | X91: =MROUND(V91*3*(1-$B$7),$B$6) -> 362 | Y91: =MROUND(V91*6*(1-$B$8),$B$6) -> 683 | Z91: =MROUND(V91*10*(1-$B$9),$B$6) -> 1072 | AC91: =IF(OR(D91="ACTIVE",D91="CONSULTATION"),1,0) -> 1
A92: Vascular Lesions Treatment | B92: Face | C92: aesthetics | D92: ACTIVE | E92: laser-ipl-platform | F92: 30 | G92: 30 | H92: 0.2 | I92: 150 | J92: =I92/(1+H92*$B$5) -> 125 | K92: 2 | L92: =G92/60*Machinery!$H$6*Assumptions!$B$23/100 -> 0.108 | M92: =G92/60*Machinery!$K$6 -> 4.1666667 | N92: =G92/60*Machinery!$L$6 -> 7.8125 | O92: =F92/60*Assumptions!$B$20 -> 17.231884 | P92: =I92*Assumptions!$B$34*Assumptions!$B$35 -> 2.4225 | Q92: =SUM(K92:P92) -> 33.741551 | R92: =J92-Q92 -> 91.258449 | S92: =IF(J92=0,0,R92/J92) -> 0.73006759 | T92: =INDEX($B$13:$B$25,MATCH(E92,$A$13:$A$25,0)) -> 0.7 | U92: =SUM(K92:O92)/(1-T92-Assumptions!$B$34*Assumptions!$B$35*(1+H92*$B$5)) -> 111.60662 | V92: =MROUND(U92*(1+H92*$B$5),$B$6) -> 134 | W92: =IF(I92=0,0,V92/I92-1) -> -0.10666667 | X92: =MROUND(V92*3*(1-$B$7),$B$6) -> 362 | Y92: =MROUND(V92*6*(1-$B$8),$B$6) -> 683 | Z92: =MROUND(V92*10*(1-$B$9),$B$6) -> 1072 | AC92: =IF(OR(D92="ACTIVE",D92="CONSULTATION"),1,0) -> 1
A93: Spider Veins Removal | B93: Nose Thread Vein | C93: aesthetics | D93: CONSULTATION | E93: laser-ipl-platform | F93: 25 | G93: 25 | H93: 0.2 | I93: 230 | J93: =I93/(1+H93*$B$5) -> 191.66667 | K93: 2 | L93: =G93/60*Machinery!$H$6*Assumptions!$B$23/100 -> 0.09 | M93: =G93/60*Machinery!$K$6 -> 3.4722222 | N93: =G93/60*Machinery!$L$6 -> 6.5104167 | O93: =F93/60*Assumptions!$B$20 -> 14.359903 | P93: =I93*Assumptions!$B$34*Assumptions!$B$35 -> 3.7145 | Q93: =SUM(K93:P93) -> 30.147042 | R93: =J93-Q93 -> 161.51962 | S93: =IF(J93=0,0,R93/J93) -> 0.84271108 | T93: =INDEX($B$13:$B$25,MATCH(E93,$A$13:$A$25,0)) -> 0.7 | U93: =SUM(K93:O93)/(1-T93-Assumptions!$B$34*Assumptions!$B$35*(1+H93*$B$5)) -> 94.193366 | V93: =MROUND(U93*(1+H93*$B$5),$B$6) -> 113 | W93: =IF(I93=0,0,V93/I93-1) -> -0.50869565 | X93: =MROUND(V93*3*(1-$B$7),$B$6) -> 305 | Y93: =MROUND(V93*6*(1-$B$8),$B$6) -> 576 | Z93: =MROUND(V93*10*(1-$B$9),$B$6) -> 904 | AC93: =IF(OR(D93="ACTIVE",D93="CONSULTATION"),1,0) -> 1
A94: Spider Veins Removal | B94: Cheek Thread Vein | C94: aesthetics | D94: CONSULTATION | E94: laser-ipl-platform | F94: 30 | G94: 30 | H94: 0.2 | I94: 296 | J94: =I94/(1+H94*$B$5) -> 246.66667 | K94: 2 | L94: =G94/60*Machinery!$H$6*Assumptions!$B$23/100 -> 0.108 | M94: =G94/60*Machinery!$K$6 -> 4.1666667 | N94: =G94/60*Machinery!$L$6 -> 7.8125 | O94: =F94/60*Assumptions!$B$20 -> 17.231884 | P94: =I94*Assumptions!$B$34*Assumptions!$B$35 -> 4.7804 | Q94: =SUM(K94:P94) -> 36.099451 | R94: =J94-Q94 -> 210.56722 | S94: =IF(J94=0,0,R94/J94) -> 0.85365088 | T94: =INDEX($B$13:$B$25,MATCH(E94,$A$13:$A$25,0)) -> 0.7 | U94: =SUM(K94:O94)/(1-T94-Assumptions!$B$34*Assumptions!$B$35*(1+H94*$B$5)) -> 111.60662 | V94: =MROUND(U94*(1+H94*$B$5),$B$6) -> 134 | W94: =IF(I94=0,0,V94/I94-1) -> -0.5472973 | X94: =MROUND(V94*3*(1-$B$7),$B$6) -> 362 | Y94: =MROUND(V94*6*(1-$B$8),$B$6) -> 683 | Z94: =MROUND(V94*10*(1-$B$9),$B$6) -> 1072 | AC94: =IF(OR(D94="ACTIVE",D94="CONSULTATION"),1,0) -> 1
A95: Spider Veins Removal | B95: Leg Thread Vein | C95: aesthetics | D95: CONSULTATION | E95: laser-ipl-platform | F95: 40 | G95: 40 | H95: 0.2 | I95: 417 | J95: =I95/(1+H95*$B$5) -> 347.5 | K95: 3 | L95: =G95/60*Machinery!$H$6*Assumptions!$B$23/100 -> 0.144 | M95: =G95/60*Machinery!$K$6 -> 5.5555556 | N95: =G95/60*Machinery!$L$6 -> 10.416667 | O95: =F95/60*Assumptions!$B$20 -> 22.975845 | P95: =I95*Assumptions!$B$34*Assumptions!$B$35 -> 6.73455 | Q95: =SUM(K95:P95) -> 48.826618 | R95: =J95-Q95 -> 298.67338 | S95: =IF(J95=0,0,R95/J95) -> 0.85949175 | T95: =INDEX($B$13:$B$25,MATCH(E95,$A$13:$A$25,0)) -> 0.7 | U95: =SUM(K95:O95)/(1-T95-Assumptions!$B$34*Assumptions!$B$35*(1+H95*$B$5)) -> 149.99668 | V95: =MROUND(U95*(1+H95*$B$5),$B$6) -> 180 | W95: =IF(I95=0,0,V95/I95-1) -> -0.56834532 | X95: =MROUND(V95*3*(1-$B$7),$B$6) -> 486 | Y95: =MROUND(V95*6*(1-$B$8),$B$6) -> 918 | Z95: =MROUND(V95*10*(1-$B$9),$B$6) -> 1440 | AC95: =IF(OR(D95="ACTIVE",D95="CONSULTATION"),1,0) -> 1
A96: Carbon Laser Facial (Hollywood Peel) | B96: Neck | C96: aesthetics | D96: INACTIVE | E96: laser-ipl-platform | F96: 30 | G96: 30 | H96: 0.2 | I96: 90 | J96: =I96/(1+H96*$B$5) -> 75 | K96: 5 | L96: =G96/60*Machinery!$H$6*Assumptions!$B$23/100 -> 0.108 | M96: =G96/60*Machinery!$K$6 -> 4.1666667 | N96: =G96/60*Machinery!$L$6 -> 7.8125 | O96: =F96/60*Assumptions!$B$20 -> 17.231884 | P96: =I96*Assumptions!$B$34*Assumptions!$B$35 -> 1.4535 | Q96: =SUM(K96:P96) -> 35.772551 | R96: =J96-Q96 -> 39.227449 | S96: =IF(J96=0,0,R96/J96) -> 0.52303266 | T96: =INDEX($B$13:$B$25,MATCH(E96,$A$13:$A$25,0)) -> 0.7 | U96: =SUM(K96:O96)/(1-T96-Assumptions!$B$34*Assumptions!$B$35*(1+H96*$B$5)) -> 122.29724 | V96: =MROUND(U96*(1+H96*$B$5),$B$6) -> 147 | W96: =IF(I96=0,0,V96/I96-1) -> 0.63333333 | X96: =MROUND(V96*3*(1-$B$7),$B$6) -> 397 | Y96: =MROUND(V96*6*(1-$B$8),$B$6) -> 750 | Z96: =MROUND(V96*10*(1-$B$9),$B$6) -> 1176 | AC96: =IF(OR(D96="ACTIVE",D96="CONSULTATION"),1,0) -> 0
A97: Carbon Laser Facial (Hollywood Peel) | B97: Full Face | C97: aesthetics | D97: INACTIVE | E97: laser-ipl-platform | F97: 50 | G97: 50 | H97: 0.2 | I97: 121 | J97: =I97/(1+H97*$B$5) -> 100.83333 | K97: 5 | L97: =G97/60*Machinery!$H$6*Assumptions!$B$23/100 -> 0.18 | M97: =G97/60*Machinery!$K$6 -> 6.9444444 | N97: =G97/60*Machinery!$L$6 -> 13.020833 | O97: =F97/60*Assumptions!$B$20 -> 28.719807 | P97: =I97*Assumptions!$B$34*Assumptions!$B$35 -> 1.95415 | Q97: =SUM(K97:P97) -> 55.819235 | R97: =J97-Q97 -> 45.014099 | S97: =IF(J97=0,0,R97/J97) -> 0.44642081 | T97: =INDEX($B$13:$B$25,MATCH(E97,$A$13:$A$25,0)) -> 0.7 | U97: =SUM(K97:O97)/(1-T97-Assumptions!$B$34*Assumptions!$B$35*(1+H97*$B$5)) -> 191.95027 | V97: =MROUND(U97*(1+H97*$B$5),$B$6) -> 230 | W97: =IF(I97=0,0,V97/I97-1) -> 0.90082645 | X97: =MROUND(V97*3*(1-$B$7),$B$6) -> 621 | Y97: =MROUND(V97*6*(1-$B$8),$B$6) -> 1173 | Z97: =MROUND(V97*10*(1-$B$9),$B$6) -> 1840 | AC97: =IF(OR(D97="ACTIVE",D97="CONSULTATION"),1,0) -> 0
A98: Carbon Laser Facial (Hollywood Peel) | B98: Face & Neck | C98: aesthetics | D98: INACTIVE | E98: laser-ipl-platform | F98: 60 | G98: 60 | H98: 0.2 | I98: 205 | J98: =I98/(1+H98*$B$5) -> 170.83333 | K98: 6 | L98: =G98/60*Machinery!$H$6*Assumptions!$B$23/100 -> 0.216 | M98: =G98/60*Machinery!$K$6 -> 8.3333333 | N98: =G98/60*Machinery!$L$6 -> 15.625 | O98: =F98/60*Assumptions!$B$20 -> 34.463768 | P98: =I98*Assumptions!$B$34*Assumptions!$B$35 -> 3.31075 | Q98: =SUM(K98:P98) -> 67.948851 | R98: =J98-Q98 -> 102.88448 | S98: =IF(J98=0,0,R98/J98) -> 0.60225063 | T98: =INDEX($B$13:$B$25,MATCH(E98,$A$13:$A$25,0)) -> 0.7 | U98: =SUM(K98:O98)/(1-T98-Assumptions!$B$34*Assumptions!$B$35*(1+H98*$B$5)) -> 230.34032 | V98: =MROUND(U98*(1+H98*$B$5),$B$6) -> 276 | W98: =IF(I98=0,0,V98/I98-1) -> 0.34634146 | X98: =MROUND(V98*3*(1-$B$7),$B$6) -> 745 | Y98: =MROUND(V98*6*(1-$B$8),$B$6) -> 1408 | Z98: =MROUND(V98*10*(1-$B$9),$B$6) -> 2208 | AC98: =IF(OR(D98="ACTIVE",D98="CONSULTATION"),1,0) -> 0
A99: Carbon Laser Facial (Hollywood Peel) | B99: Face, Neck & Décolleté | C99: aesthetics | D99: INACTIVE | E99: laser-ipl-platform | F99: 70 | G99: 70 | H99: 0.2 | I99: 237 | J99: =I99/(1+H99*$B$5) -> 197.5 | K99: 7 | L99: =G99/60*Machinery!$H$6*Assumptions!$B$23/100 -> 0.252 | M99: =G99/60*Machinery!$K$6 -> 9.7222222 | N99: =G99/60*Machinery!$L$6 -> 18.229167 | O99: =F99/60*Assumptions!$B$20 -> 40.207729 | P99: =I99*Assumptions!$B$34*Assumptions!$B$35 -> 3.82755 | Q99: =SUM(K99:P99) -> 79.238668 | R99: =J99-Q99 -> 118.26133 | S99: =IF(J99=0,0,R99/J99) -> 0.59879155 | T99: =INDEX($B$13:$B$25,MATCH(E99,$A$13:$A$25,0)) -> 0.7 | U99: =SUM(K99:O99)/(1-T99-Assumptions!$B$34*Assumptions!$B$35*(1+H99*$B$5)) -> 268.73038 | V99: =MROUND(U99*(1+H99*$B$5),$B$6) -> 322 | W99: =IF(I99=0,0,V99/I99-1) -> 0.35864979 | X99: =MROUND(V99*3*(1-$B$7),$B$6) -> 869 | Y99: =MROUND(V99*6*(1-$B$8),$B$6) -> 1642 | Z99: =MROUND(V99*10*(1-$B$9),$B$6) -> 2576 | AC99: =IF(OR(D99="ACTIVE",D99="CONSULTATION"),1,0) -> 0
A100: Laser Fungal Nail Treatment | B100: 1 Foot | C100: aesthetics | D100: COMING_SOON | E100: laser-ipl-platform | F100: 30 | G100: 30 | H100: 0.2 | I100: 79 | J100: =I100/(1+H100*$B$5) -> 65.833333 | K100: 2 | L100: =G100/60*Machinery!$H$6*Assumptions!$B$23/100 -> 0.108 | M100: =G100/60*Machinery!$K$6 -> 4.1666667 | N100: =G100/60*Machinery!$L$6 -> 7.8125 | O100: =F100/60*Assumptions!$B$20 -> 17.231884 | P100: =I100*Assumptions!$B$34*Assumptions!$B$35 -> 1.27585 | Q100: =SUM(K100:P100) -> 32.594901 | R100: =J100-Q100 -> 33.238433 | S100: =IF(J100=0,0,R100/J100) -> 0.50488758 | T100: =INDEX($B$13:$B$25,MATCH(E100,$A$13:$A$25,0)) -> 0.7 | U100: =SUM(K100:O100)/(1-T100-Assumptions!$B$34*Assumptions!$B$35*(1+H100*$B$5)) -> 111.60662 | V100: =MROUND(U100*(1+H100*$B$5),$B$6) -> 134 | W100: =IF(I100=0,0,V100/I100-1) -> 0.69620253 | X100: =MROUND(V100*3*(1-$B$7),$B$6) -> 362 | Y100: =MROUND(V100*6*(1-$B$8),$B$6) -> 683 | Z100: =MROUND(V100*10*(1-$B$9),$B$6) -> 1072 | AC100: =IF(OR(D100="ACTIVE",D100="CONSULTATION"),1,0) -> 0
A101: Laser Fungal Nail Treatment | B101: 2 Feet | C101: aesthetics | D101: COMING_SOON | E101: laser-ipl-platform | F101: 40 | G101: 40 | H101: 0.2 | I101: 100 | J101: =I101/(1+H101*$B$5) -> 83.333333 | K101: 2 | L101: =G101/60*Machinery!$H$6*Assumptions!$B$23/100 -> 0.144 | M101: =G101/60*Machinery!$K$6 -> 5.5555556 | N101: =G101/60*Machinery!$L$6 -> 10.416667 | O101: =F101/60*Assumptions!$B$20 -> 22.975845 | P101: =I101*Assumptions!$B$34*Assumptions!$B$35 -> 1.615 | Q101: =SUM(K101:P101) -> 42.707068 | R101: =J101-Q101 -> 40.626266 | S101: =IF(J101=0,0,R101/J101) -> 0.48751519 | T101: =INDEX($B$13:$B$25,MATCH(E101,$A$13:$A$25,0)) -> 0.7 | U101: =SUM(K101:O101)/(1-T101-Assumptions!$B$34*Assumptions!$B$35*(1+H101*$B$5)) -> 146.43314 | V101: =MROUND(U101*(1+H101*$B$5),$B$6) -> 176 | W101: =IF(I101=0,0,V101/I101-1) -> 0.76 | X101: =MROUND(V101*3*(1-$B$7),$B$6) -> 475 | Y101: =MROUND(V101*6*(1-$B$8),$B$6) -> 898 | Z101: =MROUND(V101*10*(1-$B$9),$B$6) -> 1408 | AC101: =IF(OR(D101="ACTIVE",D101="CONSULTATION"),1,0) -> 0
A102: Laser Tattoo Removal | B102: Very Small (1–3 cm) | C102: aesthetics | D102: COMING_SOON | E102: pico-laser-PLANNED | F102: 20 | G102: 20 | H102: 0.2 | I102: 44 | J102: =I102/(1+H102*$B$5) -> 36.666667 | K102: 1 | L102: =G102/60*Machinery!$H$7*Assumptions!$B$23/100 -> 0.09 | M102: =G102/60*Machinery!$K$7 -> 8.3333333 | N102: =G102/60*Machinery!$L$7 -> 0 | O102: =F102/60*Assumptions!$B$20 -> 11.487923 | P102: =I102*Assumptions!$B$34*Assumptions!$B$35 -> 0.7106 | Q102: =SUM(K102:P102) -> 21.621856 | R102: =J102-Q102 -> 15.044811 | S102: =IF(J102=0,0,R102/J102) -> 0.41031302 | T102: =INDEX($B$13:$B$25,MATCH(E102,$A$13:$A$25,0)) -> 0.7 | U102: =SUM(K102:O102)/(1-T102-Assumptions!$B$34*Assumptions!$B$35*(1+H102*$B$5)) -> 74.518053 | V102: =MROUND(U102*(1+H102*$B$5),$B$6) -> 89 | W102: =IF(I102=0,0,V102/I102-1) -> 1.0227273 | X102: =MROUND(V102*3*(1-$B$7),$B$6) -> 240 | Y102: =MROUND(V102*6*(1-$B$8),$B$6) -> 454 | Z102: =MROUND(V102*10*(1-$B$9),$B$6) -> 712 | AC102: =IF(OR(D102="ACTIVE",D102="CONSULTATION"),1,0) -> 0
A103: Laser Tattoo Removal | B103: Small (4–6 cm) | C103: aesthetics | D103: COMING_SOON | E103: pico-laser-PLANNED | F103: 20 | G103: 20 | H103: 0.2 | I103: 66 | J103: =I103/(1+H103*$B$5) -> 55 | K103: 1 | L103: =G103/60*Machinery!$H$7*Assumptions!$B$23/100 -> 0.09 | M103: =G103/60*Machinery!$K$7 -> 8.3333333 | N103: =G103/60*Machinery!$L$7 -> 0 | O103: =F103/60*Assumptions!$B$20 -> 11.487923 | P103: =I103*Assumptions!$B$34*Assumptions!$B$35 -> 1.0659 | Q103: =SUM(K103:P103) -> 21.977156 | R103: =J103-Q103 -> 33.022844 | S103: =IF(J103=0,0,R103/J103) -> 0.60041534 | T103: =INDEX($B$13:$B$25,MATCH(E103,$A$13:$A$25,0)) -> 0.7 | U103: =SUM(K103:O103)/(1-T103-Assumptions!$B$34*Assumptions!$B$35*(1+H103*$B$5)) -> 74.518053 | V103: =MROUND(U103*(1+H103*$B$5),$B$6) -> 89 | W103: =IF(I103=0,0,V103/I103-1) -> 0.34848485 | X103: =MROUND(V103*3*(1-$B$7),$B$6) -> 240 | Y103: =MROUND(V103*6*(1-$B$8),$B$6) -> 454 | Z103: =MROUND(V103*10*(1-$B$9),$B$6) -> 712 | AC103: =IF(OR(D103="ACTIVE",D103="CONSULTATION"),1,0) -> 0
A104: Laser Tattoo Removal | B104: Medium (7–15 cm) | C104: aesthetics | D104: COMING_SOON | E104: pico-laser-PLANNED | F104: 25 | G104: 25 | H104: 0.2 | I104: 116 | J104: =I104/(1+H104*$B$5) -> 96.666667 | K104: 1.5 | L104: =G104/60*Machinery!$H$7*Assumptions!$B$23/100 -> 0.1125 | M104: =G104/60*Machinery!$K$7 -> 10.416667 | N104: =G104/60*Machinery!$L$7 -> 0 | O104: =F104/60*Assumptions!$B$20 -> 14.359903 | P104: =I104*Assumptions!$B$34*Assumptions!$B$35 -> 1.8734 | Q104: =SUM(K104:P104) -> 28.26247 | R104: =J104-Q104 -> 68.404197 | S104: =IF(J104=0,0,R104/J104) -> 0.70762962 | T104: =INDEX($B$13:$B$25,MATCH(E104,$A$13:$A$25,0)) -> 0.7 | U104: =SUM(K104:O104)/(1-T104-Assumptions!$B$34*Assumptions!$B$35*(1+H104*$B$5)) -> 94.038451 | V104: =MROUND(U104*(1+H104*$B$5),$B$6) -> 113 | W104: =IF(I104=0,0,V104/I104-1) -> -0.025862069 | X104: =MROUND(V104*3*(1-$B$7),$B$6) -> 305 | Y104: =MROUND(V104*6*(1-$B$8),$B$6) -> 576 | Z104: =MROUND(V104*10*(1-$B$9),$B$6) -> 904 | AC104: =IF(OR(D104="ACTIVE",D104="CONSULTATION"),1,0) -> 0
A105: Laser Tattoo Removal | B105: Large (16–20 cm) | C105: aesthetics | D105: COMING_SOON | E105: pico-laser-PLANNED | F105: 35 | G105: 35 | H105: 0.2 | I105: 165 | J105: =I105/(1+H105*$B$5) -> 137.5 | K105: 2 | L105: =G105/60*Machinery!$H$7*Assumptions!$B$23/100 -> 0.1575 | M105: =G105/60*Machinery!$K$7 -> 14.583333 | N105: =G105/60*Machinery!$L$7 -> 0 | O105: =F105/60*Assumptions!$B$20 -> 20.103865 | P105: =I105*Assumptions!$B$34*Assumptions!$B$35 -> 2.66475 | Q105: =SUM(K105:P105) -> 39.509448 | R105: =J105-Q105 -> 97.990552 | S105: =IF(J105=0,0,R105/J105) -> 0.71265856 | T105: =INDEX($B$13:$B$25,MATCH(E105,$A$13:$A$25,0)) -> 0.7 | U105: =SUM(K105:O105)/(1-T105-Assumptions!$B$34*Assumptions!$B$35*(1+H105*$B$5)) -> 131.29748 | V105: =MROUND(U105*(1+H105*$B$5),$B$6) -> 158 | W105: =IF(I105=0,0,V105/I105-1) -> -0.042424242 | X105: =MROUND(V105*3*(1-$B$7),$B$6) -> 427 | Y105: =MROUND(V105*6*(1-$B$8),$B$6) -> 806 | Z105: =MROUND(V105*10*(1-$B$9),$B$6) -> 1264 | AC105: =IF(OR(D105="ACTIVE",D105="CONSULTATION"),1,0) -> 0
A106: Laser Tattoo Removal | B106: X-Large (21 cm+) | C106: aesthetics | D106: COMING_SOON | E106: pico-laser-PLANNED | F106: 45 | G106: 45 | H106: 0.2 | I106: 237 | J106: =I106/(1+H106*$B$5) -> 197.5 | K106: 2.5 | L106: =G106/60*Machinery!$H$7*Assumptions!$B$23/100 -> 0.2025 | M106: =G106/60*Machinery!$K$7 -> 18.75 | N106: =G106/60*Machinery!$L$7 -> 0 | O106: =F106/60*Assumptions!$B$20 -> 25.847826 | P106: =I106*Assumptions!$B$34*Assumptions!$B$35 -> 3.82755 | Q106: =SUM(K106:P106) -> 51.127876 | R106: =J106-Q106 -> 146.37212 | S106: =IF(J106=0,0,R106/J106) -> 0.74112468 | T106: =INDEX($B$13:$B$25,MATCH(E106,$A$13:$A$25,0)) -> 0.7 | U106: =SUM(K106:O106)/(1-T106-Assumptions!$B$34*Assumptions!$B$35*(1+H106*$B$5)) -> 168.5565 | V106: =MROUND(U106*(1+H106*$B$5),$B$6) -> 202 | W106: =IF(I106=0,0,V106/I106-1) -> -0.14767932 | X106: =MROUND(V106*3*(1-$B$7),$B$6) -> 545 | Y106: =MROUND(V106*6*(1-$B$8),$B$6) -> 1030 | Z106: =MROUND(V106*10*(1-$B$9),$B$6) -> 1616 | AC106: =IF(OR(D106="ACTIVE",D106="CONSULTATION"),1,0) -> 0
A107: Permanent Make-Up Removal | B107: Eyebrows | C107: aesthetics | D107: COMING_SOON | E107: pico-laser-PLANNED | F107: 30 | G107: 30 | H107: 0.2 | I107: 275 | J107: =I107/(1+H107*$B$5) -> 229.16667 | K107: 1 | L107: =G107/60*Machinery!$H$7*Assumptions!$B$23/100 -> 0.135 | M107: =G107/60*Machinery!$K$7 -> 12.5 | N107: =G107/60*Machinery!$L$7 -> 0 | O107: =F107/60*Assumptions!$B$20 -> 17.231884 | P107: =I107*Assumptions!$B$34*Assumptions!$B$35 -> 4.44125 | Q107: =SUM(K107:P107) -> 35.308134 | R107: =J107-Q107 -> 193.85853 | S107: =IF(J107=0,0,R107/J107) -> 0.84592814 | T107: =INDEX($B$13:$B$25,MATCH(E107,$A$13:$A$25,0)) -> 0.7 | U107: =SUM(K107:O107)/(1-T107-Assumptions!$B$34*Assumptions!$B$35*(1+H107*$B$5)) -> 109.99531 | V107: =MROUND(U107*(1+H107*$B$5),$B$6) -> 132 | W107: =IF(I107=0,0,V107/I107-1) -> -0.52 | X107: =MROUND(V107*3*(1-$B$7),$B$6) -> 356 | Y107: =MROUND(V107*6*(1-$B$8),$B$6) -> 673 | Z107: =MROUND(V107*10*(1-$B$9),$B$6) -> 1056 | AC107: =IF(OR(D107="ACTIVE",D107="CONSULTATION"),1,0) -> 0
A108: HydraFacial | B108: Signature Express (30 min) | C108: aesthetics | D108: ACTIVE | E108: hydrafacial-platform | F108: 45 | G108: 45 | H108: 0.2 | I108: 95 | J108: =I108/(1+H108*$B$5) -> 79.166667 | K108: 15 | L108: =G108/60*Machinery!$H$11*Assumptions!$B$23/100 -> 0.0405 | M108: =G108/60*Machinery!$K$11 -> 1.5625 | N108: =G108/60*Machinery!$L$11 -> 4.3402778 | O108: =F108/60*Assumptions!$B$20 -> 25.847826 | P108: =I108*Assumptions!$B$34*Assumptions!$B$35 -> 1.53425 | Q108: =SUM(K108:P108) -> 48.325354 | R108: =J108-Q108 -> 30.841313 | S108: =IF(J108=0,0,R108/J108) -> 0.38957448 | T108: =INDEX($B$13:$B$25,MATCH(E108,$A$13:$A$25,0)) -> 0.65 | U108: =SUM(K108:O108)/(1-T108-Assumptions!$B$34*Assumptions!$B$35*(1+H108*$B$5)) -> 141.52533 | V108: =MROUND(U108*(1+H108*$B$5),$B$6) -> 170 | W108: =IF(I108=0,0,V108/I108-1) -> 0.78947368 | X108: =MROUND(V108*3*(1-$B$7),$B$6) -> 459 | Y108: =MROUND(V108*6*(1-$B$8),$B$6) -> 867 | Z108: =MROUND(V108*10*(1-$B$9),$B$6) -> 1360 | AC108: =IF(OR(D108="ACTIVE",D108="CONSULTATION"),1,0) -> 1
A109: HydraFacial | B109: Full Face Deluxe (50 min) | C109: aesthetics | D109: ACTIVE | E109: hydrafacial-platform | F109: 60 | G109: 60 | H109: 0.2 | I109: 145 | J109: =I109/(1+H109*$B$5) -> 120.83333 | K109: 20 | L109: =G109/60*Machinery!$H$11*Assumptions!$B$23/100 -> 0.054 | M109: =G109/60*Machinery!$K$11 -> 2.0833333 | N109: =G109/60*Machinery!$L$11 -> 5.787037 | O109: =F109/60*Assumptions!$B$20 -> 34.463768 | P109: =I109*Assumptions!$B$34*Assumptions!$B$35 -> 2.34175 | Q109: =SUM(K109:P109) -> 64.729888 | R109: =J109-Q109 -> 56.103445 | S109: =IF(J109=0,0,R109/J109) -> 0.46430437 | T109: =INDEX($B$13:$B$25,MATCH(E109,$A$13:$A$25,0)) -> 0.65 | U109: =SUM(K109:O109)/(1-T109-Assumptions!$B$34*Assumptions!$B$35*(1+H109*$B$5)) -> 188.70044 | V109: =MROUND(U109*(1+H109*$B$5),$B$6) -> 226 | W109: =IF(I109=0,0,V109/I109-1) -> 0.55862069 | X109: =MROUND(V109*3*(1-$B$7),$B$6) -> 610 | Y109: =MROUND(V109*6*(1-$B$8),$B$6) -> 1153 | Z109: =MROUND(V109*10*(1-$B$9),$B$6) -> 1808 | AC109: =IF(OR(D109="ACTIVE",D109="CONSULTATION"),1,0) -> 1
A110: HydraFacial | B110: Platinum — Anti-Acne (60 min) | C110: aesthetics | D110: ACTIVE | E110: hydrafacial-platform | F110: 70 | G110: 70 | H110: 0.2 | I110: 185 | J110: =I110/(1+H110*$B$5) -> 154.16667 | K110: 25 | L110: =G110/60*Machinery!$H$11*Assumptions!$B$23/100 -> 0.063 | M110: =G110/60*Machinery!$K$11 -> 2.4305556 | N110: =G110/60*Machinery!$L$11 -> 6.7515432 | O110: =F110/60*Assumptions!$B$20 -> 40.207729 | P110: =I110*Assumptions!$B$34*Assumptions!$B$35 -> 2.98775 | Q110: =SUM(K110:P110) -> 77.440578 | R110: =J110-Q110 -> 76.726088 | S110: =IF(J110=0,0,R110/J110) -> 0.49768274 | T110: =INDEX($B$13:$B$25,MATCH(E110,$A$13:$A$25,0)) -> 0.65 | U110: =SUM(K110:O110)/(1-T110-Assumptions!$B$34*Assumptions!$B$35*(1+H110*$B$5)) -> 225.19154 | V110: =MROUND(U110*(1+H110*$B$5),$B$6) -> 270 | W110: =IF(I110=0,0,V110/I110-1) -> 0.45945946 | X110: =MROUND(V110*3*(1-$B$7),$B$6) -> 729 | Y110: =MROUND(V110*6*(1-$B$8),$B$6) -> 1377 | Z110: =MROUND(V110*10*(1-$B$9),$B$6) -> 2160 | AC110: =IF(OR(D110="ACTIVE",D110="CONSULTATION"),1,0) -> 1
A111: HydraFacial | B111: Platinum — Collagen (60 min) | C111: aesthetics | D111: ACTIVE | E111: hydrafacial-platform | F111: 70 | G111: 70 | H111: 0.2 | I111: 185 | J111: =I111/(1+H111*$B$5) -> 154.16667 | K111: 25 | L111: =G111/60*Machinery!$H$11*Assumptions!$B$23/100 -> 0.063 | M111: =G111/60*Machinery!$K$11 -> 2.4305556 | N111: =G111/60*Machinery!$L$11 -> 6.7515432 | O111: =F111/60*Assumptions!$B$20 -> 40.207729 | P111: =I111*Assumptions!$B$34*Assumptions!$B$35 -> 2.98775 | Q111: =SUM(K111:P111) -> 77.440578 | R111: =J111-Q111 -> 76.726088 | S111: =IF(J111=0,0,R111/J111) -> 0.49768274 | T111: =INDEX($B$13:$B$25,MATCH(E111,$A$13:$A$25,0)) -> 0.65 | U111: =SUM(K111:O111)/(1-T111-Assumptions!$B$34*Assumptions!$B$35*(1+H111*$B$5)) -> 225.19154 | V111: =MROUND(U111*(1+H111*$B$5),$B$6) -> 270 | W111: =IF(I111=0,0,V111/I111-1) -> 0.45945946 | X111: =MROUND(V111*3*(1-$B$7),$B$6) -> 729 | Y111: =MROUND(V111*6*(1-$B$8),$B$6) -> 1377 | Z111: =MROUND(V111*10*(1-$B$9),$B$6) -> 2160 | AC111: =IF(OR(D111="ACTIVE",D111="CONSULTATION"),1,0) -> 1
A112: HydraFacial | B112: Platinum — Pigmentation & Sun Damage (60 min) | C112: aesthetics | D112: ACTIVE | E112: hydrafacial-platform | F112: 70 | G112: 70 | H112: 0.2 | I112: 185 | J112: =I112/(1+H112*$B$5) -> 154.16667 | K112: 25 | L112: =G112/60*Machinery!$H$11*Assumptions!$B$23/100 -> 0.063 | M112: =G112/60*Machinery!$K$11 -> 2.4305556 | N112: =G112/60*Machinery!$L$11 -> 6.7515432 | O112: =F112/60*Assumptions!$B$20 -> 40.207729 | P112: =I112*Assumptions!$B$34*Assumptions!$B$35 -> 2.98775 | Q112: =SUM(K112:P112) -> 77.440578 | R112: =J112-Q112 -> 76.726088 | S112: =IF(J112=0,0,R112/J112) -> 0.49768274 | T112: =INDEX($B$13:$B$25,MATCH(E112,$A$13:$A$25,0)) -> 0.65 | U112: =SUM(K112:O112)/(1-T112-Assumptions!$B$34*Assumptions!$B$35*(1+H112*$B$5)) -> 225.19154 | V112: =MROUND(U112*(1+H112*$B$5),$B$6) -> 270 | W112: =IF(I112=0,0,V112/I112-1) -> 0.45945946 | X112: =MROUND(V112*3*(1-$B$7),$B$6) -> 729 | Y112: =MROUND(V112*6*(1-$B$8),$B$6) -> 1377 | Z112: =MROUND(V112*10*(1-$B$9),$B$6) -> 2160 | AC112: =IF(OR(D112="ACTIVE",D112="CONSULTATION"),1,0) -> 1
A113: HydraFacial | B113: Platinum — Anti-Ageing (60 min) | C113: aesthetics | D113: ACTIVE | E113: hydrafacial-platform | F113: 70 | G113: 70 | H113: 0.2 | I113: 185 | J113: =I113/(1+H113*$B$5) -> 154.16667 | K113: 25 | L113: =G113/60*Machinery!$H$11*Assumptions!$B$23/100 -> 0.063 | M113: =G113/60*Machinery!$K$11 -> 2.4305556 | N113: =G113/60*Machinery!$L$11 -> 6.7515432 | O113: =F113/60*Assumptions!$B$20 -> 40.207729 | P113: =I113*Assumptions!$B$34*Assumptions!$B$35 -> 2.98775 | Q113: =SUM(K113:P113) -> 77.440578 | R113: =J113-Q113 -> 76.726088 | S113: =IF(J113=0,0,R113/J113) -> 0.49768274 | T113: =INDEX($B$13:$B$25,MATCH(E113,$A$13:$A$25,0)) -> 0.65 | U113: =SUM(K113:O113)/(1-T113-Assumptions!$B$34*Assumptions!$B$35*(1+H113*$B$5)) -> 225.19154 | V113: =MROUND(U113*(1+H113*$B$5),$B$6) -> 270 | W113: =IF(I113=0,0,V113/I113-1) -> 0.45945946 | X113: =MROUND(V113*3*(1-$B$7),$B$6) -> 729 | Y113: =MROUND(V113*6*(1-$B$8),$B$6) -> 1377 | Z113: =MROUND(V113*10*(1-$B$9),$B$6) -> 2160 | AC113: =IF(OR(D113="ACTIVE",D113="CONSULTATION"),1,0) -> 1
A114: HydraFacial | B114: Platinum — Brightening (60 min) | C114: aesthetics | D114: ACTIVE | E114: hydrafacial-platform | F114: 70 | G114: 70 | H114: 0.2 | I114: 185 | J114: =I114/(1+H114*$B$5) -> 154.16667 | K114: 25 | L114: =G114/60*Machinery!$H$11*Assumptions!$B$23/100 -> 0.063 | M114: =G114/60*Machinery!$K$11 -> 2.4305556 | N114: =G114/60*Machinery!$L$11 -> 6.7515432 | O114: =F114/60*Assumptions!$B$20 -> 40.207729 | P114: =I114*Assumptions!$B$34*Assumptions!$B$35 -> 2.98775 | Q114: =SUM(K114:P114) -> 77.440578 | R114: =J114-Q114 -> 76.726088 | S114: =IF(J114=0,0,R114/J114) -> 0.49768274 | T114: =INDEX($B$13:$B$25,MATCH(E114,$A$13:$A$25,0)) -> 0.65 | U114: =SUM(K114:O114)/(1-T114-Assumptions!$B$34*Assumptions!$B$35*(1+H114*$B$5)) -> 225.19154 | V114: =MROUND(U114*(1+H114*$B$5),$B$6) -> 270 | W114: =IF(I114=0,0,V114/I114-1) -> 0.45945946 | X114: =MROUND(V114*3*(1-$B$7),$B$6) -> 729 | Y114: =MROUND(V114*6*(1-$B$8),$B$6) -> 1377 | Z114: =MROUND(V114*10*(1-$B$9),$B$6) -> 2160 | AC114: =IF(OR(D114="ACTIVE",D114="CONSULTATION"),1,0) -> 1
A115: SMAS HIFU Lifting | B115: Eyebrow Lift | C115: aesthetics | D115: ACTIVE | E115: hifu | F115: 30 | G115: 30 | H115: 0.2 | I115: 349 | J115: =I115/(1+H115*$B$5) -> 290.83333 | K115: 40 | L115: =G115/60*Machinery!$H$9*Assumptions!$B$23/100 -> 0.0405 | M115: =G115/60*Machinery!$K$9 -> 3.75 | N115: =G115/60*Machinery!$L$9 -> 8.3333333 | O115: =F115/60*Assumptions!$B$20 -> 17.231884 | P115: =I115*Assumptions!$B$34*Assumptions!$B$35 -> 5.63635 | Q115: =SUM(K115:P115) -> 74.992067 | R115: =J115-Q115 -> 215.84127 | S115: =IF(J115=0,0,R115/J115) -> 0.74214762 | T115: =INDEX($B$13:$B$25,MATCH(E115,$A$13:$A$25,0)) -> 0.6 | U115: =SUM(K115:O115)/(1-T115-Assumptions!$B$34*Assumptions!$B$35*(1+H115*$B$5)) -> 182.21774 | V115: =MROUND(U115*(1+H115*$B$5),$B$6) -> 219 | W115: =IF(I115=0,0,V115/I115-1) -> -0.37249284 | X115: =MROUND(V115*3*(1-$B$7),$B$6) -> 591 | Y115: =MROUND(V115*6*(1-$B$8),$B$6) -> 1117 | Z115: =MROUND(V115*10*(1-$B$9),$B$6) -> 1752 | AC115: =IF(OR(D115="ACTIVE",D115="CONSULTATION"),1,0) -> 1
A116: SMAS HIFU Lifting | B116: Forehead Lift | C116: aesthetics | D116: ACTIVE | E116: hifu | F116: 30 | G116: 30 | H116: 0.2 | I116: 349 | J116: =I116/(1+H116*$B$5) -> 290.83333 | K116: 40 | L116: =G116/60*Machinery!$H$9*Assumptions!$B$23/100 -> 0.0405 | M116: =G116/60*Machinery!$K$9 -> 3.75 | N116: =G116/60*Machinery!$L$9 -> 8.3333333 | O116: =F116/60*Assumptions!$B$20 -> 17.231884 | P116: =I116*Assumptions!$B$34*Assumptions!$B$35 -> 5.63635 | Q116: =SUM(K116:P116) -> 74.992067 | R116: =J116-Q116 -> 215.84127 | S116: =IF(J116=0,0,R116/J116) -> 0.74214762 | T116: =INDEX($B$13:$B$25,MATCH(E116,$A$13:$A$25,0)) -> 0.6 | U116: =SUM(K116:O116)/(1-T116-Assumptions!$B$34*Assumptions!$B$35*(1+H116*$B$5)) -> 182.21774 | V116: =MROUND(U116*(1+H116*$B$5),$B$6) -> 219 | W116: =IF(I116=0,0,V116/I116-1) -> -0.37249284 | X116: =MROUND(V116*3*(1-$B$7),$B$6) -> 591 | Y116: =MROUND(V116*6*(1-$B$8),$B$6) -> 1117 | Z116: =MROUND(V116*10*(1-$B$9),$B$6) -> 1752 | AC116: =IF(OR(D116="ACTIVE",D116="CONSULTATION"),1,0) -> 1
A117: SMAS HIFU Lifting | B117: Neck Lift | C117: aesthetics | D117: ACTIVE | E117: hifu | F117: 40 | G117: 40 | H117: 0.2 | I117: 349 | J117: =I117/(1+H117*$B$5) -> 290.83333 | K117: 50 | L117: =G117/60*Machinery!$H$9*Assumptions!$B$23/100 -> 0.054 | M117: =G117/60*Machinery!$K$9 -> 5 | N117: =G117/60*Machinery!$L$9 -> 11.111111 | O117: =F117/60*Assumptions!$B$20 -> 22.975845 | P117: =I117*Assumptions!$B$34*Assumptions!$B$35 -> 5.63635 | Q117: =SUM(K117:P117) -> 94.777307 | R117: =J117-Q117 -> 196.05603 | S117: =IF(J117=0,0,R117/J117) -> 0.67411814 | T117: =INDEX($B$13:$B$25,MATCH(E117,$A$13:$A$25,0)) -> 0.6 | U117: =SUM(K117:O117)/(1-T117-Assumptions!$B$34*Assumptions!$B$35*(1+H117*$B$5)) -> 234.19935 | V117: =MROUND(U117*(1+H117*$B$5),$B$6) -> 281 | W117: =IF(I117=0,0,V117/I117-1) -> -0.19484241 | X117: =MROUND(V117*3*(1-$B$7),$B$6) -> 759 | Y117: =MROUND(V117*6*(1-$B$8),$B$6) -> 1433 | Z117: =MROUND(V117*10*(1-$B$9),$B$6) -> 2248 | AC117: =IF(OR(D117="ACTIVE",D117="CONSULTATION"),1,0) -> 1
A118: SMAS HIFU Lifting | B118: Jawline Lift | C118: aesthetics | D118: ACTIVE | E118: hifu | F118: 40 | G118: 40 | H118: 0.2 | I118: 399 | J118: =I118/(1+H118*$B$5) -> 332.5 | K118: 50 | L118: =G118/60*Machinery!$H$9*Assumptions!$B$23/100 -> 0.054 | M118: =G118/60*Machinery!$K$9 -> 5 | N118: =G118/60*Machinery!$L$9 -> 11.111111 | O118: =F118/60*Assumptions!$B$20 -> 22.975845 | P118: =I118*Assumptions!$B$34*Assumptions!$B$35 -> 6.44385 | Q118: =SUM(K118:P118) -> 95.584807 | R118: =J118-Q118 -> 236.91519 | S118: =IF(J118=0,0,R118/J118) -> 0.7125269 | T118: =INDEX($B$13:$B$25,MATCH(E118,$A$13:$A$25,0)) -> 0.6 | U118: =SUM(K118:O118)/(1-T118-Assumptions!$B$34*Assumptions!$B$35*(1+H118*$B$5)) -> 234.19935 | V118: =MROUND(U118*(1+H118*$B$5),$B$6) -> 281 | W118: =IF(I118=0,0,V118/I118-1) -> -0.29573935 | X118: =MROUND(V118*3*(1-$B$7),$B$6) -> 759 | Y118: =MROUND(V118*6*(1-$B$8),$B$6) -> 1433 | Z118: =MROUND(V118*10*(1-$B$9),$B$6) -> 2248 | AC118: =IF(OR(D118="ACTIVE",D118="CONSULTATION"),1,0) -> 1
A119: SMAS HIFU Lifting | B119: Full Face | C119: aesthetics | D119: ACTIVE | E119: hifu | F119: 60 | G119: 60 | H119: 0.2 | I119: 479 | J119: =I119/(1+H119*$B$5) -> 399.16667 | K119: 65 | L119: =G119/60*Machinery!$H$9*Assumptions!$B$23/100 -> 0.081 | M119: =G119/60*Machinery!$K$9 -> 7.5 | N119: =G119/60*Machinery!$L$9 -> 16.666667 | O119: =F119/60*Assumptions!$B$20 -> 34.463768 | P119: =I119*Assumptions!$B$34*Assumptions!$B$35 -> 7.73585 | Q119: =SUM(K119:P119) -> 131.44728 | R119: =J119-Q119 -> 267.71938 | S119: =IF(J119=0,0,R119/J119) -> 0.67069574 | T119: =INDEX($B$13:$B$25,MATCH(E119,$A$13:$A$25,0)) -> 0.6 | U119: =SUM(K119:O119)/(1-T119-Assumptions!$B$34*Assumptions!$B$35*(1+H119*$B$5)) -> 325.0261 | V119: =MROUND(U119*(1+H119*$B$5),$B$6) -> 390 | W119: =IF(I119=0,0,V119/I119-1) -> -0.18580376 | X119: =MROUND(V119*3*(1-$B$7),$B$6) -> 1053 | Y119: =MROUND(V119*6*(1-$B$8),$B$6) -> 1989 | Z119: =MROUND(V119*10*(1-$B$9),$B$6) -> 3120 | AC119: =IF(OR(D119="ACTIVE",D119="CONSULTATION"),1,0) -> 1
A120: SMAS HIFU Lifting | B120: Full Face & Neck | C120: aesthetics | D120: ACTIVE | E120: hifu | F120: 60 | G120: 60 | H120: 0.2 | I120: 559 | J120: =I120/(1+H120*$B$5) -> 465.83333 | K120: 75 | L120: =G120/60*Machinery!$H$9*Assumptions!$B$23/100 -> 0.081 | M120: =G120/60*Machinery!$K$9 -> 7.5 | N120: =G120/60*Machinery!$L$9 -> 16.666667 | O120: =F120/60*Assumptions!$B$20 -> 34.463768 | P120: =I120*Assumptions!$B$34*Assumptions!$B$35 -> 9.02785 | Q120: =SUM(K120:P120) -> 142.73928 | R120: =J120-Q120 -> 323.09405 | S120: =IF(J120=0,0,R120/J120) -> 0.69358293 | T120: =INDEX($B$13:$B$25,MATCH(E120,$A$13:$A$25,0)) -> 0.6 | U120: =SUM(K120:O120)/(1-T120-Assumptions!$B$34*Assumptions!$B$35*(1+H120*$B$5)) -> 351.29902 | V120: =MROUND(U120*(1+H120*$B$5),$B$6) -> 422 | W120: =IF(I120=0,0,V120/I120-1) -> -0.2450805 | X120: =MROUND(V120*3*(1-$B$7),$B$6) -> 1139 | Y120: =MROUND(V120*6*(1-$B$8),$B$6) -> 2152 | Z120: =MROUND(V120*10*(1-$B$9),$B$6) -> 3376 | AC120: =IF(OR(D120="ACTIVE",D120="CONSULTATION"),1,0) -> 1
A121: SMAS HIFU Lifting | B121: Stomach | C121: aesthetics | D121: ACTIVE | E121: hifu | F121: 60 | G121: 60 | H121: 0.2 | I121: 399 | J121: =I121/(1+H121*$B$5) -> 332.5 | K121: 80 | L121: =G121/60*Machinery!$H$9*Assumptions!$B$23/100 -> 0.081 | M121: =G121/60*Machinery!$K$9 -> 7.5 | N121: =G121/60*Machinery!$L$9 -> 16.666667 | O121: =F121/60*Assumptions!$B$20 -> 34.463768 | P121: =I121*Assumptions!$B$34*Assumptions!$B$35 -> 6.44385 | Q121: =SUM(K121:P121) -> 145.15528 | R121: =J121-Q121 -> 187.34472 | S121: =IF(J121=0,0,R121/J121) -> 0.56344275 | T121: =INDEX($B$13:$B$25,MATCH(E121,$A$13:$A$25,0)) -> 0.6 | U121: =SUM(K121:O121)/(1-T121-Assumptions!$B$34*Assumptions!$B$35*(1+H121*$B$5)) -> 364.43549 | V121: =MROUND(U121*(1+H121*$B$5),$B$6) -> 437 | W121: =IF(I121=0,0,V121/I121-1) -> 0.095238095 | X121: =MROUND(V121*3*(1-$B$7),$B$6) -> 1180 | Y121: =MROUND(V121*6*(1-$B$8),$B$6) -> 2229 | Z121: =MROUND(V121*10*(1-$B$9),$B$6) -> 3496 | AC121: =IF(OR(D121="ACTIVE",D121="CONSULTATION"),1,0) -> 1
A122: SMAS HIFU Lifting | B122: Outer Thighs | C122: aesthetics | D122: ACTIVE | E122: hifu | F122: 60 | G122: 60 | H122: 0.2 | I122: 329 | J122: =I122/(1+H122*$B$5) -> 274.16667 | K122: 80 | L122: =G122/60*Machinery!$H$9*Assumptions!$B$23/100 -> 0.081 | M122: =G122/60*Machinery!$K$9 -> 7.5 | N122: =G122/60*Machinery!$L$9 -> 16.666667 | O122: =F122/60*Assumptions!$B$20 -> 34.463768 | P122: =I122*Assumptions!$B$34*Assumptions!$B$35 -> 5.31335 | Q122: =SUM(K122:P122) -> 144.02478 | R122: =J122-Q122 -> 130.14188 | S122: =IF(J122=0,0,R122/J122) -> 0.47468164 | T122: =INDEX($B$13:$B$25,MATCH(E122,$A$13:$A$25,0)) -> 0.6 | U122: =SUM(K122:O122)/(1-T122-Assumptions!$B$34*Assumptions!$B$35*(1+H122*$B$5)) -> 364.43549 | V122: =MROUND(U122*(1+H122*$B$5),$B$6) -> 437 | W122: =IF(I122=0,0,V122/I122-1) -> 0.32826748 | X122: =MROUND(V122*3*(1-$B$7),$B$6) -> 1180 | Y122: =MROUND(V122*6*(1-$B$8),$B$6) -> 2229 | Z122: =MROUND(V122*10*(1-$B$9),$B$6) -> 3496 | AC122: =IF(OR(D122="ACTIVE",D122="CONSULTATION"),1,0) -> 1
A123: SMAS HIFU Lifting | B123: Inner Thighs | C123: aesthetics | D123: ACTIVE | E123: hifu | F123: 60 | G123: 60 | H123: 0.2 | I123: 349 | J123: =I123/(1+H123*$B$5) -> 290.83333 | K123: 80 | L123: =G123/60*Machinery!$H$9*Assumptions!$B$23/100 -> 0.081 | M123: =G123/60*Machinery!$K$9 -> 7.5 | N123: =G123/60*Machinery!$L$9 -> 16.666667 | O123: =F123/60*Assumptions!$B$20 -> 34.463768 | P123: =I123*Assumptions!$B$34*Assumptions!$B$35 -> 5.63635 | Q123: =SUM(K123:P123) -> 144.34778 | R123: =J123-Q123 -> 146.48555 | S123: =IF(J123=0,0,R123/J123) -> 0.50367524 | T123: =INDEX($B$13:$B$25,MATCH(E123,$A$13:$A$25,0)) -> 0.6 | U123: =SUM(K123:O123)/(1-T123-Assumptions!$B$34*Assumptions!$B$35*(1+H123*$B$5)) -> 364.43549 | V123: =MROUND(U123*(1+H123*$B$5),$B$6) -> 437 | W123: =IF(I123=0,0,V123/I123-1) -> 0.252149 | X123: =MROUND(V123*3*(1-$B$7),$B$6) -> 1180 | Y123: =MROUND(V123*6*(1-$B$8),$B$6) -> 2229 | Z123: =MROUND(V123*10*(1-$B$9),$B$6) -> 3496 | AC123: =IF(OR(D123="ACTIVE",D123="CONSULTATION"),1,0) -> 1
A124: SMAS HIFU Lifting | B124: Back & Flanks | C124: aesthetics | D124: ACTIVE | E124: hifu | F124: 60 | G124: 60 | H124: 0.2 | I124: 329 | J124: =I124/(1+H124*$B$5) -> 274.16667 | K124: 80 | L124: =G124/60*Machinery!$H$9*Assumptions!$B$23/100 -> 0.081 | M124: =G124/60*Machinery!$K$9 -> 7.5 | N124: =G124/60*Machinery!$L$9 -> 16.666667 | O124: =F124/60*Assumptions!$B$20 -> 34.463768 | P124: =I124*Assumptions!$B$34*Assumptions!$B$35 -> 5.31335 | Q124: =SUM(K124:P124) -> 144.02478 | R124: =J124-Q124 -> 130.14188 | S124: =IF(J124=0,0,R124/J124) -> 0.47468164 | T124: =INDEX($B$13:$B$25,MATCH(E124,$A$13:$A$25,0)) -> 0.6 | U124: =SUM(K124:O124)/(1-T124-Assumptions!$B$34*Assumptions!$B$35*(1+H124*$B$5)) -> 364.43549 | V124: =MROUND(U124*(1+H124*$B$5),$B$6) -> 437 | W124: =IF(I124=0,0,V124/I124-1) -> 0.32826748 | X124: =MROUND(V124*3*(1-$B$7),$B$6) -> 1180 | Y124: =MROUND(V124*6*(1-$B$8),$B$6) -> 2229 | Z124: =MROUND(V124*10*(1-$B$9),$B$6) -> 3496 | AC124: =IF(OR(D124="ACTIVE",D124="CONSULTATION"),1,0) -> 1
A125: SMAS HIFU Lifting | B125: Buttock | C125: aesthetics | D125: ACTIVE | E125: hifu | F125: 60 | G125: 60 | H125: 0.2 | I125: 349 | J125: =I125/(1+H125*$B$5) -> 290.83333 | K125: 80 | L125: =G125/60*Machinery!$H$9*Assumptions!$B$23/100 -> 0.081 | M125: =G125/60*Machinery!$K$9 -> 7.5 | N125: =G125/60*Machinery!$L$9 -> 16.666667 | O125: =F125/60*Assumptions!$B$20 -> 34.463768 | P125: =I125*Assumptions!$B$34*Assumptions!$B$35 -> 5.63635 | Q125: =SUM(K125:P125) -> 144.34778 | R125: =J125-Q125 -> 146.48555 | S125: =IF(J125=0,0,R125/J125) -> 0.50367524 | T125: =INDEX($B$13:$B$25,MATCH(E125,$A$13:$A$25,0)) -> 0.6 | U125: =SUM(K125:O125)/(1-T125-Assumptions!$B$34*Assumptions!$B$35*(1+H125*$B$5)) -> 364.43549 | V125: =MROUND(U125*(1+H125*$B$5),$B$6) -> 437 | W125: =IF(I125=0,0,V125/I125-1) -> 0.252149 | X125: =MROUND(V125*3*(1-$B$7),$B$6) -> 1180 | Y125: =MROUND(V125*6*(1-$B$8),$B$6) -> 2229 | Z125: =MROUND(V125*10*(1-$B$9),$B$6) -> 3496 | AC125: =IF(OR(D125="ACTIVE",D125="CONSULTATION"),1,0) -> 1
A126: SMAS HIFU Lifting | B126: Skin Above the Knee Caps | C126: aesthetics | D126: ACTIVE | E126: hifu | F126: 40 | G126: 40 | H126: 0.2 | I126: 309 | J126: =I126/(1+H126*$B$5) -> 257.5 | K126: 50 | L126: =G126/60*Machinery!$H$9*Assumptions!$B$23/100 -> 0.054 | M126: =G126/60*Machinery!$K$9 -> 5 | N126: =G126/60*Machinery!$L$9 -> 11.111111 | O126: =F126/60*Assumptions!$B$20 -> 22.975845 | P126: =I126*Assumptions!$B$34*Assumptions!$B$35 -> 4.99035 | Q126: =SUM(K126:P126) -> 94.131307 | R126: =J126-Q126 -> 163.36869 | S126: =IF(J126=0,0,R126/J126) -> 0.63444153 | T126: =INDEX($B$13:$B$25,MATCH(E126,$A$13:$A$25,0)) -> 0.6 | U126: =SUM(K126:O126)/(1-T126-Assumptions!$B$34*Assumptions!$B$35*(1+H126*$B$5)) -> 234.19935 | V126: =MROUND(U126*(1+H126*$B$5),$B$6) -> 281 | W126: =IF(I126=0,0,V126/I126-1) -> -0.090614887 | X126: =MROUND(V126*3*(1-$B$7),$B$6) -> 759 | Y126: =MROUND(V126*6*(1-$B$8),$B$6) -> 1433 | Z126: =MROUND(V126*10*(1-$B$9),$B$6) -> 2248 | AC126: =IF(OR(D126="ACTIVE",D126="CONSULTATION"),1,0) -> 1
A127: SMAS HIFU Lifting | B127: Arms (bingo wings) | C127: aesthetics | D127: ACTIVE | E127: hifu | F127: 50 | G127: 50 | H127: 0.2 | I127: 349 | J127: =I127/(1+H127*$B$5) -> 290.83333 | K127: 65 | L127: =G127/60*Machinery!$H$9*Assumptions!$B$23/100 -> 0.0675 | M127: =G127/60*Machinery!$K$9 -> 6.25 | N127: =G127/60*Machinery!$L$9 -> 13.888889 | O127: =F127/60*Assumptions!$B$20 -> 28.719807 | P127: =I127*Assumptions!$B$34*Assumptions!$B$35 -> 5.63635 | Q127: =SUM(K127:P127) -> 119.56255 | R127: =J127-Q127 -> 171.27079 | S127: =IF(J127=0,0,R127/J127) -> 0.58889669 | T127: =INDEX($B$13:$B$25,MATCH(E127,$A$13:$A$25,0)) -> 0.6 | U127: =SUM(K127:O127)/(1-T127-Assumptions!$B$34*Assumptions!$B$35*(1+H127*$B$5)) -> 299.31742 | V127: =MROUND(U127*(1+H127*$B$5),$B$6) -> 359 | W127: =IF(I127=0,0,V127/I127-1) -> 0.028653295 | X127: =MROUND(V127*3*(1-$B$7),$B$6) -> 969 | Y127: =MROUND(V127*6*(1-$B$8),$B$6) -> 1831 | Z127: =MROUND(V127*10*(1-$B$9),$B$6) -> 2872 | AC127: =IF(OR(D127="ACTIVE",D127="CONSULTATION"),1,0) -> 1
A128: Cosmetic Peels | B128: Full Face | C128: aesthetics | D128: ACTIVE | E128: none-manual | F128: 60 | G128: 0 | H128: 0.2 | I128: 125 | J128: =I128/(1+H128*$B$5) -> 104.16667 | K128: 12 | L128: =G128/60*Machinery!$H$17*Assumptions!$B$23/100 -> 0 | M128: =G128/60*Machinery!$K$17 -> 0 | N128: =G128/60*Machinery!$L$17 -> 0 | O128: =F128/60*Assumptions!$B$20 -> 34.463768 | P128: =I128*Assumptions!$B$34*Assumptions!$B$35 -> 2.01875 | Q128: =SUM(K128:P128) -> 48.482518 | R128: =J128-Q128 -> 55.684149 | S128: =IF(J128=0,0,R128/J128) -> 0.53456783 | T128: =INDEX($B$13:$B$25,MATCH(E128,$A$13:$A$25,0)) -> 0.65 | U128: =SUM(K128:O128)/(1-T128-Assumptions!$B$34*Assumptions!$B$35*(1+H128*$B$5)) -> 140.53526 | V128: =MROUND(U128*(1+H128*$B$5),$B$6) -> 169 | W128: =IF(I128=0,0,V128/I128-1) -> 0.352 | X128: =MROUND(V128*3*(1-$B$7),$B$6) -> 456 | Y128: =MROUND(V128*6*(1-$B$8),$B$6) -> 862 | Z128: =MROUND(V128*10*(1-$B$9),$B$6) -> 1352 | AC128: =IF(OR(D128="ACTIVE",D128="CONSULTATION"),1,0) -> 1
A129: Fat-Dissolving Injections | B129: Small Area (under chin) | C129: aesthetics | D129: ACTIVE | E129: none-injectables | F129: 30 | G129: 0 | H129: 0.2 | I129: 145 | J129: =I129/(1+H129*$B$5) -> 120.83333 | K129: 35 | L129: =G129/60*Machinery!$H$16*Assumptions!$B$23/100 -> 0 | M129: =G129/60*Machinery!$K$16 -> 0 | N129: =G129/60*Machinery!$L$16 -> 0 | O129: =F129/60*Assumptions!$B$20 -> 17.231884 | P129: =I129*Assumptions!$B$34*Assumptions!$B$35 -> 2.34175 | Q129: =SUM(K129:P129) -> 54.573634 | R129: =J129-Q129 -> 66.259699 | S129: =IF(J129=0,0,R129/J129) -> 0.54835613 | T129: =INDEX($B$13:$B$25,MATCH(E129,$A$13:$A$25,0)) -> 0.55 | U129: =SUM(K129:O129)/(1-T129-Assumptions!$B$34*Assumptions!$B$35*(1+H129*$B$5)) -> 121.29461 | V129: =MROUND(U129*(1+H129*$B$5),$B$6) -> 146 | W129: =IF(I129=0,0,V129/I129-1) -> 0.0068965517 | X129: =MROUND(V129*3*(1-$B$7),$B$6) -> 394 | Y129: =MROUND(V129*6*(1-$B$8),$B$6) -> 745 | Z129: =MROUND(V129*10*(1-$B$9),$B$6) -> 1168 | AC129: =IF(OR(D129="ACTIVE",D129="CONSULTATION"),1,0) -> 1
A130: Fat-Dissolving Injections | B130: Medium Area (Stomach, Bingo Wings, Knees) | C130: aesthetics | D130: ACTIVE | E130: none-injectables | F130: 30 | G130: 0 | H130: 0.2 | I130: 225 | J130: =I130/(1+H130*$B$5) -> 187.5 | K130: 55 | L130: =G130/60*Machinery!$H$16*Assumptions!$B$23/100 -> 0 | M130: =G130/60*Machinery!$K$16 -> 0 | N130: =G130/60*Machinery!$L$16 -> 0 | O130: =F130/60*Assumptions!$B$20 -> 17.231884 | P130: =I130*Assumptions!$B$34*Assumptions!$B$35 -> 3.63375 | Q130: =SUM(K130:P130) -> 75.865634 | R130: =J130-Q130 -> 111.63437 | S130: =IF(J130=0,0,R130/J130) -> 0.59538329 | T130: =INDEX($B$13:$B$25,MATCH(E130,$A$13:$A$25,0)) -> 0.55 | U130: =SUM(K130:O130)/(1-T130-Assumptions!$B$34*Assumptions!$B$35*(1+H130*$B$5)) -> 167.73927 | V130: =MROUND(U130*(1+H130*$B$5),$B$6) -> 201 | W130: =IF(I130=0,0,V130/I130-1) -> -0.10666667 | X130: =MROUND(V130*3*(1-$B$7),$B$6) -> 543 | Y130: =MROUND(V130*6*(1-$B$8),$B$6) -> 1025 | Z130: =MROUND(V130*10*(1-$B$9),$B$6) -> 1608 | AC130: =IF(OR(D130="ACTIVE",D130="CONSULTATION"),1,0) -> 1
A131: Fat-Dissolving Injections | B131: Large Area (Thighs, Waist, Stomach) | C131: aesthetics | D131: ACTIVE | E131: none-injectables | F131: 30 | G131: 0 | H131: 0.2 | I131: 290 | J131: =I131/(1+H131*$B$5) -> 241.66667 | K131: 75 | L131: =G131/60*Machinery!$H$16*Assumptions!$B$23/100 -> 0 | M131: =G131/60*Machinery!$K$16 -> 0 | N131: =G131/60*Machinery!$L$16 -> 0 | O131: =F131/60*Assumptions!$B$20 -> 17.231884 | P131: =I131*Assumptions!$B$34*Assumptions!$B$35 -> 4.6835 | Q131: =SUM(K131:P131) -> 96.915384 | R131: =J131-Q131 -> 144.75128 | S131: =IF(J131=0,0,R131/J131) -> 0.59897082 | T131: =INDEX($B$13:$B$25,MATCH(E131,$A$13:$A$25,0)) -> 0.55 | U131: =SUM(K131:O131)/(1-T131-Assumptions!$B$34*Assumptions!$B$35*(1+H131*$B$5)) -> 214.18393 | V131: =MROUND(U131*(1+H131*$B$5),$B$6) -> 257 | W131: =IF(I131=0,0,V131/I131-1) -> -0.1137931 | X131: =MROUND(V131*3*(1-$B$7),$B$6) -> 694 | Y131: =MROUND(V131*6*(1-$B$8),$B$6) -> 1311 | Z131: =MROUND(V131*10*(1-$B$9),$B$6) -> 2056 | AC131: =IF(OR(D131="ACTIVE",D131="CONSULTATION"),1,0) -> 1
A132: RF Lifting | B132: RF Lifting | C132: aesthetics | D132: ACTIVE | E132: rf-tightening | F132: 60 | G132: 60 | H132: 0.2 | I132: 260 | J132: =I132/(1+H132*$B$5) -> 216.66667 | K132: 3 | L132: =G132/60*Machinery!$H$10*Assumptions!$B$23/100 -> 0.135 | M132: =G132/60*Machinery!$K$10 -> 20.833333 | N132: =G132/60*Machinery!$L$10 -> 39.68254 | O132: =F132/60*Assumptions!$B$20 -> 34.463768 | P132: =I132*Assumptions!$B$34*Assumptions!$B$35 -> 4.199 | Q132: =SUM(K132:P132) -> 102.31364 | R132: =J132-Q132 -> 114.35303 | S132: =IF(J132=0,0,R132/J132) -> 0.52778319 | T132: =INDEX($B$13:$B$25,MATCH(E132,$A$13:$A$25,0)) -> 0.7 | U132: =SUM(K132:O132)/(1-T132-Assumptions!$B$34*Assumptions!$B$35*(1+H132*$B$5)) -> 349.63524 | V132: =MROUND(U132*(1+H132*$B$5),$B$6) -> 420 | W132: =IF(I132=0,0,V132/I132-1) -> 0.61538462 | X132: =MROUND(V132*3*(1-$B$7),$B$6) -> 1134 | Y132: =MROUND(V132*6*(1-$B$8),$B$6) -> 2142 | Z132: =MROUND(V132*10*(1-$B$9),$B$6) -> 3360 | AC132: =IF(OR(D132="ACTIVE",D132="CONSULTATION"),1,0) -> 1
A133: IPL Phototherapy | B133: Face | C133: aesthetics | D133: ACTIVE | E133: laser-ipl-platform | F133: 30 | G133: 30 | H133: 0.2 | I133: 150 | J133: =I133/(1+H133*$B$5) -> 125 | K133: 2 | L133: =G133/60*Machinery!$H$6*Assumptions!$B$23/100 -> 0.108 | M133: =G133/60*Machinery!$K$6 -> 4.1666667 | N133: =G133/60*Machinery!$L$6 -> 7.8125 | O133: =F133/60*Assumptions!$B$20 -> 17.231884 | P133: =I133*Assumptions!$B$34*Assumptions!$B$35 -> 2.4225 | Q133: =SUM(K133:P133) -> 33.741551 | R133: =J133-Q133 -> 91.258449 | S133: =IF(J133=0,0,R133/J133) -> 0.73006759 | T133: =INDEX($B$13:$B$25,MATCH(E133,$A$13:$A$25,0)) -> 0.7 | U133: =SUM(K133:O133)/(1-T133-Assumptions!$B$34*Assumptions!$B$35*(1+H133*$B$5)) -> 111.60662 | V133: =MROUND(U133*(1+H133*$B$5),$B$6) -> 134 | W133: =IF(I133=0,0,V133/I133-1) -> -0.10666667 | X133: =MROUND(V133*3*(1-$B$7),$B$6) -> 362 | Y133: =MROUND(V133*6*(1-$B$8),$B$6) -> 683 | Z133: =MROUND(V133*10*(1-$B$9),$B$6) -> 1072 | AC133: =IF(OR(D133="ACTIVE",D133="CONSULTATION"),1,0) -> 1
A134: IPL Phototherapy | B134: Face & Neck | C134: aesthetics | D134: ACTIVE | E134: laser-ipl-platform | F134: 30 | G134: 30 | H134: 0.2 | I134: 210 | J134: =I134/(1+H134*$B$5) -> 175 | K134: 2 | L134: =G134/60*Machinery!$H$6*Assumptions!$B$23/100 -> 0.108 | M134: =G134/60*Machinery!$K$6 -> 4.1666667 | N134: =G134/60*Machinery!$L$6 -> 7.8125 | O134: =F134/60*Assumptions!$B$20 -> 17.231884 | P134: =I134*Assumptions!$B$34*Assumptions!$B$35 -> 3.3915 | Q134: =SUM(K134:P134) -> 34.710551 | R134: =J134-Q134 -> 140.28945 | S134: =IF(J134=0,0,R134/J134) -> 0.801654 | T134: =INDEX($B$13:$B$25,MATCH(E134,$A$13:$A$25,0)) -> 0.7 | U134: =SUM(K134:O134)/(1-T134-Assumptions!$B$34*Assumptions!$B$35*(1+H134*$B$5)) -> 111.60662 | V134: =MROUND(U134*(1+H134*$B$5),$B$6) -> 134 | W134: =IF(I134=0,0,V134/I134-1) -> -0.36190476 | X134: =MROUND(V134*3*(1-$B$7),$B$6) -> 362 | Y134: =MROUND(V134*6*(1-$B$8),$B$6) -> 683 | Z134: =MROUND(V134*10*(1-$B$9),$B$6) -> 1072 | AC134: =IF(OR(D134="ACTIVE",D134="CONSULTATION"),1,0) -> 1
A135: Laser Skin Rejuvenation | B135: Face & Neck | C135: aesthetics | D135: ACTIVE | E135: laser-ipl-platform | F135: 45 | G135: 45 | H135: 0.2 | I135: 210 | J135: =I135/(1+H135*$B$5) -> 175 | K135: 2 | L135: =G135/60*Machinery!$H$6*Assumptions!$B$23/100 -> 0.162 | M135: =G135/60*Machinery!$K$6 -> 6.25 | N135: =G135/60*Machinery!$L$6 -> 11.71875 | O135: =F135/60*Assumptions!$B$20 -> 25.847826 | P135: =I135*Assumptions!$B$34*Assumptions!$B$35 -> 3.3915 | Q135: =SUM(K135:P135) -> 49.370076 | R135: =J135-Q135 -> 125.62992 | S135: =IF(J135=0,0,R135/J135) -> 0.71788528 | T135: =INDEX($B$13:$B$25,MATCH(E135,$A$13:$A$25,0)) -> 0.7 | U135: =SUM(K135:O135)/(1-T135-Assumptions!$B$34*Assumptions!$B$35*(1+H135*$B$5)) -> 163.8464 | V135: =MROUND(U135*(1+H135*$B$5),$B$6) -> 197 | W135: =IF(I135=0,0,V135/I135-1) -> -0.061904762 | X135: =MROUND(V135*3*(1-$B$7),$B$6) -> 532 | Y135: =MROUND(V135*6*(1-$B$8),$B$6) -> 1005 | Z135: =MROUND(V135*10*(1-$B$9),$B$6) -> 1576 | AC135: =IF(OR(D135="ACTIVE",D135="CONSULTATION"),1,0) -> 1
A136: Laser Skin Rejuvenation | B136: Face | C136: aesthetics | D136: ACTIVE | E136: laser-ipl-platform | F136: 40 | G136: 40 | H136: 0.2 | I136: 150 | J136: =I136/(1+H136*$B$5) -> 125 | K136: 2 | L136: =G136/60*Machinery!$H$6*Assumptions!$B$23/100 -> 0.144 | M136: =G136/60*Machinery!$K$6 -> 5.5555556 | N136: =G136/60*Machinery!$L$6 -> 10.416667 | O136: =F136/60*Assumptions!$B$20 -> 22.975845 | P136: =I136*Assumptions!$B$34*Assumptions!$B$35 -> 2.4225 | Q136: =SUM(K136:P136) -> 43.514568 | R136: =J136-Q136 -> 81.485432 | S136: =IF(J136=0,0,R136/J136) -> 0.65188346 | T136: =INDEX($B$13:$B$25,MATCH(E136,$A$13:$A$25,0)) -> 0.7 | U136: =SUM(K136:O136)/(1-T136-Assumptions!$B$34*Assumptions!$B$35*(1+H136*$B$5)) -> 146.43314 | V136: =MROUND(U136*(1+H136*$B$5),$B$6) -> 176 | W136: =IF(I136=0,0,V136/I136-1) -> 0.17333333 | X136: =MROUND(V136*3*(1-$B$7),$B$6) -> 475 | Y136: =MROUND(V136*6*(1-$B$8),$B$6) -> 898 | Z136: =MROUND(V136*10*(1-$B$9),$B$6) -> 1408 | AC136: =IF(OR(D136="ACTIVE",D136="CONSULTATION"),1,0) -> 1
A137: Laser Skin Resurfacing | B137: Laser Skin Resurfacing | C137: aesthetics | D137: ACTIVE | E137: laser-ipl-platform | F137: 60 | G137: 60 | H137: 0.2 | I137: 180 | J137: =I137/(1+H137*$B$5) -> 150 | K137: 2 | L137: =G137/60*Machinery!$H$6*Assumptions!$B$23/100 -> 0.216 | M137: =G137/60*Machinery!$K$6 -> 8.3333333 | N137: =G137/60*Machinery!$L$6 -> 15.625 | O137: =F137/60*Assumptions!$B$20 -> 34.463768 | P137: =I137*Assumptions!$B$34*Assumptions!$B$35 -> 2.907 | Q137: =SUM(K137:P137) -> 63.545101 | R137: =J137-Q137 -> 86.454899 | S137: =IF(J137=0,0,R137/J137) -> 0.57636599 | T137: =INDEX($B$13:$B$25,MATCH(E137,$A$13:$A$25,0)) -> 0.7 | U137: =SUM(K137:O137)/(1-T137-Assumptions!$B$34*Assumptions!$B$35*(1+H137*$B$5)) -> 216.08617 | V137: =MROUND(U137*(1+H137*$B$5),$B$6) -> 259 | W137: =IF(I137=0,0,V137/I137-1) -> 0.43888889 | X137: =MROUND(V137*3*(1-$B$7),$B$6) -> 699 | Y137: =MROUND(V137*6*(1-$B$8),$B$6) -> 1321 | Z137: =MROUND(V137*10*(1-$B$9),$B$6) -> 2072 | AC137: =IF(OR(D137="ACTIVE",D137="CONSULTATION"),1,0) -> 1
A138: Endosphere Body Contouring | B138: BodySphere 30 min | C138: aesthetics | D138: ACTIVE | E138: endosphere-vacuum | F138: 35 | G138: 35 | H138: 0.2 | I138: 75 | J138: =I138/(1+H138*$B$5) -> 62.5 | K138: 2 | L138: =G138/60*Machinery!$H$12*Assumptions!$B$23/100 -> 0.055125 | M138: =G138/60*Machinery!$K$12 -> 1.8904321 | N138: =G138/60*Machinery!$L$12 -> 4.1666667 | O138: =F138/60*Assumptions!$B$20 -> 20.103865 | P138: =I138*Assumptions!$B$34*Assumptions!$B$35 -> 1.21125 | Q138: =SUM(K138:P138) -> 29.427338 | R138: =J138-Q138 -> 33.072662 | S138: =IF(J138=0,0,R138/J138) -> 0.52916258 | T138: =INDEX($B$13:$B$25,MATCH(E138,$A$13:$A$25,0)) -> 0.7 | U138: =SUM(K138:O138)/(1-T138-Assumptions!$B$34*Assumptions!$B$35*(1+H138*$B$5)) -> 100.5491 | V138: =MROUND(U138*(1+H138*$B$5),$B$6) -> 121 | W138: =IF(I138=0,0,V138/I138-1) -> 0.61333333 | X138: =MROUND(V138*3*(1-$B$7),$B$6) -> 327 | Y138: =MROUND(V138*6*(1-$B$8),$B$6) -> 617 | Z138: =MROUND(V138*10*(1-$B$9),$B$6) -> 968 | AC138: =IF(OR(D138="ACTIVE",D138="CONSULTATION"),1,0) -> 1
A139: Endosphere Body Contouring | B139: BodySphere 45 min | C139: aesthetics | D139: ACTIVE | E139: endosphere-vacuum | F139: 45 | G139: 45 | H139: 0.2 | I139: 105 | J139: =I139/(1+H139*$B$5) -> 87.5 | K139: 2 | L139: =G139/60*Machinery!$H$12*Assumptions!$B$23/100 -> 0.070875 | M139: =G139/60*Machinery!$K$12 -> 2.4305556 | N139: =G139/60*Machinery!$L$12 -> 5.3571429 | O139: =F139/60*Assumptions!$B$20 -> 25.847826 | P139: =I139*Assumptions!$B$34*Assumptions!$B$35 -> 1.69575 | Q139: =SUM(K139:P139) -> 37.402149 | R139: =J139-Q139 -> 50.097851 | S139: =IF(J139=0,0,R139/J139) -> 0.57254686 | T139: =INDEX($B$13:$B$25,MATCH(E139,$A$13:$A$25,0)) -> 0.7 | U139: =SUM(K139:O139)/(1-T139-Assumptions!$B$34*Assumptions!$B$35*(1+H139*$B$5)) -> 127.24111 | V139: =MROUND(U139*(1+H139*$B$5),$B$6) -> 153 | W139: =IF(I139=0,0,V139/I139-1) -> 0.45714286 | X139: =MROUND(V139*3*(1-$B$7),$B$6) -> 413 | Y139: =MROUND(V139*6*(1-$B$8),$B$6) -> 780 | Z139: =MROUND(V139*10*(1-$B$9),$B$6) -> 1224 | AC139: =IF(OR(D139="ACTIVE",D139="CONSULTATION"),1,0) -> 1
A140: Endosphere Body Contouring | B140: BodySphere 60 min | C140: aesthetics | D140: ACTIVE | E140: endosphere-vacuum | F140: 60 | G140: 60 | H140: 0.2 | I140: 120 | J140: =I140/(1+H140*$B$5) -> 100 | K140: 2 | L140: =G140/60*Machinery!$H$12*Assumptions!$B$23/100 -> 0.0945 | M140: =G140/60*Machinery!$K$12 -> 3.2407407 | N140: =G140/60*Machinery!$L$12 -> 7.1428571 | O140: =F140/60*Assumptions!$B$20 -> 34.463768 | P140: =I140*Assumptions!$B$34*Assumptions!$B$35 -> 1.938 | Q140: =SUM(K140:P140) -> 48.879866 | R140: =J140-Q140 -> 51.120134 | S140: =IF(J140=0,0,R140/J140) -> 0.51120134 | T140: =INDEX($B$13:$B$25,MATCH(E140,$A$13:$A$25,0)) -> 0.7 | U140: =SUM(K140:O140)/(1-T140-Assumptions!$B$34*Assumptions!$B$35*(1+H140*$B$5)) -> 167.27912 | V140: =MROUND(U140*(1+H140*$B$5),$B$6) -> 201 | W140: =IF(I140=0,0,V140/I140-1) -> 0.675 | X140: =MROUND(V140*3*(1-$B$7),$B$6) -> 543 | Y140: =MROUND(V140*6*(1-$B$8),$B$6) -> 1025 | Z140: =MROUND(V140*10*(1-$B$9),$B$6) -> 1608 | AC140: =IF(OR(D140="ACTIVE",D140="CONSULTATION"),1,0) -> 1
A141: Endosphere Body Contouring | B141: BodySphere & Facial Massage 60 min | C141: aesthetics | D141: ACTIVE | E141: endosphere-vacuum | F141: 60 | G141: 60 | H141: 0.2 | I141: 125 | J141: =I141/(1+H141*$B$5) -> 104.16667 | K141: 2.5 | L141: =G141/60*Machinery!$H$12*Assumptions!$B$23/100 -> 0.0945 | M141: =G141/60*Machinery!$K$12 -> 3.2407407 | N141: =G141/60*Machinery!$L$12 -> 7.1428571 | O141: =F141/60*Assumptions!$B$20 -> 34.463768 | P141: =I141*Assumptions!$B$34*Assumptions!$B$35 -> 2.01875 | Q141: =SUM(K141:P141) -> 49.460616 | R141: =J141-Q141 -> 54.706051 | S141: =IF(J141=0,0,R141/J141) -> 0.52517809 | T141: =INDEX($B$13:$B$25,MATCH(E141,$A$13:$A$25,0)) -> 0.7 | U141: =SUM(K141:O141)/(1-T141-Assumptions!$B$34*Assumptions!$B$35*(1+H141*$B$5)) -> 169.06089 | V141: =MROUND(U141*(1+H141*$B$5),$B$6) -> 203 | W141: =IF(I141=0,0,V141/I141-1) -> 0.624 | X141: =MROUND(V141*3*(1-$B$7),$B$6) -> 548 | Y141: =MROUND(V141*6*(1-$B$8),$B$6) -> 1035 | Z141: =MROUND(V141*10*(1-$B$9),$B$6) -> 1624 | AC141: =IF(OR(D141="ACTIVE",D141="CONSULTATION"),1,0) -> 1
A142: CACI Treatment | B142: CACI Face & Neck Lift | C142: aesthetics | D142: INACTIVE | E142: microcurrent-led | F142: 70 | G142: 70 | H142: 0.2 | I142: 140 | J142: =I142/(1+H142*$B$5) -> 116.66667 | K142: 4 | L142: =G142/60*Machinery!$H$15*Assumptions!$B$23/100 -> 0.0315 | M142: =G142/60*Machinery!$K$15 -> 2.9166667 | N142: =G142/60*Machinery!$L$15 -> 7.2916667 | O142: =F142/60*Assumptions!$B$20 -> 40.207729 | P142: =I142*Assumptions!$B$34*Assumptions!$B$35 -> 2.261 | Q142: =SUM(K142:P142) -> 56.708563 | R142: =J142-Q142 -> 59.958104 | S142: =IF(J142=0,0,R142/J142) -> 0.5139266 | T142: =INDEX($B$13:$B$25,MATCH(E142,$A$13:$A$25,0)) -> 0.7 | U142: =SUM(K142:O142)/(1-T142-Assumptions!$B$34*Assumptions!$B$35*(1+H142*$B$5)) -> 194.02595 | V142: =MROUND(U142*(1+H142*$B$5),$B$6) -> 233 | W142: =IF(I142=0,0,V142/I142-1) -> 0.66428571 | X142: =MROUND(V142*3*(1-$B$7),$B$6) -> 629 | Y142: =MROUND(V142*6*(1-$B$8),$B$6) -> 1188 | Z142: =MROUND(V142*10*(1-$B$9),$B$6) -> 1864 | AC142: =IF(OR(D142="ACTIVE",D142="CONSULTATION"),1,0) -> 0
A143: CACI Treatment | B143: CACI with Hydra Mask | C143: aesthetics | D143: INACTIVE | E143: microcurrent-led | F143: 70 | G143: 70 | H143: 0.2 | I143: 150 | J143: =I143/(1+H143*$B$5) -> 125 | K143: 8 | L143: =G143/60*Machinery!$H$15*Assumptions!$B$23/100 -> 0.0315 | M143: =G143/60*Machinery!$K$15 -> 2.9166667 | N143: =G143/60*Machinery!$L$15 -> 7.2916667 | O143: =F143/60*Assumptions!$B$20 -> 40.207729 | P143: =I143*Assumptions!$B$34*Assumptions!$B$35 -> 2.4225 | Q143: =SUM(K143:P143) -> 60.870063 | R143: =J143-Q143 -> 64.129937 | S143: =IF(J143=0,0,R143/J143) -> 0.5130395 | T143: =INDEX($B$13:$B$25,MATCH(E143,$A$13:$A$25,0)) -> 0.7 | U143: =SUM(K143:O143)/(1-T143-Assumptions!$B$34*Assumptions!$B$35*(1+H143*$B$5)) -> 208.2801 | V143: =MROUND(U143*(1+H143*$B$5),$B$6) -> 250 | W143: =IF(I143=0,0,V143/I143-1) -> 0.66666667 | X143: =MROUND(V143*3*(1-$B$7),$B$6) -> 675 | Y143: =MROUND(V143*6*(1-$B$8),$B$6) -> 1275 | Z143: =MROUND(V143*10*(1-$B$9),$B$6) -> 2000 | AC143: =IF(OR(D143="ACTIVE",D143="CONSULTATION"),1,0) -> 0
A144: CACI Treatment | B144: CACI Jaw Line Lift | C144: aesthetics | D144: INACTIVE | E144: microcurrent-led | F144: 40 | G144: 40 | H144: 0.2 | I144: 70 | J144: =I144/(1+H144*$B$5) -> 58.333333 | K144: 3 | L144: =G144/60*Machinery!$H$15*Assumptions!$B$23/100 -> 0.018 | M144: =G144/60*Machinery!$K$15 -> 1.6666667 | N144: =G144/60*Machinery!$L$15 -> 4.1666667 | O144: =F144/60*Assumptions!$B$20 -> 22.975845 | P144: =I144*Assumptions!$B$34*Assumptions!$B$35 -> 1.1305 | Q144: =SUM(K144:P144) -> 32.957679 | R144: =J144-Q144 -> 25.375655 | S144: =IF(J144=0,0,R144/J144) -> 0.43501122 | T144: =INDEX($B$13:$B$25,MATCH(E144,$A$13:$A$25,0)) -> 0.7 | U144: =SUM(K144:O144)/(1-T144-Assumptions!$B$34*Assumptions!$B$35*(1+H144*$B$5)) -> 113.41736 | V144: =MROUND(U144*(1+H144*$B$5),$B$6) -> 136 | W144: =IF(I144=0,0,V144/I144-1) -> 0.94285714 | X144: =MROUND(V144*3*(1-$B$7),$B$6) -> 367 | Y144: =MROUND(V144*6*(1-$B$8),$B$6) -> 694 | Z144: =MROUND(V144*10*(1-$B$9),$B$6) -> 1088 | AC144: =IF(OR(D144="ACTIVE",D144="CONSULTATION"),1,0) -> 0
A145: CACI Treatment | B145: Microcurrent | C145: aesthetics | D145: INACTIVE | E145: microcurrent-led | F145: 30 | G145: 30 | H145: 0.2 | I145: 85 | J145: =I145/(1+H145*$B$5) -> 70.833333 | K145: 3 | L145: =G145/60*Machinery!$H$15*Assumptions!$B$23/100 -> 0.0135 | M145: =G145/60*Machinery!$K$15 -> 1.25 | N145: =G145/60*Machinery!$L$15 -> 3.125 | O145: =F145/60*Assumptions!$B$20 -> 17.231884 | P145: =I145*Assumptions!$B$34*Assumptions!$B$35 -> 1.37275 | Q145: =SUM(K145:P145) -> 25.993134 | R145: =J145-Q145 -> 44.840199 | S145: =IF(J145=0,0,R145/J145) -> 0.63303811 | T145: =INDEX($B$13:$B$25,MATCH(E145,$A$13:$A$25,0)) -> 0.7 | U145: =SUM(K145:O145)/(1-T145-Assumptions!$B$34*Assumptions!$B$35*(1+H145*$B$5)) -> 87.735671 | V145: =MROUND(U145*(1+H145*$B$5),$B$6) -> 105 | W145: =IF(I145=0,0,V145/I145-1) -> 0.23529412 | X145: =MROUND(V145*3*(1-$B$7),$B$6) -> 284 | Y145: =MROUND(V145*6*(1-$B$8),$B$6) -> 536 | Z145: =MROUND(V145*10*(1-$B$9),$B$6) -> 840 | AC145: =IF(OR(D145="ACTIVE",D145="CONSULTATION"),1,0) -> 0
A146: Red Carpet Lift | B146: BB Glow | C146: aesthetics | D146: INACTIVE | E146: microneedling-pen | F146: 50 | G146: 50 | H146: 0.2 | I146: 145 | J146: =I146/(1+H146*$B$5) -> 120.83333 | K146: 25 | L146: =G146/60*Machinery!$H$13*Assumptions!$B$23/100 -> 0.0045 | M146: =G146/60*Machinery!$K$13 -> 0.38580247 | N146: =G146/60*Machinery!$L$13 -> 2.8935185 | O146: =F146/60*Assumptions!$B$20 -> 28.719807 | P146: =I146*Assumptions!$B$34*Assumptions!$B$35 -> 2.34175 | Q146: =SUM(K146:P146) -> 59.345378 | R146: =J146-Q146 -> 61.487956 | S146: =IF(J146=0,0,R146/J146) -> 0.50886584 | T146: =INDEX($B$13:$B$25,MATCH(E146,$A$13:$A$25,0)) -> 0.65 | U146: =SUM(K146:O146)/(1-T146-Assumptions!$B$34*Assumptions!$B$35*(1+H146*$B$5)) -> 172.41434 | V146: =MROUND(U146*(1+H146*$B$5),$B$6) -> 207 | W146: =IF(I146=0,0,V146/I146-1) -> 0.42758621 | X146: =MROUND(V146*3*(1-$B$7),$B$6) -> 559 | Y146: =MROUND(V146*6*(1-$B$8),$B$6) -> 1056 | Z146: =MROUND(V146*10*(1-$B$9),$B$6) -> 1656 | AC146: =IF(OR(D146="ACTIVE",D146="CONSULTATION"),1,0) -> 0
A147: BB Glow | B147: BB Glow | C147: aesthetics | D147: ACTIVE | E147: microneedling-pen | F147: 60 | G147: 60 | H147: 0.2 | I147: 145 | J147: =I147/(1+H147*$B$5) -> 120.83333 | K147: 25 | L147: =G147/60*Machinery!$H$13*Assumptions!$B$23/100 -> 0.0054 | M147: =G147/60*Machinery!$K$13 -> 0.46296296 | N147: =G147/60*Machinery!$L$13 -> 3.4722222 | O147: =F147/60*Assumptions!$B$20 -> 34.463768 | P147: =I147*Assumptions!$B$34*Assumptions!$B$35 -> 2.34175 | Q147: =SUM(K147:P147) -> 65.746103 | R147: =J147-Q147 -> 55.08723 | S147: =IF(J147=0,0,R147/J147) -> 0.45589432 | T147: =INDEX($B$13:$B$25,MATCH(E147,$A$13:$A$25,0)) -> 0.65 | U147: =SUM(K147:O147)/(1-T147-Assumptions!$B$34*Assumptions!$B$35*(1+H147*$B$5)) -> 191.7741 | V147: =MROUND(U147*(1+H147*$B$5),$B$6) -> 230 | W147: =IF(I147=0,0,V147/I147-1) -> 0.5862069 | X147: =MROUND(V147*3*(1-$B$7),$B$6) -> 621 | Y147: =MROUND(V147*6*(1-$B$8),$B$6) -> 1173 | Z147: =MROUND(V147*10*(1-$B$9),$B$6) -> 1840 | AC147: =IF(OR(D147="ACTIVE",D147="CONSULTATION"),1,0) -> 1
A148: Massage | B148: Deep Tissue Massage | C148: aesthetics | D148: ACTIVE | E148: none-manual | F148: 60 | G148: 0 | H148: 0.2 | I148: 95 | J148: =I148/(1+H148*$B$5) -> 79.166667 | K148: 3 | L148: =G148/60*Machinery!$H$17*Assumptions!$B$23/100 -> 0 | M148: =G148/60*Machinery!$K$17 -> 0 | N148: =G148/60*Machinery!$L$17 -> 0 | O148: =F148/60*Assumptions!$B$20 -> 34.463768 | P148: =I148*Assumptions!$B$34*Assumptions!$B$35 -> 1.53425 | Q148: =SUM(K148:P148) -> 38.998018 | R148: =J148-Q148 -> 40.168649 | S148: =IF(J148=0,0,R148/J148) -> 0.50739346 | T148: =INDEX($B$13:$B$25,MATCH(E148,$A$13:$A$25,0)) -> 0.65 | U148: =SUM(K148:O148)/(1-T148-Assumptions!$B$34*Assumptions!$B$35*(1+H148*$B$5)) -> 113.31368 | V148: =MROUND(U148*(1+H148*$B$5),$B$6) -> 136 | W148: =IF(I148=0,0,V148/I148-1) -> 0.43157895 | X148: =MROUND(V148*3*(1-$B$7),$B$6) -> 367 | Y148: =MROUND(V148*6*(1-$B$8),$B$6) -> 694 | Z148: =MROUND(V148*10*(1-$B$9),$B$6) -> 1088 | AC148: =IF(OR(D148="ACTIVE",D148="CONSULTATION"),1,0) -> 1
A149: Massage | B149: Swedish Massage | C149: aesthetics | D149: ACTIVE | E149: none-manual | F149: 60 | G149: 0 | H149: 0.2 | I149: 95 | J149: =I149/(1+H149*$B$5) -> 79.166667 | K149: 3 | L149: =G149/60*Machinery!$H$17*Assumptions!$B$23/100 -> 0 | M149: =G149/60*Machinery!$K$17 -> 0 | N149: =G149/60*Machinery!$L$17 -> 0 | O149: =F149/60*Assumptions!$B$20 -> 34.463768 | P149: =I149*Assumptions!$B$34*Assumptions!$B$35 -> 1.53425 | Q149: =SUM(K149:P149) -> 38.998018 | R149: =J149-Q149 -> 40.168649 | S149: =IF(J149=0,0,R149/J149) -> 0.50739346 | T149: =INDEX($B$13:$B$25,MATCH(E149,$A$13:$A$25,0)) -> 0.65 | U149: =SUM(K149:O149)/(1-T149-Assumptions!$B$34*Assumptions!$B$35*(1+H149*$B$5)) -> 113.31368 | V149: =MROUND(U149*(1+H149*$B$5),$B$6) -> 136 | W149: =IF(I149=0,0,V149/I149-1) -> 0.43157895 | X149: =MROUND(V149*3*(1-$B$7),$B$6) -> 367 | Y149: =MROUND(V149*6*(1-$B$8),$B$6) -> 694 | Z149: =MROUND(V149*10*(1-$B$9),$B$6) -> 1088 | AC149: =IF(OR(D149="ACTIVE",D149="CONSULTATION"),1,0) -> 1
A150: Massage | B150: Back, Neck & Shoulders Massage | C150: aesthetics | D150: ACTIVE | E150: none-manual | F150: 30 | G150: 0 | H150: 0.2 | I150: 60 | J150: =I150/(1+H150*$B$5) -> 50 | K150: 2 | L150: =G150/60*Machinery!$H$17*Assumptions!$B$23/100 -> 0 | M150: =G150/60*Machinery!$K$17 -> 0 | N150: =G150/60*Machinery!$L$17 -> 0 | O150: =F150/60*Assumptions!$B$20 -> 17.231884 | P150: =I150*Assumptions!$B$34*Assumptions!$B$35 -> 0.969 | Q150: =SUM(K150:P150) -> 20.200884 | R150: =J150-Q150 -> 29.799116 | S150: =IF(J150=0,0,R150/J150) -> 0.59598232 | T150: =INDEX($B$13:$B$25,MATCH(E150,$A$13:$A$25,0)) -> 0.65 | U150: =SUM(K150:O150)/(1-T150-Assumptions!$B$34*Assumptions!$B$35*(1+H150*$B$5)) -> 58.169149 | V150: =MROUND(U150*(1+H150*$B$5),$B$6) -> 70 | W150: =IF(I150=0,0,V150/I150-1) -> 0.16666667 | X150: =MROUND(V150*3*(1-$B$7),$B$6) -> 189 | Y150: =MROUND(V150*6*(1-$B$8),$B$6) -> 357 | Z150: =MROUND(V150*10*(1-$B$9),$B$6) -> 560 | AC150: =IF(OR(D150="ACTIVE",D150="CONSULTATION"),1,0) -> 1
A151: Massage | B151: Relaxing Massage | C151: aesthetics | D151: ACTIVE | E151: none-manual | F151: 60 | G151: 0 | H151: 0.2 | I151: 95 | J151: =I151/(1+H151*$B$5) -> 79.166667 | K151: 3 | L151: =G151/60*Machinery!$H$17*Assumptions!$B$23/100 -> 0 | M151: =G151/60*Machinery!$K$17 -> 0 | N151: =G151/60*Machinery!$L$17 -> 0 | O151: =F151/60*Assumptions!$B$20 -> 34.463768 | P151: =I151*Assumptions!$B$34*Assumptions!$B$35 -> 1.53425 | Q151: =SUM(K151:P151) -> 38.998018 | R151: =J151-Q151 -> 40.168649 | S151: =IF(J151=0,0,R151/J151) -> 0.50739346 | T151: =INDEX($B$13:$B$25,MATCH(E151,$A$13:$A$25,0)) -> 0.65 | U151: =SUM(K151:O151)/(1-T151-Assumptions!$B$34*Assumptions!$B$35*(1+H151*$B$5)) -> 113.31368 | V151: =MROUND(U151*(1+H151*$B$5),$B$6) -> 136 | W151: =IF(I151=0,0,V151/I151-1) -> 0.43157895 | X151: =MROUND(V151*3*(1-$B$7),$B$6) -> 367 | Y151: =MROUND(V151*6*(1-$B$8),$B$6) -> 694 | Z151: =MROUND(V151*10*(1-$B$9),$B$6) -> 1088 | AC151: =IF(OR(D151="ACTIVE",D151="CONSULTATION"),1,0) -> 1
...

Sheet Volumes
A1: Volume & revenue forecast — capacity × utilisation × mix
A2: Room capacity comes from Assumptions. The utilisation ramp (blue row) is THE dominant free assumption — current run-rate is ~3% (225 bookings in the 90 days after the May 2026 reopening). Mix % splits treated hours across machine classes; seeded from live booking mix. Per-class average price/cost auto-computed from the Pricing tab (sellable variants); use the blue override column to demand-weight.
A4: Family | B4: Class key | C4: Avg session min (auto) | D4: Min override | E4: Min used | F4: Avg price £ (auto) | G4: Price override | H4: Price used £ | I4: Avg direct cost £ (auto) | J4: Cost override | K4: Cost used £ | L4: Machine min/session | M4: kWh/treatment hr | N4: Hours mix %
A5: Laser hair removal (diode) | B5: diode-laser | C5: =IFERROR(AVERAGEIFS(Pricing!$F$29:$F$194,Pricing!$E$29:$E$194,B5,Pricing!$AC$29:$AC$194,1),0) -> 30.25 | E5: =IF(D5<>"",D5,C5) -> 30.25 | F5: =IFERROR(AVERAGEIFS(Pricing!$I$29:$I$194,Pricing!$E$29:$E$194,B5,Pricing!$AC$29:$AC$194,1),0) -> 80.133333 | H5: =IF(G5<>"",G5,F5) -> 80.133333 | I5: =IFERROR(AVERAGEIFS(Pricing!$K$29:$K$194,Pricing!$E$29:$E$194,B5,Pricing!$AC$29:$AC$194,1)+AVERAGEIFS(Pricing!$L$29:$L$194,Pricing!$E$29:$E$194,B5,Pricing!$AC$29:$AC$194,1)+AVERAGEIFS(Pricing!$M$29:$M$194,Pricing!$E$29:$E$194,B5,Pricing!$AC$29:$AC$194,1),0) -> 2.113625 | K5: =IF(J5<>"",J5,I5) -> 2.113625 | L5: =IFERROR(AVERAGEIFS(Pricing!$G$29:$G$194,Pricing!$E$29:$E$194,B5,Pricing!$AC$29:$AC$194,1),0) -> 30.25 | M5: =Machinery!$H$5 -> 1 | N5: 0.495
A6: IPL / laser skin | B6: laser-ipl-platform | C6: =IFERROR(AVERAGEIFS(Pricing!$F$29:$F$194,Pricing!$E$29:$E$194,B6,Pricing!$AC$29:$AC$194,1),0) -> 35 | E6: =IF(D6<>"",D6,C6) -> 35 | F6: =IFERROR(AVERAGEIFS(Pricing!$I$29:$I$194,Pricing!$E$29:$E$194,B6,Pricing!$AC$29:$AC$194,1),0) -> 203.58333 | H6: =IF(G6<>"",G6,F6) -> 203.58333 | I6: =IFERROR(AVERAGEIFS(Pricing!$K$29:$K$194,Pricing!$E$29:$E$194,B6,Pricing!$AC$29:$AC$194,1)+AVERAGEIFS(Pricing!$L$29:$L$194,Pricing!$E$29:$E$194,B6,Pricing!$AC$29:$AC$194,1)+AVERAGEIFS(Pricing!$M$29:$M$194,Pricing!$E$29:$E$194,B6,Pricing!$AC$29:$AC$194,1),0) -> 7.0704444 | K6: =IF(J6<>"",J6,I6) -> 7.0704444 | L6: =IFERROR(AVERAGEIFS(Pricing!$G$29:$G$194,Pricing!$E$29:$E$194,B6,Pricing!$AC$29:$AC$194,1),0) -> 35 | M6: =Machinery!$H$6 -> 0.8 | N6: 0.03
A7: HIFU lifting | B7: hifu | C7: =IFERROR(AVERAGEIFS(Pricing!$F$29:$F$194,Pricing!$E$29:$E$194,B7,Pricing!$AC$29:$AC$194,1),0) -> 50 | E7: =IF(D7<>"",D7,C7) -> 50 | F7: =IFERROR(AVERAGEIFS(Pricing!$I$29:$I$194,Pricing!$E$29:$E$194,B7,Pricing!$AC$29:$AC$194,1),0) -> 376.69231 | H7: =IF(G7<>"",G7,F7) -> 376.69231 | I7: =IFERROR(AVERAGEIFS(Pricing!$K$29:$K$194,Pricing!$E$29:$E$194,B7,Pricing!$AC$29:$AC$194,1)+AVERAGEIFS(Pricing!$L$29:$L$194,Pricing!$E$29:$E$194,B7,Pricing!$AC$29:$AC$194,1)+AVERAGEIFS(Pricing!$M$29:$M$194,Pricing!$E$29:$E$194,B7,Pricing!$AC$29:$AC$194,1),0) -> 70.548269 | K7: =IF(J7<>"",J7,I7) -> 70.548269 | L7: =IFERROR(AVERAGEIFS(Pricing!$G$29:$G$194,Pricing!$E$29:$E$194,B7,Pricing!$AC$29:$AC$194,1),0) -> 50 | M7: =Machinery!$H$9 -> 0.3 | N7: 0.02
A8: RF tightening | B8: rf-tightening | C8: =IFERROR(AVERAGEIFS(Pricing!$F$29:$F$194,Pricing!$E$29:$E$194,B8,Pricing!$AC$29:$AC$194,1),0) -> 60 | E8: =IF(D8<>"",D8,C8) -> 60 | F8: =IFERROR(AVERAGEIFS(Pricing!$I$29:$I$194,Pricing!$E$29:$E$194,B8,Pricing!$AC$29:$AC$194,1),0) -> 260 | H8: =IF(G8<>"",G8,F8) -> 260 | I8: =IFERROR(AVERAGEIFS(Pricing!$K$29:$K$194,Pricing!$E$29:$E$194,B8,Pricing!$AC$29:$AC$194,1)+AVERAGEIFS(Pricing!$L$29:$L$194,Pricing!$E$29:$E$194,B8,Pricing!$AC$29:$AC$194,1)+AVERAGEIFS(Pricing!$M$29:$M$194,Pricing!$E$29:$E$194,B8,Pricing!$AC$29:$AC$194,1),0) -> 23.968333 | K8: =IF(J8<>"",J8,I8) -> 23.968333 | L8: =IFERROR(AVERAGEIFS(Pricing!$G$29:$G$194,Pricing!$E$29:$E$194,B8,Pricing!$AC$29:$AC$194,1),0) -> 60 | M8: =Machinery!$H$10 -> 0.5 | N8: 0.02
A9: HydraFacial & facials | B9: hydrafacial-platform | C9: =IFERROR(AVERAGEIFS(Pricing!$F$29:$F$194,Pricing!$E$29:$E$194,B9,Pricing!$AC$29:$AC$194,1),0) -> 65.909091 | E9: =IF(D9<>"",D9,C9) -> 65.909091 | F9: =IFERROR(AVERAGEIFS(Pricing!$I$29:$I$194,Pricing!$E$29:$E$194,B9,Pricing!$AC$29:$AC$194,1),0) -> 157.72727 | H9: =IF(G9<>"",G9,F9) -> 157.72727 | I9: =IFERROR(AVERAGEIFS(Pricing!$K$29:$K$194,Pricing!$E$29:$E$194,B9,Pricing!$AC$29:$AC$194,1)+AVERAGEIFS(Pricing!$L$29:$L$194,Pricing!$E$29:$E$194,B9,Pricing!$AC$29:$AC$194,1)+AVERAGEIFS(Pricing!$M$29:$M$194,Pricing!$E$29:$E$194,B9,Pricing!$AC$29:$AC$194,1),0) -> 20.984192 | K9: =IF(J9<>"",J9,I9) -> 20.984192 | L9: =IFERROR(AVERAGEIFS(Pricing!$G$29:$G$194,Pricing!$E$29:$E$194,B9,Pricing!$AC$29:$AC$194,1),0) -> 65.909091 | M9: =Machinery!$H$11 -> 0.2 | N9: 0.11
A10: Body contouring (Endosphere/vacuum) | B10: endosphere-vacuum | C10: =IFERROR(AVERAGEIFS(Pricing!$F$29:$F$194,Pricing!$E$29:$E$194,B10,Pricing!$AC$29:$AC$194,1),0) -> 51.428571 | E10: =IF(D10<>"",D10,C10) -> 51.428571 | F10: =IFERROR(AVERAGEIFS(Pricing!$I$29:$I$194,Pricing!$E$29:$E$194,B10,Pricing!$AC$29:$AC$194,1),0) -> 103.57143 | H10: =IF(G10<>"",G10,F10) -> 103.57143 | I10: =IFERROR(AVERAGEIFS(Pricing!$K$29:$K$194,Pricing!$E$29:$E$194,B10,Pricing!$AC$29:$AC$194,1)+AVERAGEIFS(Pricing!$L$29:$L$194,Pricing!$E$29:$E$194,B10,Pricing!$AC$29:$AC$194,1)+AVERAGEIFS(Pricing!$M$29:$M$194,Pricing!$E$29:$E$194,B10,Pricing!$AC$29:$AC$194,1),0) -> 4.9302063 | K10: =IF(J10<>"",J10,I10) -> 4.9302063 | L10: =IFERROR(AVERAGEIFS(Pricing!$G$29:$G$194,Pricing!$E$29:$E$194,B10,Pricing!$AC$29:$AC$194,1),0) -> 51.428571 | M10: =Machinery!$H$12 -> 0.35 | N10: 0.08
A11: Microneedling & BB Glow | B11: microneedling-pen | C11: =IFERROR(AVERAGEIFS(Pricing!$F$29:$F$194,Pricing!$E$29:$E$194,B11,Pricing!$AC$29:$AC$194,1),0) -> 60 | E11: =IF(D11<>"",D11,C11) -> 60 | F11: =IFERROR(AVERAGEIFS(Pricing!$I$29:$I$194,Pricing!$E$29:$E$194,B11,Pricing!$AC$29:$AC$194,1),0) -> 125 | H11: =IF(G11<>"",G11,F11) -> 125 | I11: =IFERROR(AVERAGEIFS(Pricing!$K$29:$K$194,Pricing!$E$29:$E$194,B11,Pricing!$AC$29:$AC$194,1)+AVERAGEIFS(Pricing!$L$29:$L$194,Pricing!$E$29:$E$194,B11,Pricing!$AC$29:$AC$194,1)+AVERAGEIFS(Pricing!$M$29:$M$194,Pricing!$E$29:$E$194,B11,Pricing!$AC$29:$AC$194,1),0) -> 25.968363 | K11: =IF(J11<>"",J11,I11) -> 25.968363 | L11: =IFERROR(AVERAGEIFS(Pricing!$G$29:$G$194,Pricing!$E$29:$E$194,B11,Pricing!$AC$29:$AC$194,1),0) -> 60 | M11: =Machinery!$H$13 -> 0.02 | N11: 0.03
A12: Microdermabrasion | B12: microdermabrasion | C12: =IFERROR(AVERAGEIFS(Pricing!$F$29:$F$194,Pricing!$E$29:$E$194,B12,Pricing!$AC$29:$AC$194,1),0) -> 30 | E12: =IF(D12<>"",D12,C12) -> 30 | F12: =IFERROR(AVERAGEIFS(Pricing!$I$29:$I$194,Pricing!$E$29:$E$194,B12,Pricing!$AC$29:$AC$194,1),0) -> 80 | H12: =IF(G12<>"",G12,F12) -> 80 | I12: =IFERROR(AVERAGEIFS(Pricing!$K$29:$K$194,Pricing!$E$29:$E$194,B12,Pricing!$AC$29:$AC$194,1)+AVERAGEIFS(Pricing!$L$29:$L$194,Pricing!$E$29:$E$194,B12,Pricing!$AC$29:$AC$194,1)+AVERAGEIFS(Pricing!$M$29:$M$194,Pricing!$E$29:$E$194,B12,Pricing!$AC$29:$AC$194,1),0) -> 3.59625 | K12: =IF(J12<>"",J12,I12) -> 3.59625 | L12: =IFERROR(AVERAGEIFS(Pricing!$G$29:$G$194,Pricing!$E$29:$E$194,B12,Pricing!$AC$29:$AC$194,1),0) -> 30 | M12: =Machinery!$H$14 -> 0.25 | N12: 0.005
A13: Microcurrent & LED | B13: microcurrent-led | C13: =IFERROR(AVERAGEIFS(Pricing!$F$29:$F$194,Pricing!$E$29:$E$194,B13,Pricing!$AC$29:$AC$194,1),0) -> 48.75 | E13: =IF(D13<>"",D13,C13) -> 48.75 | F13: =IFERROR(AVERAGEIFS(Pricing!$I$29:$I$194,Pricing!$E$29:$E$194,B13,Pricing!$AC$29:$AC$194,1),0) -> 105 | H13: =IF(G13<>"",G13,F13) -> 105 | I13: =IFERROR(AVERAGEIFS(Pricing!$K$29:$K$194,Pricing!$E$29:$E$194,B13,Pricing!$AC$29:$AC$194,1)+AVERAGEIFS(Pricing!$L$29:$L$194,Pricing!$E$29:$E$194,B13,Pricing!$AC$29:$AC$194,1)+AVERAGEIFS(Pricing!$M$29:$M$194,Pricing!$E$29:$E$194,B13,Pricing!$AC$29:$AC$194,1),0) -> 5.8031875 | K13: =IF(J13<>"",J13,I13) -> 5.8031875 | L13: =IFERROR(AVERAGEIFS(Pricing!$G$29:$G$194,Pricing!$E$29:$E$194,B13,Pricing!$AC$29:$AC$194,1),0) -> 48.75 | M13: =Machinery!$H$15 -> 0.1 | N13: 0.04
A14: Injectables | B14: none-injectables | C14: =IFERROR(AVERAGEIFS(Pricing!$F$29:$F$194,Pricing!$E$29:$E$194,B14,Pricing!$AC$29:$AC$194,1),0) -> 40.227273 | E14: =IF(D14<>"",D14,C14) -> 40.227273 | F14: =IFERROR(AVERAGEIFS(Pricing!$I$29:$I$194,Pricing!$E$29:$E$194,B14,Pricing!$AC$29:$AC$194,1),0) -> 204.54545 | H14: =IF(G14<>"",G14,F14) -> 204.54545 | I14: =IFERROR(AVERAGEIFS(Pricing!$K$29:$K$194,Pricing!$E$29:$E$194,B14,Pricing!$AC$29:$AC$194,1)+AVERAGEIFS(Pricing!$L$29:$L$194,Pricing!$E$29:$E$194,B14,Pricing!$AC$29:$AC$194,1)+AVERAGEIFS(Pricing!$M$29:$M$194,Pricing!$E$29:$E$194,B14,Pricing!$AC$29:$AC$194,1),0) -> 55.227273 | K14: =IF(J14<>"",J14,I14) -> 55.227273 | L14: =IFERROR(AVERAGEIFS(Pricing!$G$29:$G$194,Pricing!$E$29:$E$194,B14,Pricing!$AC$29:$AC$194,1),0) -> 0 | M14: =Machinery!$H$16 -> 0 | N14: 0.03
A15: Peels, massage & manual | B15: none-manual | C15: =IFERROR(AVERAGEIFS(Pricing!$F$29:$F$194,Pricing!$E$29:$E$194,B15,Pricing!$AC$29:$AC$194,1),0) -> 46.25 | E15: =IF(D15<>"",D15,C15) -> 46.25 | F15: =IFERROR(AVERAGEIFS(Pricing!$I$29:$I$194,Pricing!$E$29:$E$194,B15,Pricing!$AC$29:$AC$194,1),0) -> 78.75 | H15: =IF(G15<>"",G15,F15) -> 78.75 | I15: =IFERROR(AVERAGEIFS(Pricing!$K$29:$K$194,Pricing!$E$29:$E$194,B15,Pricing!$AC$29:$AC$194,1)+AVERAGEIFS(Pricing!$L$29:$L$194,Pricing!$E$29:$E$194,B15,Pricing!$AC$29:$AC$194,1)+AVERAGEIFS(Pricing!$M$29:$M$194,Pricing!$E$29:$E$194,B15,Pricing!$AC$29:$AC$194,1),0) -> 3.375 | K15: =IF(J15<>"",J15,I15) -> 3.375 | L15: =IFERROR(AVERAGEIFS(Pricing!$G$29:$G$194,Pricing!$E$29:$E$194,B15,Pricing!$AC$29:$AC$194,1),0) -> 0 | M15: =Machinery!$H$17 -> 0.1 | N15: 0.02
A16: CO2 laser (intimate) — coming soon | B16: co2-laser | C16: =IFERROR(AVERAGEIFS(Pricing!$F$29:$F$194,Pricing!$E$29:$E$194,B16,Pricing!$AC$29:$AC$194,1),0) -> 0 | E16: =IF(D16<>"",D16,C16) -> 0 | F16: =IFERROR(AVERAGEIFS(Pricing!$I$29:$I$194,Pricing!$E$29:$E$194,B16,Pricing!$AC$29:$AC$194,1),0) -> 0 | H16: =IF(G16<>"",G16,F16) -> 0 | I16: =IFERROR(AVERAGEIFS(Pricing!$K$29:$K$194,Pricing!$E$29:$E$194,B16,Pricing!$AC$29:$AC$194,1)+AVERAGEIFS(Pricing!$L$29:$L$194,Pricing!$E$29:$E$194,B16,Pricing!$AC$29:$AC$194,1)+AVERAGEIFS(Pricing!$M$29:$M$194,Pricing!$E$29:$E$194,B16,Pricing!$AC$29:$AC$194,1),0) -> 0 | K16: =IF(J16<>"",J16,I16) -> 0 | L16: =IFERROR(AVERAGEIFS(Pricing!$G$29:$G$194,Pricing!$E$29:$E$194,B16,Pricing!$AC$29:$AC$194,1),0) -> 0 | M16: =Machinery!$H$8 -> 0.4 | N16: 0
A17: Tattoo/pigment removal (pico) — not yet purchased | B17: pico-laser-PLANNED | C17: =IFERROR(AVERAGEIFS(Pricing!$F$29:$F$194,Pricing!$E$29:$E$194,B17,Pricing!$AC$29:$AC$194,1),0) -> 0 | E17: =IF(D17<>"",D17,C17) -> 0 | F17: =IFERROR(AVERAGEIFS(Pricing!$I$29:$I$194,Pricing!$E$29:$E$194,B17,Pricing!$AC$29:$AC$194,1),0) -> 0 | H17: =IF(G17<>"",G17,F17) -> 0 | I17: =IFERROR(AVERAGEIFS(Pricing!$K$29:$K$194,Pricing!$E$29:$E$194,B17,Pricing!$AC$29:$AC$194,1)+AVERAGEIFS(Pricing!$L$29:$L$194,Pricing!$E$29:$E$194,B17,Pricing!$AC$29:$AC$194,1)+AVERAGEIFS(Pricing!$M$29:$M$194,Pricing!$E$29:$E$194,B17,Pricing!$AC$29:$AC$194,1),0) -> 0 | K17: =IF(J17<>"",J17,I17) -> 0 | L17: =IFERROR(AVERAGEIFS(Pricing!$G$29:$G$194,Pricing!$E$29:$E$194,B17,Pricing!$AC$29:$AC$194,1),0) -> 0 | M17: =Machinery!$H$7 -> 1 | N17: 0
A18: Consultations (no revenue) | B18: consultation | C18: 0 | D18: 20 | E18: =IF(D18<>"",D18,C18) -> 20 | F18: 0 | G18: 0 | H18: =IF(G18<>"",G18,F18) -> 0 | I18: 0 | J18: 1 | K18: =IF(J18<>"",J18,I18) -> 1 | L18: 0 | M18: 0 | N18: 0.12
A19: Mix check (must be 100%) | N19: =SUM(N5:N18) -> 1
A22: MONTHLY FORECAST
A23: Month | C23: =EDATE(Assumptions!$B$5,COLUMN()-3) -> 46266 | D23: =EDATE(Assumptions!$B$5,COLUMN()-3) -> 46296 | E23: =EDATE(Assumptions!$B$5,COLUMN()-3) -> 46327 | F23: =EDATE(Assumptions!$B$5,COLUMN()-3) -> 46357 | G23: =EDATE(Assumptions!$B$5,COLUMN()-3) -> 46388 | H23: =EDATE(Assumptions!$B$5,COLUMN()-3) -> 46419 | I23: =EDATE(Assumptions!$B$5,COLUMN()-3) -> 46447 | J23: =EDATE(Assumptions!$B$5,COLUMN()-3) -> 46478 | ... AL23: =EDATE(Assumptions!$B$5,COLUMN()-3) -> 47331
A24: Days open | C24: =ROUND(DAY(EOMONTH(C$23,0))*Assumptions!$B$8/7,0) -> 26 | D24: =ROUND(DAY(EOMONTH(D$23,0))*Assumptions!$B$8/7,0) -> 27 | E24: =ROUND(DAY(EOMONTH(E$23,0))*Assumptions!$B$8/7,0) -> 26 | F24: =ROUND(DAY(EOMONTH(F$23,0))*Assumptions!$B$8/7,0) -> 27 | G24: =ROUND(DAY(EOMONTH(G$23,0))*Assumptions!$B$8/7,0) -> 27 | H24: =ROUND(DAY(EOMONTH(H$23,0))*Assumptions!$B$8/7,0) -> 24 | I24: =ROUND(DAY(EOMONTH(I$23,0))*Assumptions!$B$8/7,0) -> 27 | J24: =ROUND(DAY(EOMONTH(J$23,0))*Assumptions!$B$8/7,0) -> 26 | ... AL24: =ROUND(DAY(EOMONTH(AL$23,0))*Assumptions!$B$8/7,0) -> 27
A25: Room-hours available | C25: =Assumptions!$B$6*Assumptions!$B$9*C$24 -> 2223 | D25: =Assumptions!$B$6*Assumptions!$B$9*D$24 -> 2308.5 | E25: =Assumptions!$B$6*Assumptions!$B$9*E$24 -> 2223 | F25: =Assumptions!$B$6*Assumptions!$B$9*F$24 -> 2308.5 | G25: =Assumptions!$B$6*Assumptions!$B$9*G$24 -> 2308.5 | H25: =Assumptions!$B$6*Assumptions!$B$9*H$24 -> 2052 | I25: =Assumptions!$B$6*Assumptions!$B$9*I$24 -> 2308.5 | J25: =Assumptions!$B$6*Assumptions!$B$9*J$24 -> 2223 | ... AL25: =Assumptions!$B$6*Assumptions!$B$9*AL$24 -> 2308.5
A26: Utilisation % (EDIT — the model's biggest lever) | C26: 0.04 | D26: 0.046 | E26: 0.052 | F26: 0.058 | G26: 0.064 | H26: 0.07 | I26: 0.076 | J26: 0.082 | K26: 0.088 | L26: 0.094 | M26: 0.1 | N26: 0.106 | O26: 0.112 | P26: 0.118 | Q26: 0.124 | R26: 0.13 | S26: 0.136 | T26: 0.142 | U26: 0.148 | V26: 0.154 | W26: 0.16 | X26: 0.166 | Y26: 0.172 | Z26: 0.178 | AA26: 0.184 | AB26: 0.19 | AC26: 0.196 | AD26: 0.202 | AE26: 0.208 | AF26: 0.214 | AG26: 0.22 | AH26: 0.226 | AI26: 0.232 | AJ26: 0.238 | AK26: 0.244 | AL26: 0.25
A27: Treated hours | C27: =C$25*C$26 -> 88.92 | D27: =D$25*D$26 -> 106.191 | E27: =E$25*E$26 -> 115.596 | F27: =F$25*F$26 -> 133.893 | G27: =G$25*G$26 -> 147.744 | H27: =H$25*H$26 -> 143.64 | I27: =I$25*I$26 -> 175.446 | J27: =J$25*J$26 -> 182.286 | ... AL27: =AL$25*AL$26 -> 577.125
A29: Laser hair removal (diode)
A30: hours | C30: =C$27*$N$5 -> 44.0154 | D30: =D$27*$N$5 -> 52.564545 | E30: =E$27*$N$5 -> 57.22002 | F30: =F$27*$N$5 -> 66.277035 | G30: =G$27*$N$5 -> 73.13328 | H30: =H$27*$N$5 -> 71.1018 | I30: =I$27*$N$5 -> 86.84577 | J30: =J$27*$N$5 -> 90.23157 | ... AL30: =AL$27*$N$5 -> 285.67687
A31: sessions | C31: =IF($E$5=0,0,C30*60/$E$5) -> 87.303273 | D31: =IF($E$5=0,0,D30*60/$E$5) -> 104.26025 | E31: =IF($E$5=0,0,E30*60/$E$5) -> 113.49425 | F31: =IF($E$5=0,0,F30*60/$E$5) -> 131.45858 | G31: =IF($E$5=0,0,G30*60/$E$5) -> 145.05775 | H31: =IF($E$5=0,0,H30*60/$E$5) -> 141.02836 | I31: =IF($E$5=0,0,I30*60/$E$5) -> 172.25607 | J31: =IF($E$5=0,0,J30*60/$E$5) -> 178.97171 | ... AL31: =IF($E$5=0,0,AL30*60/$E$5) -> 566.63182
A32: gross revenue | C32: =C31*$H$5 -> 6995.9023 | D32: =D31*$H$5 -> 8354.7217 | E32: =E31*$H$5 -> 9094.6729 | F32: =F31*$H$5 -> 10534.214 | G32: =G31*$H$5 -> 11623.961 | H32: =H31*$H$5 -> 11301.073 | I32: =I31*$H$5 -> 13803.453 | J32: =J31*$H$5 -> 14341.6 | ... AL32: =AL31*$H$5 -> 45406.096
A33: direct costs | C33: =C31*$K$5 -> 184.52638 | D33: =D31*$K$5 -> 220.36708 | E33: =E31*$K$5 -> 239.88429 | F33: =F31*$K$5 -> 277.85414 | G33: =G31*$K$5 -> 306.59768 | H33: =H31*$K$5 -> 298.08108 | I33: =I31*$K$5 -> 364.08474 | J33: =J31*$K$5 -> 378.27908 | ... AL33: =AL31*$K$5 -> 1197.6472
A34: machine kWh | C34: =C31*$L$5/60*$M$5 -> 44.0154 | D34: =D31*$L$5/60*$M$5 -> 52.564545 | E34: =E31*$L$5/60*$M$5 -> 57.22002 | F34: =F31*$L$5/60*$M$5 -> 66.277035 | G34: =G31*$L$5/60*$M$5 -> 73.13328 | H34: =H31*$L$5/60*$M$5 -> 71.1018 | I34: =I31*$L$5/60*$M$5 -> 86.84577 | J34: =J31*$L$5/60*$M$5 -> 90.23157 | ... AL34: =AL31*$L$5/60*$M$5 -> 285.67687
A35: IPL / laser skin
A36: hours | C36: =C$27*$N$6 -> 2.6676 | D36: =D$27*$N$6 -> 3.18573 | E36: =E$27*$N$6 -> 3.46788 | F36: =F$27*$N$6 -> 4.01679 | G36: =G$27*$N$6 -> 4.43232 | H36: =H$27*$N$6 -> 4.3092 | I36: =I$27*$N$6 -> 5.26338 | J36: =J$27*$N$6 -> 5.46858 | ... AL36: =AL$27*$N$6 -> 17.31375
A37: sessions | C37: =IF($E$6=0,0,C36*60/$E$6) -> 4.5730286 | D37: =IF($E$6=0,0,D36*60/$E$6) -> 5.4612514 | E37: =IF($E$6=0,0,E36*60/$E$6) -> 5.9449371 | F37: =IF($E$6=0,0,F36*60/$E$6) -> 6.8859257 | G37: =IF($E$6=0,0,G36*60/$E$6) -> 7.5982629 | H37: =IF($E$6=0,0,H36*60/$E$6) -> 7.3872 | I37: =IF($E$6=0,0,I36*60/$E$6) -> 9.0229371 | J37: =IF($E$6=0,0,J36*60/$E$6) -> 9.3747086 | ... AL37: =IF($E$6=0,0,AL36*60/$E$6) -> 29.680714
A38: gross revenue | C38: =C37*$H$6 -> 930.9924 | D38: =D37*$H$6 -> 1111.8198 | E38: =E37*$H$6 -> 1210.2901 | F38: =F37*$H$6 -> 1401.8597 | G38: =G37*$H$6 -> 1546.8797 | H38: =H37*$H$6 -> 1503.9108 | I38: =I37*$H$6 -> 1836.9196 | J38: =J37*$H$6 -> 1908.5344 | ... AL38: =AL37*$H$6 -> 6042.4987
A39: direct costs | C39: =C37*$K$6 -> 32.333344 | D39: =D37*$K$6 -> 38.613475 | E39: =E37*$K$6 -> 42.033348 | F39: =F37*$K$6 -> 48.686555 | G39: =G37*$K$6 -> 53.723095 | H39: =H37*$K$6 -> 52.230787 | I39: =I37*$K$6 -> 63.796176 | J39: =J37*$K$6 -> 66.283356 | ... AL39: =AL37*$K$6 -> 209.85584
A40: machine kWh | C40: =C37*$L$6/60*$M$6 -> 2.13408 | D40: =D37*$L$6/60*$M$6 -> 2.548584 | E40: =E37*$L$6/60*$M$6 -> 2.774304 | F40: =F37*$L$6/60*$M$6 -> 3.213432 | G40: =G37*$L$6/60*$M$6 -> 3.545856 | H40: =H37*$L$6/60*$M$6 -> 3.44736 | I40: =I37*$L$6/60*$M$6 -> 4.210704 | J40: =J37*$L$6/60*$M$6 -> 4.374864 | ... AL40: =AL37*$L$6/60*$M$6 -> 13.851
A41: HIFU lifting
A42: hours | C42: =C$27*$N$7 -> 1.7784 | D42: =D$27*$N$7 -> 2.12382 | E42: =E$27*$N$7 -> 2.31192 | F42: =F$27*$N$7 -> 2.67786 | G42: =G$27*$N$7 -> 2.95488 | H42: =H$27*$N$7 -> 2.8728 | I42: =I$27*$N$7 -> 3.50892 | J42: =J$27*$N$7 -> 3.64572 | ... AL42: =AL$27*$N$7 -> 11.5425
A43: sessions | C43: =IF($E$7=0,0,C42*60/$E$7) -> 2.13408 | D43: =IF($E$7=0,0,D42*60/$E$7) -> 2.548584 | E43: =IF($E$7=0,0,E42*60/$E$7) -> 2.774304 | F43: =IF($E$7=0,0,F42*60/$E$7) -> 3.213432 | G43: =IF($E$7=0,0,G42*60/$E$7) -> 3.545856 | H43: =IF($E$7=0,0,H42*60/$E$7) -> 3.44736 | I43: =IF($E$7=0,0,I42*60/$E$7) -> 4.210704 | J43: =IF($E$7=0,0,J42*60/$E$7) -> 4.374864 | ... AL43: =IF($E$7=0,0,AL42*60/$E$7) -> 13.851
A44: gross revenue | C44: =C43*$H$7 -> 803.89152 | D44: =D43*$H$7 -> 960.03199 | E44: =E43*$H$7 -> 1045.059 | F44: =F43*$H$7 -> 1210.4751 | G44: =G43*$H$7 -> 1335.6967 | H44: =H43*$H$7 -> 1298.594 | I44: =I43*$H$7 -> 1586.1398 | J44: =J43*$H$7 -> 1647.9776 | ... AL44: =AL43*$H$7 -> 5217.5652
A45: direct costs | C45: =C43*$K$7 -> 150.55565 | D45: =D43*$K$7 -> 179.79819 | E45: =E43*$K$7 -> 195.72235 | F45: =F43*$K$7 -> 226.70207 | G45: =G43*$K$7 -> 250.154 | H45: =H43*$K$7 -> 243.20528 | I45: =I43*$K$7 -> 297.05788 | J45: =J43*$K$7 -> 308.63908 | ... AL45: =AL43*$K$7 -> 977.16408
A46: machine kWh | C46: =C43*$L$7/60*$M$7 -> 0.53352 | D46: =D43*$L$7/60*$M$7 -> 0.637146 | E46: =E43*$L$7/60*$M$7 -> 0.693576 | F46: =F43*$L$7/60*$M$7 -> 0.803358 | G46: =G43*$L$7/60*$M$7 -> 0.886464 | H46: =H43*$L$7/60*$M$7 -> 0.86184 | I46: =I43*$L$7/60*$M$7 -> 1.052676 | J46: =J43*$L$7/60*$M$7 -> 1.093716 | ... AL46: =AL43*$L$7/60*$M$7 -> 3.46275
A47: RF tightening
A48: hours | C48: =C$27*$N$8 -> 1.7784 | D48: =D$27*$N$8 -> 2.12382 | E48: =E$27*$N$8 -> 2.31192 | F48: =F$27*$N$8 -> 2.67786 | G48: =G$27*$N$8 -> 2.95488 | H48: =H$27*$N$8 -> 2.8728 | I48: =I$27*$N$8 -> 3.50892 | J48: =J$27*$N$8 -> 3.64572 | ... AL48: =AL$27*$N$8 -> 11.5425
A49: sessions | C49: =IF($E$8=0,0,C48*60/$E$8) -> 1.7784 | D49: =IF($E$8=0,0,D48*60/$E$8) -> 2.12382 | E49: =IF($E$8=0,0,E48*60/$E$8) -> 2.31192 | F49: =IF($E$8=0,0,F48*60/$E$8) -> 2.67786 | G49: =IF($E$8=0,0,G48*60/$E$8) -> 2.95488 | H49: =IF($E$8=0,0,H48*60/$E$8) -> 2.8728 | I49: =IF($E$8=0,0,I48*60/$E$8) -> 3.50892 | J49: =IF($E$8=0,0,J48*60/$E$8) -> 3.64572 | ... AL49: =IF($E$8=0,0,AL48*60/$E$8) -> 11.5425
A50: gross revenue | C50: =C49*$H$8 -> 462.384 | D50: =D49*$H$8 -> 552.1932 | E50: =E49*$H$8 -> 601.0992 | F50: =F49*$H$8 -> 696.2436 | G50: =G49*$H$8 -> 768.2688 | H50: =H49*$H$8 -> 746.928 | I50: =I49*$H$8 -> 912.3192 | J50: =J49*$H$8 -> 947.8872 | ... AL50: =AL49*$H$8 -> 3001.05
A51: direct costs | C51: =C49*$K$8 -> 42.625284 | D51: =D49*$K$8 -> 50.904426 | E51: =E49*$K$8 -> 55.412869 | F51: =F49*$K$8 -> 64.183841 | G51: =G49*$K$8 -> 70.823549 | H51: =H49*$K$8 -> 68.856228 | I51: =I49*$K$8 -> 84.102964 | J51: =J49*$K$8 -> 87.381832 | ... AL51: =AL49*$K$8 -> 276.65449
A52: machine kWh | C52: =C49*$L$8/60*$M$8 -> 0.8892 | D52: =D49*$L$8/60*$M$8 -> 1.06191 | E52: =E49*$L$8/60*$M$8 -> 1.15596 | F52: =F49*$L$8/60*$M$8 -> 1.33893 | G52: =G49*$L$8/60*$M$8 -> 1.47744 | H52: =H49*$L$8/60*$M$8 -> 1.4364 | I52: =I49*$L$8/60*$M$8 -> 1.75446 | J52: =J49*$L$8/60*$M$8 -> 1.82286 | ... AL52: =AL49*$L$8/60*$M$8 -> 5.77125
A53: HydraFacial & facials
A54: hours | C54: =C$27*$N$9 -> 9.7812 | D54: =D$27*$N$9 -> 11.68101 | E54: =E$27*$N$9 -> 12.71556 | F54: =F$27*$N$9 -> 14.72823 | G54: =G$27*$N$9 -> 16.25184 | H54: =H$27*$N$9 -> 15.8004 | I54: =I$27*$N$9 -> 19.29906 | J54: =J$27*$N$9 -> 20.05146 | ... AL54: =AL$27*$N$9 -> 63.48375
A55: sessions | C55: =IF($E$9=0,0,C54*60/$E$9) -> 8.9042648 | D55: =IF($E$9=0,0,D54*60/$E$9) -> 10.633747 | E55: =IF($E$9=0,0,E54*60/$E$9) -> 11.575544 | F55: =IF($E$9=0,0,F54*60/$E$9) -> 13.407768 | G55: =IF($E$9=0,0,G54*60/$E$9) -> 14.794778 | H55: =IF($E$9=0,0,H54*60/$E$9) -> 14.383812 | I55: =IF($E$9=0,0,I54*60/$E$9) -> 17.568799 | J55: =IF($E$9=0,0,J54*60/$E$9) -> 18.253743 | ... AL55: =IF($E$9=0,0,AL54*60/$E$9) -> 57.792103
A56: gross revenue | C56: =C55*$H$9 -> 1404.4454 | D56: =D55*$H$9 -> 1677.2319 | E56: =E55*$H$9 -> 1825.779 | F56: =F55*$H$9 -> 2114.7707 | G56: =G55*$H$9 -> 2333.5401 | H56: =H55*$H$9 -> 2268.7195 | I56: =I55*$H$9 -> 2771.0788 | J56: =J55*$H$9 -> 2879.1131 | ... AL56: =AL55*$H$9 -> 9115.3909
A57: direct costs | C57: =C55*$K$9 -> 186.8488 | D57: =D55*$K$9 -> 223.14059 | E57: =E55*$K$9 -> 242.90344 | F57: =F55*$K$9 -> 281.35118 | G57: =G55*$K$9 -> 310.45647 | H57: =H55*$K$9 -> 301.83268 | I57: =I55*$K$9 -> 368.66706 | J57: =J55*$K$9 -> 383.04004 | ... AL57: =AL55*$K$9 -> 1212.7206
A58: machine kWh | C58: =C55*$L$9/60*$M$9 -> 1.95624 | D58: =D55*$L$9/60*$M$9 -> 2.336202 | E58: =E55*$L$9/60*$M$9 -> 2.543112 | F58: =F55*$L$9/60*$M$9 -> 2.945646 | G58: =G55*$L$9/60*$M$9 -> 3.250368 | H58: =H55*$L$9/60*$M$9 -> 3.16008 | I58: =I55*$L$9/60*$M$9 -> 3.859812 | J58: =J55*$L$9/60*$M$9 -> 4.010292 | ... AL58: =AL55*$L$9/60*$M$9 -> 12.69675
A59: Body contouring (Endosphere/vacuum)
A60: hours | C60: =C$27*$N$10 -> 7.1136 | D60: =D$27*$N$10 -> 8.49528 | E60: =E$27*$N$10 -> 9.24768 | F60: =F$27*$N$10 -> 10.71144 | G60: =G$27*$N$10 -> 11.81952 | H60: =H$27*$N$10 -> 11.4912 | I60: =I$27*$N$10 -> 14.03568 | J60: =J$27*$N$10 -> 14.58288 | ... AL60: =AL$27*$N$10 -> 46.17
A61: sessions | C61: =IF($E$10=0,0,C60*60/$E$10) -> 8.2992 | D61: =IF($E$10=0,0,D60*60/$E$10) -> 9.91116 | E61: =IF($E$10=0,0,E60*60/$E$10) -> 10.78896 | F61: =IF($E$10=0,0,F60*60/$E$10) -> 12.49668 | G61: =IF($E$10=0,0,G60*60/$E$10) -> 13.78944 | H61: =IF($E$10=0,0,H60*60/$E$10) -> 13.4064 | I61: =IF($E$10=0,0,I60*60/$E$10) -> 16.37496 | J61: =IF($E$10=0,0,J60*60/$E$10) -> 17.01336 | ... AL61: =IF($E$10=0,0,AL60*60/$E$10) -> 53.865
A62: gross revenue | C62: =C61*$H$10 -> 859.56 | D62: =D61*$H$10 -> 1026.513 | E62: =E61*$H$10 -> 1117.428 | F62: =F61*$H$10 -> 1294.299 | G62: =G61*$H$10 -> 1428.192 | H62: =H61*$H$10 -> 1388.52 | I62: =I61*$H$10 -> 1695.978 | J62: =J61*$H$10 -> 1762.098 | ... AL62: =AL61*$H$10 -> 5578.875
A63: direct costs | C63: =C61*$K$10 -> 40.916769 | D63: =D61*$K$10 -> 48.864064 | E63: =E61*$K$10 -> 53.191799 | F63: =F61*$K$10 -> 61.611211 | G63: =G61*$K$10 -> 67.984785 | H63: =H61*$K$10 -> 66.096318 | I63: =I61*$K$10 -> 80.731932 | J63: =J61*$K$10 -> 83.879375 | ... AL63: =AL61*$K$10 -> 265.56556
A64: machine kWh | C64: =C61*$L$10/60*$M$10 -> 2.48976 | D64: =D61*$L$10/60*$M$10 -> 2.973348 | E64: =E61*$L$10/60*$M$10 -> 3.236688 | F64: =F61*$L$10/60*$M$10 -> 3.749004 | G64: =G61*$L$10/60*$M$10 -> 4.136832 | H64: =H61*$L$10/60*$M$10 -> 4.02192 | I64: =I61*$L$10/60*$M$10 -> 4.912488 | J64: =J61*$L$10/60*$M$10 -> 5.104008 | ... AL64: =AL61*$L$10/60*$M$10 -> 16.1595
A65: Microneedling & BB Glow
A66: hours | C66: =C$27*$N$11 -> 2.6676 | D66: =D$27*$N$11 -> 3.18573 | E66: =E$27*$N$11 -> 3.46788 | F66: =F$27*$N$11 -> 4.01679 | G66: =G$27*$N$11 -> 4.43232 | H66: =H$27*$N$11 -> 4.3092 | I66: =I$27*$N$11 -> 5.26338 | J66: =J$27*$N$11 -> 5.46858 | ... AL66: =AL$27*$N$11 -> 17.31375
A67: sessions | C67: =IF($E$11=0,0,C66*60/$E$11) -> 2.6676 | D67: =IF($E$11=0,0,D66*60/$E$11) -> 3.18573 | E67: =IF($E$11=0,0,E66*60/$E$11) -> 3.46788 | F67: =IF($E$11=0,0,F66*60/$E$11) -> 4.01679 | G67: =IF($E$11=0,0,G66*60/$E$11) -> 4.43232 | H67: =IF($E$11=0,0,H66*60/$E$11) -> 4.3092 | I67: =IF($E$11=0,0,I66*60/$E$11) -> 5.26338 | J67: =IF($E$11=0,0,J66*60/$E$11) -> 5.46858 | ... AL67: =IF($E$11=0,0,AL66*60/$E$11) -> 17.31375
A68: gross revenue | C68: =C67*$H$11 -> 333.45 | D68: =D67*$H$11 -> 398.21625 | E68: =E67*$H$11 -> 433.485 | F68: =F67*$H$11 -> 502.09875 | G68: =G67*$H$11 -> 554.04 | H68: =H67*$H$11 -> 538.65 | I68: =I67*$H$11 -> 657.9225 | J68: =J67*$H$11 -> 683.5725 | ... AL68: =AL67*$H$11 -> 2164.2188
A69: direct costs | C69: =C67*$K$11 -> 69.273205 | D69: =D67*$K$11 -> 82.728193 | E69: =E67*$K$11 -> 90.055167 | F69: =F67*$K$11 -> 104.30946 | G69: =G67*$K$11 -> 115.10009 | H69: =H67*$K$11 -> 111.90287 | I69: =I67*$K$11 -> 136.68136 | J69: =J67*$K$11 -> 142.01007 | ... AL69: =AL67*$K$11 -> 449.60974
A70: machine kWh | C70: =C67*$L$11/60*$M$11 -> 0.053352 | D70: =D67*$L$11/60*$M$11 -> 0.0637146 | E70: =E67*$L$11/60*$M$11 -> 0.0693576 | F70: =F67*$L$11/60*$M$11 -> 0.0803358 | G70: =G67*$L$11/60*$M$11 -> 0.0886464 | H70: =H67*$L$11/60*$M$11 -> 0.086184 | I70: =I67*$L$11/60*$M$11 -> 0.1052676 | J70: =J67*$L$11/60*$M$11 -> 0.1093716 | ... AL70: =AL67*$L$11/60*$M$11 -> 0.346275
A71: Microdermabrasion
A72: hours | C72: =C$27*$N$12 -> 0.4446 | D72: =D$27*$N$12 -> 0.530955 | E72: =E$27*$N$12 -> 0.57798 | F72: =F$27*$N$12 -> 0.669465 | G72: =G$27*$N$12 -> 0.73872 | H72: =H$27*$N$12 -> 0.7182 | I72: =I$27*$N$12 -> 0.87723 | J72: =J$27*$N$12 -> 0.91143 | ... AL72: =AL$27*$N$12 -> 2.885625
A73: sessions | C73: =IF($E$12=0,0,C72*60/$E$12) -> 0.8892 | D73: =IF($E$12=0,0,D72*60/$E$12) -> 1.06191 | E73: =IF($E$12=0,0,E72*60/$E$12) -> 1.15596 | F73: =IF($E$12=0,0,F72*60/$E$12) -> 1.33893 | G73: =IF($E$12=0,0,G72*60/$E$12) -> 1.47744 | H73: =IF($E$12=0,0,H72*60/$E$12) -> 1.4364 | I73: =IF($E$12=0,0,I72*60/$E$12) -> 1.75446 | J73: =IF($E$12=0,0,J72*60/$E$12) -> 1.82286 | ... AL73: =IF($E$12=0,0,AL72*60/$E$12) -> 5.77125
A74: gross revenue | C74: =C73*$H$12 -> 71.136 | D74: =D73*$H$12 -> 84.9528 | E74: =E73*$H$12 -> 92.4768 | F74: =F73*$H$12 -> 107.1144 | G74: =G73*$H$12 -> 118.1952 | H74: =H73*$H$12 -> 114.912 | I74: =I73*$H$12 -> 140.3568 | J74: =J73*$H$12 -> 145.8288 | ... AL74: =AL73*$H$12 -> 461.7
A75: direct costs | C75: =C73*$K$12 -> 3.1977855 | D75: =D73*$K$12 -> 3.8188938 | E75: =E73*$K$12 -> 4.1571212 | F75: =F73*$K$12 -> 4.815127 | G75: =G73*$K$12 -> 5.3132436 | H75: =H73*$K$12 -> 5.1656535 | I75: =I73*$K$12 -> 6.3094768 | J75: =J73*$K$12 -> 6.5554603 | ... AL75: =AL73*$K$12 -> 20.754858
A76: machine kWh | C76: =C73*$L$12/60*$M$12 -> 0.11115 | D76: =D73*$L$12/60*$M$12 -> 0.13273875 | E76: =E73*$L$12/60*$M$12 -> 0.144495 | F76: =F73*$L$12/60*$M$12 -> 0.16736625 | G76: =G73*$L$12/60*$M$12 -> 0.18468 | H76: =H73*$L$12/60*$M$12 -> 0.17955 | I76: =I73*$L$12/60*$M$12 -> 0.2193075 | J76: =J73*$L$12/60*$M$12 -> 0.2278575 | ... AL76: =AL73*$L$12/60*$M$12 -> 0.72140625
A77: Microcurrent & LED
A78: hours | C78: =C$27*$N$13 -> 3.5568 | D78: =D$27*$N$13 -> 4.24764 | E78: =E$27*$N$13 -> 4.62384 | F78: =F$27*$N$13 -> 5.35572 | G78: =G$27*$N$13 -> 5.90976 | H78: =H$27*$N$13 -> 5.7456 | I78: =I$27*$N$13 -> 7.01784 | J78: =J$27*$N$13 -> 7.29144 | ... AL78: =AL$27*$N$13 -> 23.085
A79: sessions | C79: =IF($E$13=0,0,C78*60/$E$13) -> 4.3776 | D79: =IF($E$13=0,0,D78*60/$E$13) -> 5.2278646 | E79: =IF($E$13=0,0,E78*60/$E$13) -> 5.69088 | F79: =IF($E$13=0,0,F78*60/$E$13) -> 6.5916554 | G79: =IF($E$13=0,0,G78*60/$E$13) -> 7.2735508 | H79: =IF($E$13=0,0,H78*60/$E$13) -> 7.0715077 | I79: =IF($E$13=0,0,I78*60/$E$13) -> 8.6373415 | J79: =IF($E$13=0,0,J78*60/$E$13) -> 8.97408 | ... AL79: =IF($E$13=0,0,AL78*60/$E$13) -> 28.412308
A80: gross revenue | C80: =C79*$H$13 -> 459.648 | D80: =D79*$H$13 -> 548.92578 | E80: =E79*$H$13 -> 597.5424 | F80: =F79*$H$13 -> 692.12382 | G80: =G79*$H$13 -> 763.72283 | H80: =H79*$H$13 -> 742.50831 | I80: =I79*$H$13 -> 906.92086 | J80: =J79*$H$13 -> 942.2784 | ... AL80: =AL79*$H$13 -> 2983.2923
A81: direct costs | C81: =C79*$K$13 -> 25.404034 | D81: =D79*$K$13 -> 30.338279 | E81: =E79*$K$13 -> 33.025244 | F81: =F79*$K$13 -> 38.252612 | G81: =G79*$K$13 -> 42.209779 | H81: =H79*$K$13 -> 41.037285 | I81: =I79*$K$13 -> 50.124112 | J81: =J79*$K$13 -> 52.078269 | ... AL81: =AL79*$K$13 -> 164.88195
A82: machine kWh | C82: =C79*$L$13/60*$M$13 -> 0.35568 | D82: =D79*$L$13/60*$M$13 -> 0.424764 | E82: =E79*$L$13/60*$M$13 -> 0.462384 | F82: =F79*$L$13/60*$M$13 -> 0.535572 | G82: =G79*$L$13/60*$M$13 -> 0.590976 | H82: =H79*$L$13/60*$M$13 -> 0.57456 | I82: =I79*$L$13/60*$M$13 -> 0.701784 | J82: =J79*$L$13/60*$M$13 -> 0.729144 | ... AL82: =AL79*$L$13/60*$M$13 -> 2.3085
A83: Injectables
A84: hours | C84: =C$27*$N$14 -> 2.6676 | D84: =D$27*$N$14 -> 3.18573 | E84: =E$27*$N$14 -> 3.46788 | F84: =F$27*$N$14 -> 4.01679 | G84: =G$27*$N$14 -> 4.43232 | H84: =H$27*$N$14 -> 4.3092 | I84: =I$27*$N$14 -> 5.26338 | J84: =J$27*$N$14 -> 5.46858 | ... AL84: =AL$27*$N$14 -> 17.31375
A85: sessions | C85: =IF($E$14=0,0,C84*60/$E$14) -> 3.9787932 | D85: =IF($E$14=0,0,D84*60/$E$14) -> 4.7515973 | E85: =IF($E$14=0,0,E84*60/$E$14) -> 5.1724312 | F85: =IF($E$14=0,0,F84*60/$E$14) -> 5.9911444 | G85: =IF($E$14=0,0,G84*60/$E$14) -> 6.610918 | H85: =IF($E$14=0,0,H84*60/$E$14) -> 6.4272814 | I85: =IF($E$14=0,0,I84*60/$E$14) -> 7.8504651 | J85: =IF($E$14=0,0,J84*60/$E$14) -> 8.1565261 | ... AL85: =IF($E$14=0,0,AL84*60/$E$14) -> 25.823898
A86: gross revenue | C86: =C85*$H$14 -> 813.84407 | D86: =D85*$H$14 -> 971.91763 | E86: =E85*$H$14 -> 1057.9973 | F86: =F85*$H$14 -> 1225.4614 | G86: =G85*$H$14 -> 1352.2332 | H86: =H85*$H$14 -> 1314.6712 | I86: =I85*$H$14 -> 1605.7769 | J86: =J85*$H$14 -> 1668.3803 | ... AL86: =AL85*$H$14 -> 5282.161
A87: direct costs | C87: =C85*$K$14 -> 219.7379 | D87: =D85*$K$14 -> 262.41776 | E87: =E85*$K$14 -> 285.65927 | F87: =F85*$K$14 -> 330.87457 | G87: =G85*$K$14 -> 365.10297 | H87: =H85*$K$14 -> 354.96122 | I87: =I85*$K$14 -> 433.55978 | J87: =J85*$K$14 -> 450.46269 | ... AL87: =AL85*$K$14 -> 1426.1835
A88: machine kWh | C88: =C85*$L$14/60*$M$14 -> 0 | D88: =D85*$L$14/60*$M$14 -> 0 | E88: =E85*$L$14/60*$M$14 -> 0 | F88: =F85*$L$14/60*$M$14 -> 0 | G88: =G85*$L$14/60*$M$14 -> 0 | H88: =H85*$L$14/60*$M$14 -> 0 | I88: =I85*$L$14/60*$M$14 -> 0 | J88: =J85*$L$14/60*$M$14 -> 0 | ... AL88: =AL85*$L$14/60*$M$14 -> 0
A89: Peels, massage & manual
A90: hours | C90: =C$27*$N$15 -> 1.7784 | D90: =D$27*$N$15 -> 2.12382 | E90: =E$27*$N$15 -> 2.31192 | F90: =F$27*$N$15 -> 2.67786 | G90: =G$27*$N$15 -> 2.95488 | H90: =H$27*$N$15 -> 2.8728 | I90: =I$27*$N$15 -> 3.50892 | J90: =J$27*$N$15 -> 3.64572 | ... AL90: =AL$27*$N$15 -> 11.5425
A91: sessions | C91: =IF($E$15=0,0,C90*60/$E$15) -> 2.3071135 | D91: =IF($E$15=0,0,D90*60/$E$15) -> 2.7552259 | E91: =IF($E$15=0,0,E90*60/$E$15) -> 2.9992476 | F91: =IF($E$15=0,0,F90*60/$E$15) -> 3.4739805 | G91: =IF($E$15=0,0,G90*60/$E$15) -> 3.8333578 | H91: =IF($E$15=0,0,H90*60/$E$15) -> 3.7268757 | I91: =IF($E$15=0,0,I90*60/$E$15) -> 4.5521124 | J91: =IF($E$15=0,0,J90*60/$E$15) -> 4.7295827 | ... AL91: =IF($E$15=0,0,AL90*60/$E$15) -> 14.974054
A92: gross revenue | C92: =C91*$H$15 -> 181.68519 | D92: =D91*$H$15 -> 216.97404 | E92: =E91*$H$15 -> 236.19075 | F92: =F91*$H$15 -> 273.57597 | G92: =G91*$H$15 -> 301.87693 | H92: =H91*$H$15 -> 293.49146 | I92: =I91*$H$15 -> 358.47885 | J92: =J91*$H$15 -> 372.45464 | ... AL92: =AL91*$H$15 -> 1179.2068
A93: direct costs | C93: =C91*$K$15 -> 7.7865081 | D93: =D91*$K$15 -> 9.2988876 | E93: =E91*$K$15 -> 10.122461 | F93: =F91*$K$15 -> 11.724684 | G93: =G91*$K$15 -> 12.937583 | H93: =H91*$K$15 -> 12.578205 | I93: =I91*$K$15 -> 15.363379 | J93: =J91*$K$15 -> 15.962342 | ... AL93: =AL91*$K$15 -> 50.537432
A94: machine kWh | C94: =C91*$L$15/60*$M$15 -> 0 | D94: =D91*$L$15/60*$M$15 -> 0 | E94: =E91*$L$15/60*$M$15 -> 0 | F94: =F91*$L$15/60*$M$15 -> 0 | G94: =G91*$L$15/60*$M$15 -> 0 | H94: =H91*$L$15/60*$M$15 -> 0 | I94: =I91*$L$15/60*$M$15 -> 0 | J94: =J91*$L$15/60*$M$15 -> 0 | ... AL94: =AL91*$L$15/60*$M$15 -> 0
A95: CO2 laser (intimate) — coming soon
A96: hours | C96: =C$27*$N$16 -> 0 | D96: =D$27*$N$16 -> 0 | E96: =E$27*$N$16 -> 0 | F96: =F$27*$N$16 -> 0 | G96: =G$27*$N$16 -> 0 | H96: =H$27*$N$16 -> 0 | I96: =I$27*$N$16 -> 0 | J96: =J$27*$N$16 -> 0 | ... AL96: =AL$27*$N$16 -> 0
A97: sessions | C97: =IF($E$16=0,0,C96*60/$E$16) -> 0 | D97: =IF($E$16=0,0,D96*60/$E$16) -> 0 | E97: =IF($E$16=0,0,E96*60/$E$16) -> 0 | F97: =IF($E$16=0,0,F96*60/$E$16) -> 0 | G97: =IF($E$16=0,0,G96*60/$E$16) -> 0 | H97: =IF($E$16=0,0,H96*60/$E$16) -> 0 | I97: =IF($E$16=0,0,I96*60/$E$16) -> 0 | J97: =IF($E$16=0,0,J96*60/$E$16) -> 0 | ... AL97: =IF($E$16=0,0,AL96*60/$E$16) -> 0
A98: gross revenue | C98: =C97*$H$16 -> 0 | D98: =D97*$H$16 -> 0 | E98: =E97*$H$16 -> 0 | F98: =F97*$H$16 -> 0 | G98: =G97*$H$16 -> 0 | H98: =H97*$H$16 -> 0 | I98: =I97*$H$16 -> 0 | J98: =J97*$H$16 -> 0 | ... AL98: =AL97*$H$16 -> 0
A99: direct costs | C99: =C97*$K$16 -> 0 | D99: =D97*$K$16 -> 0 | E99: =E97*$K$16 -> 0 | F99: =F97*$K$16 -> 0 | G99: =G97*$K$16 -> 0 | H99: =H97*$K$16 -> 0 | I99: =I97*$K$16 -> 0 | J99: =J97*$K$16 -> 0 | ... AL99: =AL97*$K$16 -> 0
A100: machine kWh | C100: =C97*$L$16/60*$M$16 -> 0 | D100: =D97*$L$16/60*$M$16 -> 0 | E100: =E97*$L$16/60*$M$16 -> 0 | F100: =F97*$L$16/60*$M$16 -> 0 | G100: =G97*$L$16/60*$M$16 -> 0 | H100: =H97*$L$16/60*$M$16 -> 0 | I100: =I97*$L$16/60*$M$16 -> 0 | J100: =J97*$L$16/60*$M$16 -> 0 | ... AL100: =AL97*$L$16/60*$M$16 -> 0
A101: Tattoo/pigment removal (pico) — not yet purchased
A102: hours | C102: =C$27*$N$17 -> 0 | D102: =D$27*$N$17 -> 0 | E102: =E$27*$N$17 -> 0 | F102: =F$27*$N$17 -> 0 | G102: =G$27*$N$17 -> 0 | H102: =H$27*$N$17 -> 0 | I102: =I$27*$N$17 -> 0 | J102: =J$27*$N$17 -> 0 | ... AL102: =AL$27*$N$17 -> 0
A103: sessions | C103: =IF($E$17=0,0,C102*60/$E$17) -> 0 | D103: =IF($E$17=0,0,D102*60/$E$17) -> 0 | E103: =IF($E$17=0,0,E102*60/$E$17) -> 0 | F103: =IF($E$17=0,0,F102*60/$E$17) -> 0 | G103: =IF($E$17=0,0,G102*60/$E$17) -> 0 | H103: =IF($E$17=0,0,H102*60/$E$17) -> 0 | I103: =IF($E$17=0,0,I102*60/$E$17) -> 0 | J103: =IF($E$17=0,0,J102*60/$E$17) -> 0 | ... AL103: =IF($E$17=0,0,AL102*60/$E$17) -> 0
A104: gross revenue | C104: =C103*$H$17 -> 0 | D104: =D103*$H$17 -> 0 | E104: =E103*$H$17 -> 0 | F104: =F103*$H$17 -> 0 | G104: =G103*$H$17 -> 0 | H104: =H103*$H$17 -> 0 | I104: =I103*$H$17 -> 0 | J104: =J103*$H$17 -> 0 | ... AL104: =AL103*$H$17 -> 0
...

Sheet Energy
A1: Energy — heating & cooling by season, base load, machine consumption
A2: Assumes 15 m2/room (ASSUMPTION — no floor area in codebase). Cooling: CIBSE ~40 kWh/m2/yr = 600 kWh/room/yr, weighted Jun 20% / Jul 30% / Aug 30% / May+Sep 15% / rest 5%. Heating: 85 kWh/m2/yr delivered (mid of 50–120) / COP 3 = 425 kWh electricity/room/yr, weighted Dec–Feb 55% / Nov+Mar 30% / Oct+Apr 15%. Annual total ~1,025 kWh/room. Split A/C sizing cross-check: 2.5–3.5 kW cooling unit at 0.5–1.4 kW input, 3–8 kWh/room/day in Jul–Aug — consistent.
A3: Sanity check from research: 9 rooms x ~1,025 kWh HVAC + 12 kWh/day x 365 base + ~1,500–2,500 kWh machines = ~15,000–16,500 kWh/yr = ~£4,100–£4,700/yr at 27p + £200 standing. Within CIBSE TM46 general-retail 165 kWh/m2/yr for a ~100–140 m2 unit.
A5: HVAC kWh per room per month (EDIT — winter = heating via A/C heat pump, summer = cooling)
B6: Jan | C6: Feb | D6: Mar | E6: Apr | F6: May | G6: Jun | H6: Jul | I6: Aug | J6: Sep | K6: Oct | L6: Nov | M6: Dec
A7: kWh/room | B7: 82 | C7: 80 | D7: 68 | E7: 36 | F7: 45 | G7: 120 | H7: 180 | I7: 180 | J7: 45 | K7: 36 | L7: 68 | M7: 82
A9: MONTHLY ENERGY MODEL
A10: Month | C10: =EDATE(Assumptions!$B$5,COLUMN()-3) -> 46266 | D10: =EDATE(Assumptions!$B$5,COLUMN()-3) -> 46296 | E10: =EDATE(Assumptions!$B$5,COLUMN()-3) -> 46327 | F10: =EDATE(Assumptions!$B$5,COLUMN()-3) -> 46357 | G10: =EDATE(Assumptions!$B$5,COLUMN()-3) -> 46388 | H10: =EDATE(Assumptions!$B$5,COLUMN()-3) -> 46419 | I10: =EDATE(Assumptions!$B$5,COLUMN()-3) -> 46447 | J10: =EDATE(Assumptions!$B$5,COLUMN()-3) -> 46478 | ... AL10: =EDATE(Assumptions!$B$5,COLUMN()-3) -> 47331
A11: Days in month | C11: =DAY(EOMONTH(C$10,0)) -> 30 | D11: =DAY(EOMONTH(D$10,0)) -> 31 | E11: =DAY(EOMONTH(E$10,0)) -> 30 | F11: =DAY(EOMONTH(F$10,0)) -> 31 | G11: =DAY(EOMONTH(G$10,0)) -> 31 | H11: =DAY(EOMONTH(H$10,0)) -> 28 | I11: =DAY(EOMONTH(I$10,0)) -> 31 | J11: =DAY(EOMONTH(J$10,0)) -> 30 | ... AL11: =DAY(EOMONTH(AL$10,0)) -> 31
A12: HVAC kWh (rooms × seasonal curve) | C12: =INDEX(Energy!$B$7:$M$7,MONTH(C$10))*Assumptions!$B$7 -> 405 | D12: =INDEX(Energy!$B$7:$M$7,MONTH(D$10))*Assumptions!$B$7 -> 324 | E12: =INDEX(Energy!$B$7:$M$7,MONTH(E$10))*Assumptions!$B$7 -> 612 | F12: =INDEX(Energy!$B$7:$M$7,MONTH(F$10))*Assumptions!$B$7 -> 738 | G12: =INDEX(Energy!$B$7:$M$7,MONTH(G$10))*Assumptions!$B$7 -> 738 | H12: =INDEX(Energy!$B$7:$M$7,MONTH(H$10))*Assumptions!$B$7 -> 720 | I12: =INDEX(Energy!$B$7:$M$7,MONTH(I$10))*Assumptions!$B$7 -> 612 | J12: =INDEX(Energy!$B$7:$M$7,MONTH(J$10))*Assumptions!$B$7 -> 324 | ... AL12: =INDEX(Energy!$B$7:$M$7,MONTH(AL$10))*Assumptions!$B$7 -> 1620
A13: Base load kWh | C13: =Assumptions!$B$25*C$11 -> 360 | D13: =Assumptions!$B$25*D$11 -> 372 | E13: =Assumptions!$B$25*E$11 -> 360 | F13: =Assumptions!$B$25*F$11 -> 372 | G13: =Assumptions!$B$25*G$11 -> 372 | H13: =Assumptions!$B$25*H$11 -> 336 | I13: =Assumptions!$B$25*I$11 -> 372 | J13: =Assumptions!$B$25*J$11 -> 360 | ... AL13: =Assumptions!$B$25*AL$11 -> 372
A14: Machine kWh (from Volumes) | C14: =Volumes!C$116 -> 52.538382 | D14: =Volumes!D$116 -> 62.742952 | E14: =Volumes!E$116 -> 68.299897 | F14: =Volumes!F$116 -> 79.110679 | G14: =Volumes!G$116 -> 87.294542 | H14: =Volumes!H$116 -> 84.869694 | I14: =Volumes!I$116 -> 103.66227 | J14: =Volumes!J$116 -> 107.70368 | ... AL14: =Volumes!AL$116 -> 340.99431
A15: Total kWh | C15: =C12+C13+C14 -> 817.53838 | D15: =D12+D13+D14 -> 758.74295 | E15: =E12+E13+E14 -> 1040.2999 | F15: =F12+F13+F14 -> 1189.1107 | G15: =G12+G13+G14 -> 1197.2945 | H15: =H12+H13+H14 -> 1140.8697 | I15: =I12+I13+I14 -> 1087.6623 | J15: =J12+J13+J14 -> 791.70368 | ... AL15: =AL12+AL13+AL14 -> 2332.9943
A16: Machine energy cost £ (direct — already inside Pricing/Volumes direct costs) | C16: =C14*Assumptions!$B$23/100 -> 14.185363 | D16: =D14*Assumptions!$B$23/100 -> 16.940597 | E16: =E14*Assumptions!$B$23/100 -> 18.440972 | F16: =F14*Assumptions!$B$23/100 -> 21.359883 | G16: =G14*Assumptions!$B$23/100 -> 23.569526 | H16: =H14*Assumptions!$B$23/100 -> 22.914817 | I16: =I14*Assumptions!$B$23/100 -> 27.988813 | J16: =J14*Assumptions!$B$23/100 -> 29.079994 | ... AL16: =AL14*Assumptions!$B$23/100 -> 92.068463
A17: Facility energy cost £ (HVAC + base + standing — to P&L overheads) | C17: =(C12+C13)*Assumptions!$B$23/100+C11*Assumptions!$B$24/100 -> 223.05 | D17: =(D12+D13)*Assumptions!$B$23/100+D11*Assumptions!$B$24/100 -> 204.97 | E17: =(E12+E13)*Assumptions!$B$23/100+E11*Assumptions!$B$24/100 -> 278.94 | F17: =(F12+F13)*Assumptions!$B$23/100+F11*Assumptions!$B$24/100 -> 316.75 | G17: =(G12+G13)*Assumptions!$B$23/100+G11*Assumptions!$B$24/100 -> 316.75 | H17: =(H12+H13)*Assumptions!$B$23/100+H11*Assumptions!$B$24/100 -> 300.52 | I17: =(I12+I13)*Assumptions!$B$23/100+I11*Assumptions!$B$24/100 -> 282.73 | J17: =(J12+J13)*Assumptions!$B$23/100+J11*Assumptions!$B$24/100 -> 201.18 | ... AL17: =(AL12+AL13)*Assumptions!$B$23/100+AL11*Assumptions!$B$24/100 -> 554.89

Sheet P&L
A1: P&L forecast — 36 months + annual summary
A2: Gross profit = net revenue − variable direct costs (consumables, machine energy & service, card fees). Salaried practitioners sit in overheads: they are capacity, not per-unit cost. Monthly corporation tax is a flat 19% accrual on positive months; the annual columns apply the real 19%/26.5%/25% bands. VAT switches on automatically when the rolling 12-month turnover tracker (bottom) crosses the threshold — prices are held, so VAT comes out of margin.
A4: Month | C4: =EDATE(Assumptions!$B$5,COLUMN()-3) -> 46266 | D4: =EDATE(Assumptions!$B$5,COLUMN()-3) -> 46296 | E4: =EDATE(Assumptions!$B$5,COLUMN()-3) -> 46327 | F4: =EDATE(Assumptions!$B$5,COLUMN()-3) -> 46357 | G4: =EDATE(Assumptions!$B$5,COLUMN()-3) -> 46388 | H4: =EDATE(Assumptions!$B$5,COLUMN()-3) -> 46419 | I4: =EDATE(Assumptions!$B$5,COLUMN()-3) -> 46447 | J4: =EDATE(Assumptions!$B$5,COLUMN()-3) -> 46478 | ... AL4: =EDATE(Assumptions!$B$5,COLUMN()-3) -> 47331 | AM4: Year 1 | AN4: Year 2 | AO4: Year 3
A5: Gross booking revenue | C5: =Volumes!C$114 -> 13316.939 | D5: =Volumes!D$114 -> 15903.498 | E5: =Volumes!E$114 -> 17312.02 | F5: =Volumes!F$114 -> 20052.237 | G5: =Volumes!G$114 -> 22126.606 | H5: =Volumes!H$114 -> 21511.978 | I5: =Volumes!I$114 -> 26275.345 | J5: =Volumes!J$114 -> 27299.725 | ... AL5: =Volumes!AL$114 -> 86432.055 | AM5: =SUM(C5:N5) -> 296737.25 | AN5: =SUM(O5:Z5) -> 590811.11 | AO5: =SUM(AA5:AL5) -> 881248.43
A6: cumulative gross revenue | C6: =C5 -> 13316.939 | D6: =C6+D5 -> 29220.437 | E6: =D6+E5 -> 46532.457 | F6: =E6+F5 -> 66584.694 | G6: =F6+G5 -> 88711.3 | H6: =G6+H5 -> 110223.28 | I6: =H6+I5 -> 136498.62 | J6: =I6+J5 -> 163798.35 | K6: =J6+K5 -> 194222.43 | ... AL6: =AK6+AL5 -> 1768796.8
A7: rolling 12-mo taxable turnover (incl. pre-model estimate) | C7: =C6+Assumptions!$B$44*(12-(COLUMN()-2))/12 -> 36233.606 | D7: =D6+Assumptions!$B$44*(12-(COLUMN()-2))/12 -> 50053.77 | E7: =E6+Assumptions!$B$44*(12-(COLUMN()-2))/12 -> 65282.457 | F7: =F6+Assumptions!$B$44*(12-(COLUMN()-2))/12 -> 83251.361 | G7: =G6+Assumptions!$B$44*(12-(COLUMN()-2))/12 -> 103294.63 | H7: =H6+Assumptions!$B$44*(12-(COLUMN()-2))/12 -> 122723.28 | I7: =I6+Assumptions!$B$44*(12-(COLUMN()-2))/12 -> 146915.29 | J7: =J6+Assumptions!$B$44*(12-(COLUMN()-2))/12 -> 172131.68 | ... M7: =M6+Assumptions!$B$44*(12-(COLUMN()-2))/12 -> 262173.39 | N7: =N6 -> 296737.25 | O7: =O6-C6 -> 320707.74 | P7: =P6-D6 -> 345600.17 | Q7: =Q6-E6 -> 369570.66 | R7: =R6-F6 -> 394463.09 | S7: =S6-G6 -> 419355.53 | T7: =T6-H6 -> 443300.41 | U7: =U6-I6 -> 468192.84 | V7: =V6-J6 -> 492163.33 | ... AL7: =AL6-Z6 -> 881248.43
A8: VAT-registered this month? (1/0) | C8: =IF(Assumptions!$B$45>0,IF(COLUMN()-2>=Assumptions!$B$45,1,0),0) -> 0 | D8: =IF(Assumptions!$B$45>0,IF(COLUMN()-2>=Assumptions!$B$45,1,0),IF(OR(C8=1,C7>=Assumptions!$B$43),1,0)) -> 0 | E8: =IF(Assumptions!$B$45>0,IF(COLUMN()-2>=Assumptions!$B$45,1,0),IF(OR(D8=1,D7>=Assumptions!$B$43),1,0)) -> 0 | F8: =IF(Assumptions!$B$45>0,IF(COLUMN()-2>=Assumptions!$B$45,1,0),IF(OR(E8=1,E7>=Assumptions!$B$43),1,0)) -> 0 | G8: =IF(Assumptions!$B$45>0,IF(COLUMN()-2>=Assumptions!$B$45,1,0),IF(OR(F8=1,F7>=Assumptions!$B$43),1,0)) -> 0 | H8: =IF(Assumptions!$B$45>0,IF(COLUMN()-2>=Assumptions!$B$45,1,0),IF(OR(G8=1,G7>=Assumptions!$B$43),1,0)) -> 1 | I8: =IF(Assumptions!$B$45>0,IF(COLUMN()-2>=Assumptions!$B$45,1,0),IF(OR(H8=1,H7>=Assumptions!$B$43),1,0)) -> 1 | J8: =IF(Assumptions!$B$45>0,IF(COLUMN()-2>=Assumptions!$B$45,1,0),IF(OR(I8=1,I7>=Assumptions!$B$43),1,0)) -> 1 | K8: =IF(Assumptions!$B$45>0,IF(COLUMN()-2>=Assumptions!$B$45,1,0),IF(OR(J8=1,J7>=Assumptions!$B$43),1,0)) -> 1 | ... AL8: =IF(Assumptions!$B$45>0,IF(COLUMN()-2>=Assumptions!$B$45,1,0),IF(OR(AK8=1,AK7>=Assumptions!$B$43),1,0)) -> 1
A9: Output VAT (prices held — VAT absorbed) | C9: =-C8*C5*Assumptions!$B$42/(1+Assumptions!$B$42) -> 0 | D9: =-D8*D5*Assumptions!$B$42/(1+Assumptions!$B$42) -> 0 | E9: =-E8*E5*Assumptions!$B$42/(1+Assumptions!$B$42) -> 0 | F9: =-F8*F5*Assumptions!$B$42/(1+Assumptions!$B$42) -> 0 | G9: =-G8*G5*Assumptions!$B$42/(1+Assumptions!$B$42) -> 0 | H9: =-H8*H5*Assumptions!$B$42/(1+Assumptions!$B$42) -> -3585.3297 | I9: =-I8*I5*Assumptions!$B$42/(1+Assumptions!$B$42) -> -4379.2241 | J9: =-J8*J5*Assumptions!$B$42/(1+Assumptions!$B$42) -> -4549.9541 | ... AL9: =-AL8*AL5*Assumptions!$B$42/(1+Assumptions!$B$42) -> -14405.342 | AM9: =SUM(C9:N9) -> -34670.992 | AN9: =SUM(O9:Z9) -> -98468.519 | AO9: =SUM(AA9:AL9) -> -146874.74
A10: Net revenue | C10: =C5+C9 -> 13316.939 | D10: =D5+D9 -> 15903.498 | E10: =E5+E9 -> 17312.02 | F10: =F5+F9 -> 20052.237 | G10: =G5+G9 -> 22126.606 | H10: =H5+H9 -> 17926.648 | I10: =I5+I9 -> 21896.121 | J10: =J5+J9 -> 22749.771 | ... AL10: =AL5+AL9 -> 72026.712 | AM10: =SUM(C10:N10) -> 262066.26 | AN10: =SUM(O10:Z10) -> 492342.59 | AO10: =SUM(AA10:AL10) -> 734373.69
A11: Consumables, machine energy & service | C11: =-Volumes!C$115 -> -995.21686 | D11: =-Volumes!D$115 -> -1188.5186 | E11: =-Volumes!E$115 -> -1293.7819 | F11: =-Volumes!F$115 -> -1498.5669 | G11: =-Volumes!G$115 -> -1653.5911 | H11: =-Volumes!H$115 -> -1607.658 | I11: =-Volumes!I$115 -> -1963.6394 | J11: =-Volumes!J$115 -> -2040.1946 | ... AL11: =-Volumes!AL$115 -> -6459.3402 | AM11: =SUM(C11:N11) -> -22176.111 | AN11: =SUM(O11:Z11) -> -44153.179 | AO11: =SUM(AA11:AL11) -> -65858.476
A12: Card processing fees | C12: =-C5*Assumptions!$B$34*Assumptions!$B$35 -> -215.06856 | D12: =-D5*Assumptions!$B$34*Assumptions!$B$35 -> -256.84149 | E12: =-E5*Assumptions!$B$34*Assumptions!$B$35 -> -279.58913 | F12: =-F5*Assumptions!$B$34*Assumptions!$B$35 -> -323.84362 | G12: =-G5*Assumptions!$B$34*Assumptions!$B$35 -> -357.34469 | H12: =-H5*Assumptions!$B$34*Assumptions!$B$35 -> -347.41845 | I12: =-I5*Assumptions!$B$34*Assumptions!$B$35 -> -424.34682 | J12: =-J5*Assumptions!$B$34*Assumptions!$B$35 -> -440.89055 | ... AL12: =-AL5*Assumptions!$B$34*Assumptions!$B$35 -> -1395.8777 | AM12: =SUM(C12:N12) -> -4792.3066 | AN12: =SUM(O12:Z12) -> -9541.5995 | AO12: =SUM(AA12:AL12) -> -14232.162
A13: GROSS PROFIT | C13: =C10+C11+C12 -> 12106.653 | D13: =D10+D11+D12 -> 14458.138 | E13: =E10+E11+E12 -> 15738.649 | F13: =F10+F11+F12 -> 18229.826 | G13: =G10+G11+G12 -> 20115.67 | H13: =H10+H11+H12 -> 15971.572 | I13: =I10+I11+I12 -> 19508.134 | J13: =J10+J11+J12 -> 20268.685 | ... AL13: =AL10+AL11+AL12 -> 64171.495 | AM13: =SUM(C13:N13) -> 235097.84 | AN13: =SUM(O13:Z13) -> 438647.82 | AO13: =SUM(AA13:AL13) -> 654283.05
A14: Gross margin % | C14: =IF(C10=0,0,C13/C10) -> 0.90911684 | D14: =IF(D10=0,0,D13/D10) -> 0.90911684 | E14: =IF(E10=0,0,E13/E10) -> 0.90911684 | F14: =IF(F10=0,0,F13/F10) -> 0.90911684 | G14: =IF(G10=0,0,G13/G10) -> 0.90911684 | H14: =IF(H10=0,0,H13/H10) -> 0.89094021 | I14: =IF(I10=0,0,I13/I10) -> 0.89094021 | J14: =IF(J10=0,0,J13/J10) -> 0.89094021 | ... AL14: =IF(AL10=0,0,AL13/AL10) -> 0.89094021 | AM14: =IF(SUM(C10:N10)=0,0,SUM(C13:N13)/SUM(C10:N10)) -> 0.89709313 | AN14: =IF(SUM(O10:Z10)=0,0,SUM(O13:Z13)/SUM(O10:Z10)) -> 0.89094021 | AO14: =IF(SUM(AA10:AL10)=0,0,SUM(AA13:AL13)/SUM(AA10:AL10)) -> 0.89094021
A15: Staff (practitioners, reception, owner) | C15: =-(Assumptions!$B$16*Assumptions!$B$12+Assumptions!$B$17*Assumptions!$B$13+Assumptions!$B$14)*Assumptions!$B$15/12 -> -15176.667 | D15: =-(Assumptions!$B$16*Assumptions!$B$12+Assumptions!$B$17*Assumptions!$B$13+Assumptions!$B$14)*Assumptions!$B$15/12 -> -15176.667 | E15: =-(Assumptions!$B$16*Assumptions!$B$12+Assumptions!$B$17*Assumptions!$B$13+Assumptions!$B$14)*Assumptions!$B$15/12 -> -15176.667 | F15: =-(Assumptions!$B$16*Assumptions!$B$12+Assumptions!$B$17*Assumptions!$B$13+Assumptions!$B$14)*Assumptions!$B$15/12 -> -15176.667 | G15: =-(Assumptions!$B$16*Assumptions!$B$12+Assumptions!$B$17*Assumptions!$B$13+Assumptions!$B$14)*Assumptions!$B$15/12 -> -15176.667 | H15: =-(Assumptions!$B$16*Assumptions!$B$12+Assumptions!$B$17*Assumptions!$B$13+Assumptions!$B$14)*Assumptions!$B$15/12 -> -15176.667 | I15: =-(Assumptions!$B$16*Assumptions!$B$12+Assumptions!$B$17*Assumptions!$B$13+Assumptions!$B$14)*Assumptions!$B$15/12 -> -15176.667 | J15: =-(Assumptions!$B$16*Assumptions!$B$12+Assumptions!$B$17*Assumptions!$B$13+Assumptions!$B$14)*Assumptions!$B$15/12 -> -15176.667 | ... N15: =-(Assumptions!$B$16*Assumptions!$B$12+Assumptions!$B$17*Assumptions!$B$13+Assumptions!$B$14)*Assumptions!$B$15/12 -> -15176.667 | O15: =-(Assumptions!$C$16*Assumptions!$B$12+Assumptions!$C$17*Assumptions!$B$13+Assumptions!$B$14)*Assumptions!$B$15/12 -> -19140 | P15: =-(Assumptions!$C$16*Assumptions!$B$12+Assumptions!$C$17*Assumptions!$B$13+Assumptions!$B$14)*Assumptions!$B$15/12 -> -19140 | Q15: =-(Assumptions!$C$16*Assumptions!$B$12+Assumptions!$C$17*Assumptions!$B$13+Assumptions!$B$14)*Assumptions!$B$15/12 -> -19140 | R15: =-(Assumptions!$C$16*Assumptions!$B$12+Assumptions!$C$17*Assumptions!$B$13+Assumptions!$B$14)*Assumptions!$B$15/12 -> -19140 | S15: =-(Assumptions!$C$16*Assumptions!$B$12+Assumptions!$C$17*Assumptions!$B$13+Assumptions!$B$14)*Assumptions!$B$15/12 -> -19140 | T15: =-(Assumptions!$C$16*Assumptions!$B$12+Assumptions!$C$17*Assumptions!$B$13+Assumptions!$B$14)*Assumptions!$B$15/12 -> -19140 | U15: =-(Assumptions!$C$16*Assumptions!$B$12+Assumptions!$C$17*Assumptions!$B$13+Assumptions!$B$14)*Assumptions!$B$15/12 -> -19140 | V15: =-(Assumptions!$C$16*Assumptions!$B$12+Assumptions!$C$17*Assumptions!$B$13+Assumptions!$B$14)*Assumptions!$B$15/12 -> -19140 | ... Z15: =-(Assumptions!$C$16*Assumptions!$B$12+Assumptions!$C$17*Assumptions!$B$13+Assumptions!$B$14)*Assumptions!$B$15/12 -> -19140 | AA15: =-(Assumptions!$E$16*Assumptions!$B$12+Assumptions!$E$17*Assumptions!$B$13+Assumptions!$B$14)*Assumptions!$B$15/12 -> -29676.667 | AB15: =-(Assumptions!$E$16*Assumptions!$B$12+Assumptions!$E$17*Assumptions!$B$13+Assumptions!$B$14)*Assumptions!$B$15/12 -> -29676.667 | AC15: =-(Assumptions!$E$16*Assumptions!$B$12+Assumptions!$E$17*Assumptions!$B$13+Assumptions!$B$14)*Assumptions!$B$15/12 -> -29676.667 | AD15: =-(Assumptions!$E$16*Assumptions!$B$12+Assumptions!$E$17*Assumptions!$B$13+Assumptions!$B$14)*Assumptions!$B$15/12 -> -29676.667 | AE15: =-(Assumptions!$E$16*Assumptions!$B$12+Assumptions!$E$17*Assumptions!$B$13+Assumptions!$B$14)*Assumptions!$B$15/12 -> -29676.667 | AF15: =-(Assumptions!$E$16*Assumptions!$B$12+Assumptions!$E$17*Assumptions!$B$13+Assumptions!$B$14)*Assumptions!$B$15/12 -> -29676.667 | AG15: =-(Assumptions!$E$16*Assumptions!$B$12+Assumptions!$E$17*Assumptions!$B$13+Assumptions!$B$14)*Assumptions!$B$15/12 -> -29676.667 | AH15: =-(Assumptions!$E$16*Assumptions!$B$12+Assumptions!$E$17*Assumptions!$B$13+Assumptions!$B$14)*Assumptions!$B$15/12 -> -29676.667 | ... AL15: =-(Assumptions!$E$16*Assumptions!$B$12+Assumptions!$E$17*Assumptions!$B$13+Assumptions!$B$14)*Assumptions!$B$15/12 -> -29676.667 | AM15: =SUM(C15:N15) -> -182120 | AN15: =SUM(O15:Z15) -> -229680 | AO15: =SUM(AA15:AL15) -> -356120
A16: Rent | C16: =-Assumptions!$B$28/12 -> -5333.3333 | D16: =-Assumptions!$B$28/12 -> -5333.3333 | E16: =-Assumptions!$B$28/12 -> -5333.3333 | F16: =-Assumptions!$B$28/12 -> -5333.3333 | G16: =-Assumptions!$B$28/12 -> -5333.3333 | H16: =-Assumptions!$B$28/12 -> -5333.3333 | I16: =-Assumptions!$B$28/12 -> -5333.3333 | J16: =-Assumptions!$B$28/12 -> -5333.3333 | ... AL16: =-Assumptions!$B$28/12 -> -5333.3333 | AM16: =SUM(C16:N16) -> -64000 | AN16: =SUM(O16:Z16) -> -64000 | AO16: =SUM(AA16:AL16) -> -64000
A17: Business rates | C17: =-Assumptions!$B$29/12 -> -958.33333 | D17: =-Assumptions!$B$29/12 -> -958.33333 | E17: =-Assumptions!$B$29/12 -> -958.33333 | F17: =-Assumptions!$B$29/12 -> -958.33333 | G17: =-Assumptions!$B$29/12 -> -958.33333 | H17: =-Assumptions!$B$29/12 -> -958.33333 | I17: =-Assumptions!$B$29/12 -> -958.33333 | J17: =-Assumptions!$B$29/12 -> -958.33333 | ... AL17: =-Assumptions!$B$29/12 -> -958.33333 | AM17: =SUM(C17:N17) -> -11500 | AN17: =SUM(O17:Z17) -> -11500 | AO17: =SUM(AA17:AL17) -> -11500
A18: Service charge | C18: =-Assumptions!$B$30/12 -> 0 | D18: =-Assumptions!$B$30/12 -> 0 | E18: =-Assumptions!$B$30/12 -> 0 | F18: =-Assumptions!$B$30/12 -> 0 | G18: =-Assumptions!$B$30/12 -> 0 | H18: =-Assumptions!$B$30/12 -> 0 | I18: =-Assumptions!$B$30/12 -> 0 | J18: =-Assumptions!$B$30/12 -> 0 | ... AL18: =-Assumptions!$B$30/12 -> 0 | AM18: =SUM(C18:N18) -> 0 | AN18: =SUM(O18:Z18) -> 0 | AO18: =SUM(AA18:AL18) -> 0
A19: Facility energy (HVAC, base load, standing) | C19: =-Energy!C$17 -> -223.05 | D19: =-Energy!D$17 -> -204.97 | E19: =-Energy!E$17 -> -278.94 | F19: =-Energy!F$17 -> -316.75 | G19: =-Energy!G$17 -> -316.75 | H19: =-Energy!H$17 -> -300.52 | I19: =-Energy!I$17 -> -282.73 | J19: =-Energy!J$17 -> -201.18 | ... AL19: =-Energy!AL$17 -> -554.89 | AM19: =SUM(C19:N19) -> -3866.81 | AN19: =SUM(O19:Z19) -> -3870.6 | AO19: =SUM(AA19:AL19) -> -3866.81
A20: Marketing | C20: =-MAX(Assumptions!$B$40,Assumptions!$B$39*C10) -> -1598.0327 | D20: =-MAX(Assumptions!$B$40,Assumptions!$B$39*D10) -> -1908.4198 | E20: =-MAX(Assumptions!$B$40,Assumptions!$B$39*E10) -> -2077.4425 | F20: =-MAX(Assumptions!$B$40,Assumptions!$B$39*F10) -> -2406.2684 | G20: =-MAX(Assumptions!$B$40,Assumptions!$B$39*G10) -> -2655.1927 | H20: =-MAX(Assumptions!$B$40,Assumptions!$B$39*H10) -> -2151.1978 | I20: =-MAX(Assumptions!$B$40,Assumptions!$B$39*I10) -> -2627.5345 | J20: =-MAX(Assumptions!$B$40,Assumptions!$B$39*J10) -> -2729.9725 | ... N20: =-MAX(Assumptions!$B$40,Assumptions!$B$39*N10) -> -3664.7191 | O20: =-MAX(Assumptions!$B$40,Assumptions!$C$39*O10) -> -3107.2857 | P20: =-MAX(Assumptions!$B$40,Assumptions!$C$39*P10) -> -3399.6608 | Q20: =-MAX(Assumptions!$B$40,Assumptions!$C$39*Q10) -> -3440.2092 | R20: =-MAX(Assumptions!$B$40,Assumptions!$C$39*R10) -> -3745.389 | S20: =-MAX(Assumptions!$B$40,Assumptions!$C$39*S10) -> -3918.2532 | T20: =-MAX(Assumptions!$B$40,Assumptions!$C$39*T10) -> -3788.0715 | U20: =-MAX(Assumptions!$B$40,Assumptions!$C$39*U10) -> -4263.9814 | V20: =-MAX(Assumptions!$B$40,Assumptions!$C$39*V10) -> -4272.5179 | ... Z20: =-MAX(Assumptions!$B$40,Assumptions!$C$39*Z10) -> -5128.3019 | AA20: =-MAX(Assumptions!$B$40,Assumptions!$E$39*AA10) -> -4083.8612 | AB20: =-MAX(Assumptions!$B$40,Assumptions!$E$39*AB10) -> -4379.2241 | AC20: =-MAX(Assumptions!$B$40,Assumptions!$E$39*AC10) -> -4350.2 | AD20: =-MAX(Assumptions!$B$40,Assumptions!$E$39*AD10) -> -4655.8067 | AE20: =-MAX(Assumptions!$B$40,Assumptions!$E$39*AE10) -> -4794.098 | AF20: =-MAX(Assumptions!$B$40,Assumptions!$E$39*AF10) -> -4384.346 | AG20: =-MAX(Assumptions!$B$40,Assumptions!$E$39*AG10) -> -5070.6806 | AH20: =-MAX(Assumptions!$B$40,Assumptions!$E$39*AH10) -> -5016.047 | ... AL20: =-MAX(Assumptions!$B$40,Assumptions!$E$39*AL10) -> -5762.137 | AM20: =SUM(C20:N20) -> -31447.951 | AN20: =SUM(O20:Z20) -> -49234.259 | AO20: =SUM(AA20:AL20) -> -58749.895
A21: Insurance | C21: =-Assumptions!$B$32/12 -> -125 | D21: =-Assumptions!$B$32/12 -> -125 | E21: =-Assumptions!$B$32/12 -> -125 | F21: =-Assumptions!$B$32/12 -> -125 | G21: =-Assumptions!$B$32/12 -> -125 | H21: =-Assumptions!$B$32/12 -> -125 | I21: =-Assumptions!$B$32/12 -> -125 | J21: =-Assumptions!$B$32/12 -> -125 | ... AL21: =-Assumptions!$B$32/12 -> -125 | AM21: =SUM(C21:N21) -> -1500 | AN21: =SUM(O21:Z21) -> -1500 | AO21: =SUM(AA21:AL21) -> -1500
A22: Platform hosting & infra | C22: =-Assumptions!$B$33 -> -50 | D22: =-Assumptions!$B$33 -> -50 | E22: =-Assumptions!$B$33 -> -50 | F22: =-Assumptions!$B$33 -> -50 | G22: =-Assumptions!$B$33 -> -50 | H22: =-Assumptions!$B$33 -> -50 | I22: =-Assumptions!$B$33 -> -50 | J22: =-Assumptions!$B$33 -> -50 | ... AL22: =-Assumptions!$B$33 -> -50 | AM22: =SUM(C22:N22) -> -600 | AN22: =SUM(O22:Z22) -> -600 | AO22: =SUM(AA22:AL22) -> -600
A23: Cleaning & sundries | C23: =-Assumptions!$B$36 -> -400 | D23: =-Assumptions!$B$36 -> -400 | E23: =-Assumptions!$B$36 -> -400 | F23: =-Assumptions!$B$36 -> -400 | G23: =-Assumptions!$B$36 -> -400 | H23: =-Assumptions!$B$36 -> -400 | I23: =-Assumptions!$B$36 -> -400 | J23: =-Assumptions!$B$36 -> -400 | ... AL23: =-Assumptions!$B$36 -> -400 | AM23: =SUM(C23:N23) -> -4800 | AN23: =SUM(O23:Z23) -> -4800 | AO23: =SUM(AA23:AL23) -> -4800
A24: Other fixed | C24: =-Assumptions!$B$37 -> -200 | D24: =-Assumptions!$B$37 -> -200 | E24: =-Assumptions!$B$37 -> -200 | F24: =-Assumptions!$B$37 -> -200 | G24: =-Assumptions!$B$37 -> -200 | H24: =-Assumptions!$B$37 -> -200 | I24: =-Assumptions!$B$37 -> -200 | J24: =-Assumptions!$B$37 -> -200 | ... AL24: =-Assumptions!$B$37 -> -200 | AM24: =SUM(C24:N24) -> -2400 | AN24: =SUM(O24:Z24) -> -2400 | AO24: =SUM(AA24:AL24) -> -2400
A25: EBITDA | C25: =C13+C15+C16+C17+C18+C19+C20+C21+C22+C23+C24 -> -11957.763 | D25: =D13+D15+D16+D17+D18+D19+D20+D21+D22+D23+D24 -> -9898.5851 | E25: =E13+E15+E16+E17+E18+E19+E20+E21+E22+E23+E24 -> -8861.0664 | F25: =F13+F15+F16+F17+F18+F19+F20+F21+F22+F23+F24 -> -6736.5255 | G25: =G13+G15+G16+G17+G18+G19+G20+G21+G22+G23+G24 -> -5099.6058 | H25: =H13+H15+H16+H17+H18+H19+H20+H21+H22+H23+H24 -> -8723.4792 | I25: =I13+I15+I16+I17+I18+I19+I20+I21+I22+I23+I24 -> -5645.4635 | J25: =J13+J15+J16+J17+J18+J19+J20+J21+J22+J23+J24 -> -4905.8004 | ... AL25: =AL13+AL15+AL16+AL17+AL18+AL19+AL20+AL21+AL22+AL23+AL24 -> 21111.134 | AM25: =SUM(C25:N25) -> -67136.92 | AN25: =SUM(O25:Z25) -> 71062.957 | AO25: =SUM(AA25:AL25) -> 150746.35
A26: EBITDA margin % | C26: =IF(C10=0,0,C25/C10) -> -0.89793628 | D26: =IF(D10=0,0,D25/D10) -> -0.62241559 | E26: =IF(E10=0,0,E25/E10) -> -0.51184472 | F26: =IF(F10=0,0,F25/F10) -> -0.33594883 | G26: =IF(G10=0,0,G25/G10) -> -0.23047393 | H26: =IF(H10=0,0,H25/H10) -> -0.48662075 | I26: =IF(I10=0,0,I25/I10) -> -0.25782939 | J26: =IF(J10=0,0,J25/J10) -> -0.21564175 | ... AL26: =IF(AL10=0,0,AL25/AL10) -> 0.29310146 | AM26: =IF(SUM(C10:N10)=0,0,SUM(C25:N25)/SUM(C10:N10)) -> -0.256183 | AN26: =IF(SUM(O10:Z10)=0,0,SUM(O25:Z25)/SUM(O10:Z10)) -> 0.1443364 | AO26: =IF(SUM(AA10:AL10)=0,0,SUM(AA25:AL25)/SUM(AA10:AL10)) -> 0.20527199
A27: Depreciation (machinery) | C27: =-Machinery!B$49 -> -3048.9418 | D27: =-Machinery!C$49 -> -3048.9418 | E27: =-Machinery!D$49 -> -3048.9418 | F27: =-Machinery!E$49 -> -3048.9418 | G27: =-Machinery!F$49 -> -3048.9418 | H27: =-Machinery!G$49 -> -3048.9418 | I27: =-Machinery!H$49 -> -3048.9418 | J27: =-Machinery!I$49 -> -3048.9418 | ... AL27: =-Machinery!AK$49 -> -3048.9418 | AM27: =SUM(C27:N27) -> -36587.302 | AN27: =SUM(O27:Z27) -> -36587.302 | AO27: =SUM(AA27:AL27) -> -36587.302
A28: Amortisation (enhancements/fit-out) | C28: =-Machinery!B$50 -> 0 | D28: =-Machinery!C$50 -> 0 | E28: =-Machinery!D$50 -> 0 | F28: =-Machinery!E$50 -> 0 | G28: =-Machinery!F$50 -> 0 | H28: =-Machinery!G$50 -> -133.33333 | I28: =-Machinery!H$50 -> -133.33333 | J28: =-Machinery!I$50 -> -133.33333 | ... AL28: =-Machinery!AK$50 -> -133.33333 | AM28: =SUM(C28:N28) -> -933.33333 | AN28: =SUM(O28:Z28) -> -1600 | AO28: =SUM(AA28:AL28) -> -1600
A29: EBIT | C29: =C25+C27+C28 -> -15006.704 | D29: =D25+D27+D28 -> -12947.527 | E29: =E25+E27+E28 -> -11910.008 | F29: =F25+F27+F28 -> -9785.4673 | G29: =G25+G27+G28 -> -8148.5476 | H29: =H25+H27+H28 -> -11905.754 | I29: =I25+I27+I28 -> -8827.7386 | J29: =J25+J27+J28 -> -8088.0755 | ... AL29: =AL25+AL27+AL28 -> 17928.859 | AM29: =SUM(C29:N29) -> -104657.55 | AN29: =SUM(O29:Z29) -> 32875.655 | AO29: =SUM(AA29:AL29) -> 112559.05
A30: Interest / finance costs (EDIT if machines financed) | C30: 0 | D30: 0 | E30: 0 | F30: 0 | G30: 0 | H30: 0 | I30: 0 | J30: 0 | K30: 0 | L30: 0 | M30: 0 | N30: 0 | O30: 0 | P30: 0 | Q30: 0 | R30: 0 | S30: 0 | T30: 0 | U30: 0 | V30: 0 | W30: 0 | X30: 0 | Y30: 0 | Z30: 0 | AA30: 0 | AB30: 0 | AC30: 0 | AD30: 0 | AE30: 0 | AF30: 0 | AG30: 0 | AH30: 0 | AI30: 0 | AJ30: 0 | AK30: 0 | AL30: 0 | AM30: =SUM(C30:N30) -> 0 | AN30: =SUM(O30:Z30) -> 0 | AO30: =SUM(AA30:AL30) -> 0
A31: Profit before tax | C31: =C29+C30 -> -15006.704 | D31: =D29+D30 -> -12947.527 | E31: =E29+E30 -> -11910.008 | F31: =F29+F30 -> -9785.4673 | G31: =G29+G30 -> -8148.5476 | H31: =H29+H30 -> -11905.754 | I31: =I29+I30 -> -8827.7386 | J31: =J29+J30 -> -8088.0755 | ... AL31: =AL29+AL30 -> 17928.859 | AM31: =SUM(C31:N31) -> -104657.55 | AN31: =SUM(O31:Z31) -> 32875.655 | AO31: =SUM(AA31:AL31) -> 112559.05
A32: Corporation tax (monthly ≈ 19% accrual; annual = banded) | C32: =-MAX(0,C31)*Assumptions!$B$46 -> 0 | D32: =-MAX(0,D31)*Assumptions!$B$46 -> 0 | E32: =-MAX(0,E31)*Assumptions!$B$46 -> 0 | F32: =-MAX(0,F31)*Assumptions!$B$46 -> 0 | G32: =-MAX(0,G31)*Assumptions!$B$46 -> 0 | H32: =-MAX(0,H31)*Assumptions!$B$46 -> 0 | I32: =-MAX(0,I31)*Assumptions!$B$46 -> 0 | J32: =-MAX(0,J31)*Assumptions!$B$46 -> 0 | ... AL32: =-MAX(0,AL31)*Assumptions!$B$46 -> -3406.4832 | AM32: =-IF(SUM(C31:N31)<=0,0,IF(SUM(C31:N31)<=Assumptions!$C$46,SUM(C31:N31)*Assumptions!$B$46,IF(SUM(C31:N31)<=Assumptions!$C$47,Assumptions!$C$46*Assumptions!$B$46+(SUM(C31:N31)-Assumptions!$C$46)*Assumptions!$B$47,SUM(C31:N31)*Assumptions!$B$48))) -> 0 | AN32: =-IF(SUM(O31:Z31)<=0,0,IF(SUM(O31:Z31)<=Assumptions!$C$46,SUM(O31:Z31)*Assumptions!$B$46,IF(SUM(O31:Z31)<=Assumptions!$C$47,Assumptions!$C$46*Assumptions!$B$46+(SUM(O31:Z31)-Assumptions!$C$46)*Assumptions!$B$47,SUM(O31:Z31)*Assumptions!$B$48))) -> -6246.3745 | AO32: =-IF(SUM(AA31:AL31)<=0,0,IF(SUM(AA31:AL31)<=Assumptions!$C$46,SUM(AA31:AL31)*Assumptions!$B$46,IF(SUM(AA31:AL31)<=Assumptions!$C$47,Assumptions!$C$46*Assumptions!$B$46+(SUM(AA31:AL31)-Assumptions!$C$46)*Assumptions!$B$47,SUM(AA31:AL31)*Assumptions!$B$48))) -> -26078.147
A33: NET PROFIT | C33: =C31+C32 -> -15006.704 | D33: =D31+D32 -> -12947.527 | E33: =E31+E32 -> -11910.008 | F33: =F31+F32 -> -9785.4673 | G33: =G31+G32 -> -8148.5476 | H33: =H31+H32 -> -11905.754 | I33: =I31+I32 -> -8827.7386 | J33: =J31+J32 -> -8088.0755 | ... AO33: =AO31+AO32 -> 86480.898
A34: Net margin % | C34: =IF(C10=0,0,C33/C10) -> -1.1268884 | D34: =IF(D10=0,0,D33/D10) -> -0.81413075 | E34: =IF(E10=0,0,E33/E10) -> -0.68796176 | F34: =IF(F10=0,0,F33/F10) -> -0.48799879 | G34: =IF(G10=0,0,G33/G10) -> -0.3682692 | H34: =IF(H10=0,0,H33/H10) -> -0.66413721 | I34: =IF(I10=0,0,I33/I10) -> -0.4031645 | J34: =IF(J10=0,0,J33/J10) -> -0.35552339 | ... AL34: =IF(AL10=0,0,AL33/AL10) -> 0.20162486
A36: Practitioner-hours needed (revenue treatments) | C36: =Volumes!C$118 -> 78.2496 | D36: =Volumes!D$118 -> 93.44808 | E36: =Volumes!E$118 -> 101.72448 | F36: =Volumes!F$118 -> 117.82584 | G36: =Volumes!G$118 -> 130.01472 | H36: =Volumes!H$118 -> 126.4032 | I36: =Volumes!I$118 -> 154.39248 | J36: =Volumes!J$118 -> 160.41168 | ... AL36: =Volumes!AL$118 -> 507.87
A37: Practitioner-hours available (headcount + owner) | C37: =(Assumptions!$B$16+1)*Assumptions!$B$21 -> 345 | D37: =(Assumptions!$B$16+1)*Assumptions!$B$21 -> 345 | E37: =(Assumptions!$B$16+1)*Assumptions!$B$21 -> 345 | F37: =(Assumptions!$B$16+1)*Assumptions!$B$21 -> 345 | G37: =(Assumptions!$B$16+1)*Assumptions!$B$21 -> 345 | H37: =(Assumptions!$B$16+1)*Assumptions!$B$21 -> 345 | I37: =(Assumptions!$B$16+1)*Assumptions!$B$21 -> 345 | J37: =(Assumptions!$B$16+1)*Assumptions!$B$21 -> 345 | ... N37: =(Assumptions!$B$16+1)*Assumptions!$B$21 -> 345 | O37: =(Assumptions!$C$16+1)*Assumptions!$B$21 -> 460 | P37: =(Assumptions!$C$16+1)*Assumptions!$B$21 -> 460 | Q37: =(Assumptions!$C$16+1)*Assumptions!$B$21 -> 460 | R37: =(Assumptions!$C$16+1)*Assumptions!$B$21 -> 460 | S37: =(Assumptions!$C$16+1)*Assumptions!$B$21 -> 460 | T37: =(Assumptions!$C$16+1)*Assumptions!$B$21 -> 460 | U37: =(Assumptions!$C$16+1)*Assumptions!$B$21 -> 460 | V37: =(Assumptions!$C$16+1)*Assumptions!$B$21 -> 460 | ... Z37: =(Assumptions!$C$16+1)*Assumptions!$B$21 -> 460 | AA37: =(Assumptions!$E$16+1)*Assumptions!$B$21 -> 690 | AB37: =(Assumptions!$E$16+1)*Assumptions!$B$21 -> 690 | AC37: =(Assumptions!$E$16+1)*Assumptions!$B$21 -> 690 | AD37: =(Assumptions!$E$16+1)*Assumptions!$B$21 -> 690 | AE37: =(Assumptions!$E$16+1)*Assumptions!$B$21 -> 690 | AF37: =(Assumptions!$E$16+1)*Assumptions!$B$21 -> 690 | AG37: =(Assumptions!$E$16+1)*Assumptions!$B$21 -> 690 | AH37: =(Assumptions!$E$16+1)*Assumptions!$B$21 -> 690 | ... AL37: =(Assumptions!$E$16+1)*Assumptions!$B$21 -> 690
A38: CAPACITY CHECK | C38: =IF(C36>C37,"OVER","ok") -> ok | D38: =IF(D36>D37,"OVER","ok") -> ok | E38: =IF(E36>E37,"OVER","ok") -> ok | F38: =IF(F36>F37,"OVER","ok") -> ok | G38: =IF(G36>G37,"OVER","ok") -> ok | H38: =IF(H36>H37,"OVER","ok") -> ok | I38: =IF(I36>I37,"OVER","ok") -> ok | J38: =IF(J36>J37,"OVER","ok") -> ok | ... AL38: =IF(AL36>AL37,"OVER","ok") -> ok

Sheet Data
A1: Raw catalogue extract — audit trail for the Pricing tab
A2: Source: live production database via authenticated admin scrape, 2026-08-28. Prices in pence as stored. costPence is NULL on every variant (no recorded COGS).
A4: Service slug | B4: Service | C4: Category | D4: vatClass (stored) | E4: Service status | F4: Variant | G4: durationMin | H4: displayDurationMin | I4: pricePence | J4: costPence | K4: courses (JSON) | L4: Variant status
A5: lhr-women | B5: Laser Hair Removal — Women | C5: aesthetics | D5: EXEMPT | E5: CONSULTATION | F5: Bikini Line | G5: 20 | H5: 15 | I5: 3500 | K5: [{"sessions": 3, "totalPence": 9600}, {"sessions": 6, "totalPence": 18000}, {"sessions": 10, "totalPence": 28000}]
A6: lhr-women | B6: Laser Hair Removal — Women | C6: aesthetics | D6: EXEMPT | E6: CONSULTATION | F6: Brazilian | G6: 20 | H6: 15 | I6: 4300 | K6: [{"sessions": 3, "totalPence": 12300}, {"sessions": 6, "totalPence": 23400}, {"sessions": 10, "totalPence": 36000}]
A7: lhr-women | B7: Laser Hair Removal — Women | C7: aesthetics | D7: EXEMPT | E7: CONSULTATION | F7: Hollywood Brazilian (incl. Peri-Anal) | G7: 30 | H7: 20 | I7: 5400 | K7: [{"sessions": 3, "totalPence": 14000}, {"sessions": 6, "totalPence": 23400}, {"sessions": 10, "totalPence": 37000}]
A8: lhr-women | B8: Laser Hair Removal — Women | C8: aesthetics | D8: EXEMPT | E8: CONSULTATION | F8: Behind (Peri-Anal) | G8: 20 | H8: 10 | I8: 2600 | K8: [{"sessions": 3, "totalPence": 7100}, {"sessions": 6, "totalPence": 12700}, {"sessions": 10, "totalPence": 18000}]
A9: lhr-women | B9: Laser Hair Removal — Women | C9: aesthetics | D9: EXEMPT | E9: CONSULTATION | F9: Brazilian/Bikini & Underarms | G9: 30 | H9: 20 | I9: 6000 | K9: [{"sessions": 3, "totalPence": 17400}, {"sessions": 6, "totalPence": 33600}, {"sessions": 10, "totalPence": 53000}]
A10: lhr-women | B10: Laser Hair Removal — Women | C10: aesthetics | D10: EXEMPT | E10: CONSULTATION | F10: Hollywood Brazilian (incl. Peri-Anal) & Underarms | G10: 30 | H10: 30 | I10: 6400 | K10: [{"sessions": 3, "totalPence": 18000}, {"sessions": 6, "totalPence": 34200}, {"sessions": 10, "totalPence": 54000}]
A11: lhr-women | B11: Laser Hair Removal — Women | C11: aesthetics | D11: EXEMPT | E11: CONSULTATION | F11: Hollywood Brazilian (incl. Peri-Anal) & Full Legs | G11: 40 | H11: 30 | I11: 11900 | K11: [{"sessions": 3, "totalPence": 34500}, {"sessions": 6, "totalPence": 66000}, {"sessions": 10, "totalPence": 108000}]
A12: lhr-women | B12: Laser Hair Removal — Women | C12: aesthetics | D12: EXEMPT | E12: CONSULTATION | F12: Full Leg & Underarms | G12: 30 | H12: 30 | I12: 11500 | K12: [{"sessions": 3, "totalPence": 33300}, {"sessions": 6, "totalPence": 59400}, {"sessions": 10, "totalPence": 93000}]
A13: lhr-women | B13: Laser Hair Removal — Women | C13: aesthetics | D13: EXEMPT | E13: CONSULTATION | F13: Lower Leg, Brazilian/Bikini & Underarms | G13: 40 | H13: 40 | I13: 9500 | K13: [{"sessions": 3, "totalPence": 25600}, {"sessions": 6, "totalPence": 45600}, {"sessions": 10, "totalPence": 67900}]
A14: lhr-women | B14: Laser Hair Removal — Women | C14: aesthetics | D14: EXEMPT | E14: CONSULTATION | F14: Full Legs, Brazilian/Bikini & Underarms | G14: 50 | H14: 40 | I14: 12100 | K14: [{"sessions": 3, "totalPence": 32800}, {"sessions": 6, "totalPence": 51800}, {"sessions": 10, "totalPence": 79400}]
A15: lhr-women | B15: Laser Hair Removal — Women | C15: aesthetics | D15: EXEMPT | E15: CONSULTATION | F15: Full Legs, Hollywood Brazilian (incl. Peri-Anal) & Underarms | G15: 50 | H15: 50 | I15: 14900 | K15: [{"sessions": 3, "totalPence": 39700}, {"sessions": 6, "totalPence": 65600}, {"sessions": 10, "totalPence": 102400}]
A16: lhr-women | B16: Laser Hair Removal — Women | C16: aesthetics | D16: EXEMPT | E16: CONSULTATION | F16: Eyebrows (middle, above bridge of nose) | G16: 15 | H16: 15 | I16: 1100 | K16: [{"sessions": 3, "totalPence": 3000}, {"sessions": 6, "totalPence": 5400}, {"sessions": 10, "totalPence": 7000}]
... A41: lhr-women | B41: Laser Hair Removal — Women | C41: aesthetics | D41: EXEMPT | E41: CONSULTATION | F41: Full Body | G41: 60 | H41: 60 | I41: 21800 | K41: [{"sessions": 3, "totalPence": 57000}, {"sessions": 6, "totalPence": 82800}, {"sessions": 10, "totalPence": 113900}]
A42: lhr-men | B42: Laser Hair Removal — Men | C42: aesthetics | E42: NORMAL | F42: Centre Brow | G42: 20 | H42: 20 | I42: 1700 | K42: [{"sessions": 3, "totalPence": 4500}, {"sessions": 6, "totalPence": 7200}, {"sessions": 10, "totalPence": 10000}]
A43: lhr-men | B43: Laser Hair Removal — Men | C43: aesthetics | E43: NORMAL | F43: Front of Neck | G43: 20 | H43: 20 | I43: 5700 | K43: [{"sessions": 3, "totalPence": 15900}, {"sessions": 6, "totalPence": 29700}, {"sessions": 10, "totalPence": 44900}]
A44: lhr-men | B44: Laser Hair Removal — Men | C44: aesthetics | E44: NORMAL | F44: Back of Neck | G44: 20 | H44: 20 | I44: 5700 | K44: [{"sessions": 3, "totalPence": 15900}, {"sessions": 6, "totalPence": 29700}, {"sessions": 10, "totalPence": 44900}]
A45: lhr-men | B45: Laser Hair Removal — Men | C45: aesthetics | E45: NORMAL | F45: Full Beard | G45: 30 | H45: 30 | I45: 7500 | K45: [{"sessions": 3, "totalPence": 20700}, {"sessions": 6, "totalPence": 37300}, {"sessions": 10, "totalPence": 58800}]
A46: lhr-men | B46: Laser Hair Removal — Men | C46: aesthetics | E46: NORMAL | F46: Full Beard & Neck | G46: 40 | H46: 40 | I46: 9000 | K46: [{"sessions": 3, "totalPence": 25600}, {"sessions": 6, "totalPence": 44900}, {"sessions": 10, "totalPence": 67900}]
A47: lhr-men | B47: Laser Hair Removal — Men | C47: aesthetics | E47: NORMAL | F47: Underarms | G47: 20 | H47: 20 | I47: 3300 | K47: [{"sessions": 3, "totalPence": 9000}, {"sessions": 6, "totalPence": 15900}, {"sessions": 10, "totalPence": 22900}]
A48: lhr-men | B48: Laser Hair Removal — Men | C48: aesthetics | E48: NORMAL | F48: ½ Arms | G48: 30 | H48: 30 | I48: 9000 | K48: [{"sessions": 3, "totalPence": 24200}, {"sessions": 6, "totalPence": 44200}, {"sessions": 10, "totalPence": 67900}]
A49: lhr-men | B49: Laser Hair Removal — Men | C49: aesthetics | E49: NORMAL | F49: Shoulders | G49: 20 | H49: 20 | I49: 9000 | K49: [{"sessions": 3, "totalPence": 24200}, {"sessions": 6, "totalPence": 44200}, {"sessions": 10, "totalPence": 67900}]
A50: lhr-men | B50: Laser Hair Removal — Men | C50: aesthetics | E50: NORMAL | F50: Lower Back | G50: 30 | H50: 30 | I50: 9000 | K50: [{"sessions": 3, "totalPence": 24200}, {"sessions": 6, "totalPence": 44200}, {"sessions": 10, "totalPence": 67900}]
A51: lhr-men | B51: Laser Hair Removal — Men | C51: aesthetics | E51: NORMAL | F51: Full Arms | G51: 40 | H51: 40 | I51: 10500 | K51: [{"sessions": 3, "totalPence": 29700}, {"sessions": 6, "totalPence": 53900}, {"sessions": 10, "totalPence": 81700}]
A52: lhr-men | B52: Laser Hair Removal — Men | C52: aesthetics | E52: NORMAL | F52: Chest | G52: 25 | H52: 25 | I52: 10500 | K52: [{"sessions": 3, "totalPence": 29700}, {"sessions": 6, "totalPence": 53900}, {"sessions": 10, "totalPence": 81700}]
A53: lhr-men | B53: Laser Hair Removal — Men | C53: aesthetics | E53: NORMAL | F53: Stomach | G53: 25 | H53: 25 | I53: 10500 | K53: [{"sessions": 3, "totalPence": 29700}, {"sessions": 6, "totalPence": 53900}, {"sessions": 10, "totalPence": 81700}]
... A64: lhr-men | B64: Laser Hair Removal — Men | C64: aesthetics | E64: NORMAL | F64: Full Legs | G64: 60 | H64: 60 | I64: 14700 | K64: [{"sessions": 3, "totalPence": 41800}, {"sessions": 6, "totalPence": 77300}, {"sessions": 10, "totalPence": 113900}]
A65: intimate-rejuvenation | B65: Intimate Rejuvenation | C65: aesthetics | E65: COMING_SOON | F65: CO2 Laser Rejuvenation | G65: 40 | I65: 69000 | K65: [{"sessions": 3, "totalPence": 189000}, {"sessions": 6, "totalPence": 342000}]
A66: intimate-rejuvenation | B66: Intimate Rejuvenation | C66: aesthetics | E66: COMING_SOON | F66: Intimate Area Whitening | G66: 40 | I66: 69000 | K66: [{"sessions": 3, "totalPence": 189000}]
A67: laser-pigmentation | B67: Laser Pigmentation Removal | C67: aesthetics | E67: NORMAL | F67: laser pigmentation Face | G67: 30 | H67: 30 | I67: 15000 | K67: [{"sessions": 3, "totalPence": 40500}, {"sessions": 5, "totalPence": 60000}]
A68: vascular-lesions | B68: Vascular Lesions Treatment | C68: aesthetics | E68: NORMAL | F68: Face | G68: 30 | H68: 30 | I68: 15000 | K68: [{"sessions": 3, "totalPence": 40500}, {"sessions": 5, "totalPence": 60000}]
A69: spider-veins | B69: Spider Veins Removal | C69: aesthetics | E69: CONSULTATION | F69: Nose Thread Vein | G69: 25 | H69: 30 | I69: 23000 | K69: [{"sessions": 2, "totalPence": 41600}]
A70: spider-veins | B70: Spider Veins Removal | C70: aesthetics | E70: CONSULTATION | F70: Cheek Thread Vein | G70: 30 | H70: 30 | I70: 29600 | K70: [{"sessions": 2, "totalPence": 53700}]
A71: spider-veins | B71: Spider Veins Removal | C71: aesthetics | E71: CONSULTATION | F71: Leg Thread Vein | G71: 40 | H71: 40 | I71: 41700 | K71: [{"sessions": 2, "totalPence": 80100}, {"sessions": 3, "totalPence": 114900}]
A72: carbon-laser-peel | B72: Carbon Laser Facial (Hollywood Peel) | C72: aesthetics | E72: INACTIVE (service.active=false, stored status NORMAL) | F72: Neck | G72: 30 | I72: 9000 | K72: [{"sessions": 3, "totalPence": 25600}, {"sessions": 6, "totalPence": 47900}]
A73: carbon-laser-peel | B73: Carbon Laser Facial (Hollywood Peel) | C73: aesthetics | E73: INACTIVE (service.active=false, stored status NORMAL) | F73: Full Face | G73: 50 | I73: 12100 | K73: [{"sessions": 3, "totalPence": 33100}, {"sessions": 6, "totalPence": 59900}]
A74: carbon-laser-peel | B74: Carbon Laser Facial (Hollywood Peel) | C74: aesthetics | E74: INACTIVE (service.active=false, stored status NORMAL) | F74: Face & Neck | G74: 60 | I74: 20500 | K74: [{"sessions": 3, "totalPence": 55200}, {"sessions": 6, "totalPence": 97700}]
A75: carbon-laser-peel | B75: Carbon Laser Facial (Hollywood Peel) | C75: aesthetics | E75: INACTIVE (service.active=false, stored status NORMAL) | F75: Face, Neck & Décolleté | G75: 70 | I75: 23700 | K75: [{"sessions": 3, "totalPence": 62400}, {"sessions": 6, "totalPence": 112200}]
A76: fungal-nail | B76: Laser Fungal Nail Treatment | C76: aesthetics | E76: COMING_SOON | F76: 1 Foot | G76: 30 | I76: 7900 | K76: [{"sessions": 6, "totalPence": 37200}, {"sessions": 10, "totalPence": 51500}]
A77: fungal-nail | B77: Laser Fungal Nail Treatment | C77: aesthetics | E77: COMING_SOON | F77: 2 Feet | G77: 40 | I77: 10000 | K77: [{"sessions": 6, "totalPence": 49800}, {"sessions": 10, "totalPence": 62000}]
A78: laser-tattoo-removal | B78: Laser Tattoo Removal | C78: aesthetics | E78: COMING_SOON | F78: Very Small (1–3 cm) | G78: 20 | I78: 4400 | K78: [{"sessions": 6, "totalPence": 24500}, {"sessions": 10, "totalPence": 38500}]
A79: laser-tattoo-removal | B79: Laser Tattoo Removal | C79: aesthetics | E79: COMING_SOON | F79: Small (4–6 cm) | G79: 20 | I79: 6600 | K79: [{"sessions": 6, "totalPence": 24500}, {"sessions": 10, "totalPence": 38500}]
A80: laser-tattoo-removal | B80: Laser Tattoo Removal | C80: aesthetics | E80: COMING_SOON | F80: Medium (7–15 cm) | G80: 25 | I80: 11600 | K80: [{"sessions": 6, "totalPence": 62700}, {"sessions": 10, "totalPence": 93500}]
A81: laser-tattoo-removal | B81: Laser Tattoo Removal | C81: aesthetics | E81: COMING_SOON | F81: Large (16–20 cm) | G81: 35 | I81: 16500 | K81: [{"sessions": 6, "totalPence": 95700}, {"sessions": 10, "totalPence": 148500}]
A82: laser-tattoo-removal | B82: Laser Tattoo Removal | C82: aesthetics | E82: COMING_SOON | F82: X-Large (21 cm+) | G82: 45 | I82: 23700 | K82: [{"sessions": 6, "totalPence": 131400}, {"sessions": 10, "totalPence": 203500}]
A83: pmu-removal | B83: Permanent Make-Up Removal | C83: aesthetics | E83: COMING_SOON | F83: Eyebrows | G83: 30 | I83: 27500 | K83: [{"sessions": 4, "totalPence": 106000}, {"sessions": 6, "totalPence": 153000}]
A84: hydrafacial | B84: HydraFacial | C84: aesthetics | E84: NORMAL | F84: Signature Express (30 min) | G84: 45 | H84: 30 | I84: 9500 | K84: [{"sessions": 3, "totalPence": 26700}, {"sessions": 6, "totalPence": 47400}]
A85: hydrafacial | B85: HydraFacial | C85: aesthetics | E85: NORMAL | F85: Full Face Deluxe (50 min) | G85: 60 | H85: 50 | I85: 14500 | K85: [{"sessions": 3, "totalPence": 39900}, {"sessions": 6, "totalPence": 70800}]
A86: hydrafacial | B86: HydraFacial | C86: aesthetics | E86: NORMAL | F86: Platinum — Anti-Acne (60 min) | G86: 70 | H86: 60 | I86: 18500 | K86: [{"sessions": 3, "totalPence": 51900}, {"sessions": 6, "totalPence": 94800}]
A87: hydrafacial | B87: HydraFacial | C87: aesthetics | E87: NORMAL | F87: Platinum — Collagen (60 min) | G87: 70 | H87: 60 | I87: 18500 | K87: [{"sessions": 3, "totalPence": 51900}, {"sessions": 6, "totalPence": 94800}]
A88: hydrafacial | B88: HydraFacial | C88: aesthetics | E88: NORMAL | F88: Platinum — Pigmentation & Sun Damage (60 min) | G88: 70 | H88: 60 | I88: 18500 | K88: [{"sessions": 3, "totalPence": 51900}, {"sessions": 6, "totalPence": 94800}]
A89: hydrafacial | B89: HydraFacial | C89: aesthetics | E89: NORMAL | F89: Platinum — Anti-Ageing (60 min) | G89: 70 | H89: 60 | I89: 18500 | K89: [{"sessions": 3, "totalPence": 51900}, {"sessions": 6, "totalPence": 94800}]
A90: hydrafacial | B90: HydraFacial | C90: aesthetics | E90: NORMAL | F90: Platinum — Brightening (60 min) | G90: 70 | H90: 60 | I90: 18500 | K90: [{"sessions": 3, "totalPence": 51900}, {"sessions": 6, "totalPence": 94800}]
A91: smas-hifu | B91: SMAS HIFU Lifting | C91: aesthetics | E91: NORMAL | F91: Eyebrow Lift | G91: 30 | H91: 30 | I91: 34900 | K91: [{"sessions": 3, "totalPence": 97500}]
A92: smas-hifu | B92: SMAS HIFU Lifting | C92: aesthetics | E92: NORMAL | F92: Forehead Lift | G92: 30 | H92: 30 | I92: 34900 | K92: [{"sessions": 3, "totalPence": 97500}]
A93: smas-hifu | B93: SMAS HIFU Lifting | C93: aesthetics | E93: NORMAL | F93: Neck Lift | G93: 40 | H93: 40 | I93: 34900 | K93: [{"sessions": 3, "totalPence": 97500}]
A94: smas-hifu | B94: SMAS HIFU Lifting | C94: aesthetics | E94: NORMAL | F94: Jawline Lift | G94: 40 | H94: 40 | I94: 39900 | K94: [{"sessions": 3, "totalPence": 112500}]
A95: smas-hifu | B95: SMAS HIFU Lifting | C95: aesthetics | E95: NORMAL | F95: Full Face | G95: 60 | H95: 60 | I95: 47900 | K95: [{"sessions": 3, "totalPence": 130500}]
... A104: cosmetic-peels | B104: Cosmetic Peels | C104: aesthetics | E104: NORMAL | F104: Full Face | G104: 60 | H104: 60 | I104: 12500 | K104: [{"sessions": 3, "totalPence": 32000}]
A105: fat-dissolving | B105: Fat-Dissolving Injections | C105: aesthetics | E105: NORMAL | F105: Small Area (under chin) | G105: 30 | H105: 30 | I105: 14500
A106: fat-dissolving | B106: Fat-Dissolving Injections | C106: aesthetics | E106: NORMAL | F106: Medium Area (Stomach, Bingo Wings, Knees) | G106: 30 | H106: 30 | I106: 22500
A107: fat-dissolving | B107: Fat-Dissolving Injections | C107: aesthetics | E107: NORMAL | F107: Large Area (Things, Waist, Stomach) | G107: 30 | H107: 30 | I107: 29000
A108: rf-lifting | B108: RF Lifting | C108: aesthetics | E108: NORMAL | F108: RF Lifting | G108: 60 | H108: 60 | I108: 26000 | K108: [{"sessions": 3, "totalPence": 69000}, {"sessions": 5, "totalPence": 107500}]
A109: ipl-phototherapy | B109: IPL Phototherapy | C109: aesthetics | E109: NORMAL | F109: Face | G109: 30 | H109: 30 | I109: 15000 | K109: [{"sessions": 3, "totalPence": 40500}, {"sessions": 5, "totalPence": 60000}]
A110: ipl-phototherapy | B110: IPL Phototherapy | C110: aesthetics | E110: NORMAL | F110: Face & Neck | G110: 30 | H110: 30 | I110: 21000 | K110: [{"sessions": 3, "totalPence": 57000}, {"sessions": 5, "totalPence": 85000}]
A111: laser-skin-rejuvenation | B111: Laser Skin Rejuvenation | C111: aesthetics | E111: NORMAL | F111: Face & Neck | G111: 45 | H111: 45 | I111: 21000 | K111: [{"sessions": 3, "totalPence": 57000}, {"sessions": 5, "totalPence": 85000}] | L111: NORMAL
A112: laser-skin-rejuvenation | B112: Laser Skin Rejuvenation | C112: aesthetics | E112: NORMAL | F112: Face | G112: 40 | H112: 40 | I112: 15000 | K112: [{"sessions": 3, "totalPence": 40500}, {"sessions": 5, "totalPence": 60000}] | L112: NORMAL
